Workbook

Sheet 相关性复核
A1: ﻿query_id | B1: query_text | C1: language | D1: product_class | E1: query_type | F1: split | G1: candidate_scene_id | H1: record_id | I1: scene_start_time | J1: scene_end_time | K1: media_relative_path | L1: thumbnail_relative_path | M1: scene_text | N1: blind_order | O1: ai_relevance_grade | P1: ai_start_time | Q1: ai_end_time | R1: ai_evidence | S1: ai_evidence_sources | T1: ai_uncertainty | U1: ai_uncertainty_reason | V1: reviewer_id | W1: r1_relevance_grade | X1: r1_start_time | Y1: r1_end_time | Z1: r1_source_leakage | AA1: r1_evidence_notes | AB1: correction_reason | AC1: review_status | AD1: reviewed_at | AE1: grade_changed | AF1: time_changed | AG1: qc_status
A2: VQ-001 | B2: 空气炸锅怎样设置烹饪温度和时间？ | C2: zh-CN | D2: Air Fryer | E2: operation | F2: development | G2: airfryer-005-scene-0021 | H2: airfryer-005 | I2: 202.502 | J2: 207.465 | K2: items/airfryer-005-scene-0021/clip.mp4 | L2: items/airfryer-005-scene-0021/thumbnail.jpg | M2: ASR: air fryer, the basket goes and then we set the temperature VLM: Visual summary: A person is placing an air fryer basket containing food into an air fryer appliance on a white countertop. 视觉摘要: 一个人将装有食物的空气炸锅篮子放入空气炸锅中，置于白色台面上。 Visible product: Air Fryer Visible components: air fryer basket; air fryer appliance; white countertop; white cutting board; glass bowl; eggshells Visible actions: placing air fryer basket into air fryer appliance | N2: 1 | O2: 1 | R2: ASR mentions setting temperature after placing the basket, but no actual temperature or time setting is shown or spoken; VLM only shows placing the basket, not configuring settings. | S2: ASR|VLM | T2: low | U2: No visible or spoken evidence of temperature or time setting; only placement of basket is shown. | V2: R1 | W2: 1 | Z2: no | AA2: 画面显示将含食物的炸篮放入空气炸锅，未出现温度/时间旋钮或触控设置过程，ASR 仅提到'we set the temperature'但未给出具体数值或操作方法，无法回答如何设置。 | AC2: completed | AD2: 2026-07-27T22:01:34+08:00 | AE2: =IF(AC2<>"completed","",IF(W2=O2,"no","yes")) | AF2: =IF(AC2<>"completed","",IF(AND(X2=P2,Y2=Q2),"no","yes")) | AG2: =IF(AC2<>"completed","待复核",IF(OR(W2="",Z2="",AA2="",AD2=""),"缺少必填项",IF(AND(OR(AE2="yes",AF2="yes"),AB2=""),"修正原因缺失",IF(OR(W2=0,W2=1),IF(AND(X2="",Y2=""),"通过","0/1级时间应留空"),IF(AND(OR(W2=2,W2=3),X2<>"",Y2<>"",X2>=I2,Y2<=J2,Y2>X2),"通过","2/3级时间无效")))))
A3: VQ-001 | B3: 空气炸锅怎样设置烹饪温度和时间？ | C3: zh-CN | D3: Air Fryer | E3: operation | F3: development | G3: pressure-006-scene-0005 | H3: pressure-006 | I3: 15.083 | J3: 17.625 | K3: items/pressure-006-scene-0005/clip.mp4 | L3: items/pressure-006-scene-0005/thumbnail.jpg | M3: ASR: • Touch screen control, LCD display, visual window, cooking process at a glance VLM: Visual summary: A close-up of a yellow and black air fryer with a digital display and touch controls, showing food inside the basket. 视觉摘要: 一台黄黑相间的空气炸锅特写，配有数字显示屏和触控按钮，锅内可见食物。 Visible product: Air Fryer Visible components: digital display; touch controls; food inside basket; yellow and black casing | N3: 2 | O3: 1 | R3: The scene shows an air fryer with a digital display and touch controls, indicating it has a user interface for setting temperature and time, but no specific settings or actions are shown or described. | S3: VLM|ASR | T3: low | U3: No actual temperature or time setting is demonstrated or described in the evidence. | V3: R1 | W3: 1 | Z3: no | AA3: 画面展示空气炸锅触控/LCD面板与'880'显示，但未出现设置温度、时间的具体操作或数值，无法回答如何设置。 | AC3: completed | AD3: 2026-07-27T22:01:34+08:00 | AE3: =IF(AC3<>"completed","",IF(W3=O3,"no","yes")) | AF3: =IF(AC3<>"completed","",IF(AND(X3=P3,Y3=Q3),"no","yes")) | AG3: =IF(AC3<>"completed","待复核",IF(OR(W3="",Z3="",AA3="",AD3=""),"缺少必填项",IF(AND(OR(AE3="yes",AF3="yes"),AB3=""),"修正原因缺失",IF(OR(W3=0,W3=1),IF(AND(X3="",Y3=""),"通过","0/1级时间应留空"),IF(AND(OR(W3=2,W3=3),X3<>"",Y3<>"",X3>=I3,Y3<=J3,Y3>X3),"通过","2/3级时间无效")))))
A4: VQ-001 | B4: 空气炸锅怎样设置烹饪温度和时间？ | C4: zh-CN | D4: Air Fryer | E4: operation | F4: development | G4: airfryer-011-scene-0001 | H4: airfryer-011 | I4: 0.0 | J4: 107.95 | K4: items/airfryer-011-scene-0001/clip.mp4 | L4: items/airfryer-011-scene-0001/thumbnail.jpg | M4: ASR: Hi, welcome back to Montana, and today we're going to be making another one of my favorite air fryer recipes, grilled cheese. The ingredients are white bread, salted butter, sharp cheddar cheese, and Italian blend cheese. Your first step is to add some of your cheddar into the middle of your bread, and then sprinkle some Italian blend on top. Then butter the exterior of your bread. Put your grilled cheese inside of your air fryer, and then cook for four minutes. Now flip it over and then cook for another three minutes. Now that the three minutes is up, take it out of the air fryer, cut it, and give it a try. OCR: That's Good! WITH MONTANA MONTEREY play! RECREATION NG 5<S HONTEREY BINGA ISUR VF 2000 CA QUAS IONTEREY DECREATION BINCNAE 1SUS VIV ). 2021 ONTREY DECRATION DA REC ONTEREY ECREATION /V 20MON REC MONNEY A RECR TION 202 252 MO DA RE 1S8V 2120 BREC 2n2 MON MONTREYY DA Air Fryer Grilled Cheese 2 slices white bread Sharp Cheddar & Italian Blend Cheeses Salted butter X #showushowyouplayMonterey VLM: Visual summary: A young man in a kitchen prepares to make a grilled cheese sandwich using an air fryer. 视觉摘要: 一名年轻男子在厨房里准备使用空气炸锅制作烤奶酪三明治。 Visible product: Air Fryer Visible components: air fryer; refrigerator; wooden cabinets; countertop; knife block; coffee maker; glass jars; mug; red cutting board; bread; apron Visible actions: man standing; man handling bread | N4: 3 | O4: 3 | P4: 47.0 | Q4: 51.0 | R4: cook for four minutes. Now flip it over and then cook for another three minutes. | S4: ASR | T4: low | U4: The ASR text clearly specifies cooking times (4 minutes, then 3 minutes) and is directly tied to the air fryer operation, matching the question's request for temperature and time settings. | V4: R1 | W4: 3 | X4: 47 | Y4: 65 | Z4: no | AA4: 画面显示烤制奶酪三明治的流程，64.7s帧将三明治放入空气炸锅；ASR 中明确提到'cook for four minutes... cook for another three minutes'，语音直接给出了烹饪时间，能回答问题。 | AB4: 复核扩展时间区间至 47-65s，以覆盖证据中 64.7s 将三明治放入空气炸锅的关键帧（原 47-51s 范围偏窄，未含该帧）。 | AC4: completed | AD4: 2026-07-28T13:42:36+08:00 | AE4: =IF(AC4<>"completed","",IF(W4=O4,"no","yes")) | AF4: =IF(AC4<>"completed","",IF(AND(X4=P4,Y4=Q4),"no","yes")) | AG4: =IF(AC4<>"completed","待复核",IF(OR(W4="",Z4="",AA4="",AD4=""),"缺少必填项",IF(AND(OR(AE4="yes",AF4="yes"),AB4=""),"修正原因缺失",IF(OR(W4=0,W4=1),IF(AND(X4="",Y4=""),"通过","0/1级时间应留空"),IF(AND(OR(W4=2,W4=3),X4<>"",Y4<>"",X4>=I4,Y4<=J4,Y4>X4),"通过","2/3级时间无效")))))
A5: VQ-001 | B5: 空气炸锅怎样设置烹饪温度和时间？ | C5: zh-CN | D5: Air Fryer | E5: operation | F5: development | G5: airfryer-029-scene-0066 | H5: airfryer-029 | I5: 403.92 | J5: 405.96 | K5: items/airfryer-029-scene-0066/clip.mp4 | L5: items/airfryer-029-scene-0066/thumbnail.jpg | M5: ASR: also the chicken will be cooked perfectly. This awesome-looking Philips OCR: Philips SUPER CHEF VLM: Visual summary: A close-up of a black Philips air fryer showing its temperature dial and timer dial. 视觉摘要: 一台黑色飞利浦空气炸锅的特写，显示其温度旋钮和计时旋钮。 Visible product: Philips Visible components: temperature dial; timer dial; brand logo; control knobs | N5: 4 | O5: 2 | P5: 403.92 | Q5: 405.96 | R5: The scene shows the temperature and timer dials on a Philips air fryer, visually indicating where temperature and time settings can be adjusted, though no actual setting values or instructions are provided. | S5: VLM|ASR|OCR | T5: low | U5: No spoken or visual instruction on how to set temperature and time is given; only the controls are shown. | V5: R1 | W5: 2 | X5: 403.92 | Y5: 405.96 | Z5: no | AA5: 画面为飞利浦空气炸锅顶部特写，可见温度/时间机械旋钮及刻度（约404.3s），直接展示了设置温度/时间的控制部件，但未演示具体调节过程，属于部分回答。 | AC5: completed | AD5: 2026-07-27T22:01:34+08:00 | AE5: =IF(AC5<>"completed","",IF(W5=O5,"no","yes")) | AF5: =IF(AC5<>"completed","",IF(AND(X5=P5,Y5=Q5),"no","yes")) | AG5: =IF(AC5<>"completed","待复核",IF(OR(W5="",Z5="",AA5="",AD5=""),"缺少必填项",IF(AND(OR(AE5="yes",AF5="yes"),AB5=""),"修正原因缺失",IF(OR(W5=0,W5=1),IF(AND(X5="",Y5=""),"通过","0/1级时间应留空"),IF(AND(OR(W5=2,W5=3),X5<>"",Y5<>"",X5>=I5,Y5<=J5,Y5>X5),"通过","2/3级时间无效")))))
A6: VQ-001 | B6: 空气炸锅怎样设置烹饪温度和时间？ | C6: zh-CN | D6: Air Fryer | E6: operation | F6: development | G6: airfryer-005-scene-0022 | H6: airfryer-005 | I6: 207.465 | J6: 227.314 | K6: items/airfryer-005-scene-0022/clip.mp4 | L6: items/airfryer-005-scene-0022/thumbnail.jpg | M6: ASR: air fryer, the basket goes and then we set the temperature to 350 Fahrenheit and then we just turn it on for 10 minutes and that's it and let it do its thing. And when the timer goes off, you can take it out and look VLM: Visual summary: A man in a kitchen stands behind a black air fryer on a countertop, gesturing and speaking to the camera. 视觉摘要: 一名男子站在厨房的台面上，身后放着一台黑色空气炸锅，他正对着镜头做手势说话。 Visible product: Air Fryer Visible components: black air fryer; stainless steel refrigerator; white kitchen cabinets; glass jars; knife block; paper towel holder; whey protein container; blue funnel Visible actions: man gesturing with hands; man speaking | N6: 5 | O6: 3 | P6: 207.465 | Q6: 227.314 | R6: ASR explicitly states setting temperature to 350 Fahrenheit and timer to 10 minutes, which directly answers the question about air fryer temperature and time settings. | S6: ASR|VLM | T6: low | U6: The ASR provides complete, unambiguous instructions for temperature and time settings, and the VLM confirms the product is an air fryer. | V6: R1 | W6: 3 | X6: 207.465 | Y6: 227.314 | Z6: no | AA6: 画面中一位男士站在空气炸锅前讲解并打开/指向机身；ASR 明确说'set the temperature to 350 Fahrenheit and then we just turn it on for 10 minutes'，语音直接给出了温度与时间的设置，能回答问题。 | AC6: completed | AD6: 2026-07-27T22:01:40+08:00 | AE6: =IF(AC6<>"completed","",IF(W6=O6,"no","yes")) | AF6: =IF(AC6<>"completed","",IF(AND(X6=P6,Y6=Q6),"no","yes")) | AG6: =IF(AC6<>"completed","待复核",IF(OR(W6="",Z6="",AA6="",AD6=""),"缺少必填项",IF(AND(OR(AE6="yes",AF6="yes"),AB6=""),"修正原因缺失",IF(OR(W6=0,W6=1),IF(AND(X6="",Y6=""),"通过","0/1级时间应留空"),IF(AND(OR(W6=2,W6=3),X6<>"",Y6<>"",X6>=I6,Y6<=J6,Y6>X6),"通过","2/3级时间无效")))))
A7: VQ-001 | B7: 空气炸锅怎样设置烹饪温度和时间？ | C7: zh-CN | D7: Air Fryer | E7: operation | F7: development | G7: airfryer-027-scene-0002 | H7: airfryer-027 | I7: 7.508 | J7: 283.4 | K7: items/airfryer-027-scene-0002/clip.mp4 | L7: items/airfryer-027-scene-0002/thumbnail.jpg | M7: ASR: Okay, so first we coat the wings with baking powder, some kosher salt, and a little bit of garlic powder. And we're going to preheat the oven to 450 degrees. So after 25 minutes, we're going to take these, flip them over. And of course, with the traditional version of the oven, we're going to provide some Frank's Red Hot Sauce. real deal butter and a touch of brown sugar and that's what we're gonna of course toss our wings into and for the other wings we're going to use McCormick's air fryer buffalo wings and it supposedly has some kind of authentic Frank's red hot sauce obviously dehydrated powder and we're going to cover these and of course this takes about half the time of the oven-cooked ones and we got our air-fried version here toss with oil and the seasoning the cormac seasoning we're going to throw these babies in here doesn't seem to really cope very well honestly but turn a reminder whoops 20 20 minutes, see what happens. Okay, so here we are. There are two different versions of so-called buffalo wings. On the top we have the oven-baked version, the real Frank's hot sauce, and on the bottom we have the McCormick air fryer version. See, they look completely different. So let's try the oven-baked version first. Nothing like that real French hot sauce with butter or brown sugar. Mmm, very good. A little bit dry, but that's because these are small wings. I would have cooked them a little bit less than 50 minutes, maybe 40 minutes. Not bad. Okay, let's try the air fryer wings. Here we go. Now, in this case, I'm definitely going to dip these in a little bit of ranch dressing here. Let's check it out. Whoops. It's actually not bad. Very tasty. And since it's air fried, it's more, it seems to be evenly cooked. So for all you Buffalo Wing fans out there, the reality is the best Buffalo Wings are deep fried in a deep fryer just like they were when I grew up in Buffalo in the 1970s and tossed in Frank's hot sauce with a bit of butter and as much sugar as you want so sorry health food fans but honestly the air fryer and baked versions they're okay it tastes good but it's not like the original. OCR: WRONRSSH and bake for another 20 minutes OVEN READY McCormick AIR FRYER Buffalo RedHot m AIR FRYER FRANK: NO ARTIFICIAL FLAYORS Esenti MCCORNICE SPICES NO ARTIRICIAL FLAPORS VEN EADY ER Talo table Oil TART courmia Gourmia 3808 * courmia. GOr START 89:39 VLM: Visual summary: Chicken wings are shown cooking on a wire rack over aluminum foil on a stovetop, then plated with a dipping sauce. 视觉摘要: 鸡翅在炉灶上的烤架上烹饪，然后盛放在盘子中，配有一份蘸酱。 Visible product: Air Fryer Visible components: stovetop; gas burner grates; wire rack; aluminum foil; plate; glass cup; black and white checkered tablecloth Visible actions: chicken wings are cooking; a man is speaking to the camera Visible states: chicken wings are cooked and golden brown; dipping sauce is on the plate Visual uncertainty: The specific product being referred to as 'Air Fryer' is not visible in the frames. | N7: 6 | O7: 2 | P7: 27.508 | Q7: 283.4 | R7: ASR mentions '20 minutes' for air fryer cooking time and OCR shows 'AIR FRYER' and 'START' with visible product context, indicating a cooking time setting is implied for the air fryer, though no explicit temperature setting is provided. | S7: ASR|OCR | T7: medium | U7: The ASR mentions a time ('20 minutes') but not a temperature for the air fryer, and OCR does not specify a temperature value, only product context. | V7: R1 | W7: 2 | X7: 110.0 | Y7: 130.0 | Z7: no | AA7: 长视频主要是烤箱烤鸡翅流程，但 117.9s 帧可见空气炸锅显示屏'1934'，说明设备在运行并设有温度时间，但未明确解释如何设置，只能部分回答。 | AB7: 时间按画面中可见的空气炸锅显示区收窄至 t≈110-130s。 | AC7: completed | AD7: 2026-07-27T22:01:40+08:00 | AE7: =IF(AC7<>"completed","",IF(W7=O7,"no","yes")) | AF7: =IF(AC7<>"completed","",IF(AND(X7=P7,Y7=Q7),"no","yes")) | AG7: =IF(AC7<>"completed","待复核",IF(OR(W7="",Z7="",AA7="",AD7=""),"缺少必填项",IF(AND(OR(AE7="yes",AF7="yes"),AB7=""),"修正原因缺失",IF(OR(W7=0,W7=1),IF(AND(X7="",Y7=""),"通过","0/1级时间应留空"),IF(AND(OR(W7=2,W7=3),X7<>"",Y7<>"",X7>=I7,Y7<=J7,Y7>X7),"通过","2/3级时间无效")))))
A8: VQ-001 | B8: 空气炸锅怎样设置烹饪温度和时间？ | C8: zh-CN | D8: Air Fryer | E8: operation | F8: development | G8: airfryer-029-scene-0055 | H8: airfryer-029 | I8: 324.32 | J8: 326.44 | K8: items/airfryer-029-scene-0055/clip.mp4 | L8: items/airfryer-029-scene-0055/thumbnail.jpg | M8: ASR: degree centigrade for around 10 minutes using Philips air fryer anybody can cook OCR: PHILIPS SUPER CHEF VLM: Visual summary: A close-up of a black Philips air fryer showing its control dial and cooking guide label. 视觉摘要: 一台黑色飞利浦空气炸锅的特写，显示其控制旋钮和烹饪指南标签。 Visible product: Air Fryer Visible components: control dial; brand name 'PHILIPS'; cooking guide label with temperature and time icons; temperature indicator (200°C) | N8: 7 | O8: 2 | P8: 324.32 | Q8: 326.44 | R8: The visual shows the control dial and temperature indicator (200°C), and ASR mentions setting temperature and time (e.g., 10 minutes), indicating adjacent steps for operation, but no explicit step-by-step instruction is shown or spoken. | S8: VLM|ASR|OCR | T8: low | U8: No explicit step-by-step instruction for setting temperature and time is provided, but the visual and ASR context imply the capability to set these parameters. | V8: R1 | W8: 3 | X8: 324.32 | Y8: 326.44 | Z8: no | AA8: 画面中清晰展示手指旋转飞利浦空气炸锅的温度/时间旋钮，并可见烹饪指南图标（含温度、时间、食材图标），直接演示了如何设置温度和时间。 | AB8: AI预标2级，但画面直接展示旋钮设置动作，能直接回答问题，修正为3级。 | AC8: completed | AD8: 2026-07-27T22:01:40+08:00 | AE8: =IF(AC8<>"completed","",IF(W8=O8,"no","yes")) | AF8: =IF(AC8<>"completed","",IF(AND(X8=P8,Y8=Q8),"no","yes")) | AG8: =IF(AC8<>"completed","待复核",IF(OR(W8="",Z8="",AA8="",AD8=""),"缺少必填项",IF(AND(OR(AE8="yes",AF8="yes"),AB8=""),"修正原因缺失",IF(OR(W8=0,W8=1),IF(AND(X8="",Y8=""),"通过","0/1级时间应留空"),IF(AND(OR(W8=2,W8=3),X8<>"",Y8<>"",X8>=I8,Y8<=J8,Y8>X8),"通过","2/3级时间无效")))))
A9: VQ-001 | B9: 空气炸锅怎样设置烹饪温度和时间？ | C9: zh-CN | D9: Air Fryer | E9: operation | F9: development | G9: airfryer-017-scene-0101 | H9: airfryer-017 | I9: 1370.736 | J9: 1398.664 | K9: items/airfryer-017-scene-0101/clip.mp4 | L9: items/airfryer-017-scene-0101/thumbnail.jpg | M9: ASR: Now I'm going to do something. I don't know if this is safe, so don't try this at home, but before I reassemble this entire unit, I'm going to take my two power cords. I'm gonna plug them back into my switch and I'm gonna plug the unit back into the wall See if I can power this thing on just to make sure it's working before I spend all the time to screw everything back together And moment of truth as power it's giving me an e1 message, but I already know what it means It means that I forgot to plug the thermistor back into the circuit panel OCR: 3 11 UNIT APROFESSIONA 18 I'M NOT DON'T TRY THIS AT HOMI COUNT 19 VLM: Visual summary: A disassembled black appliance, labeled as an air fryer, is on a table with a person's hand interacting with its internal wiring and components. Tools and paper are scattered around. 视觉摘要: 一台被拆开的黑色空气炸锅放在桌子上，一个人的手正在操作其内部的电线和部件，周围散落着工具和纸张。 Visible product: Air Fryer Visible components: black appliance chassis; internal wiring; small circuit board; fan; control panel; screwdriver; pliers; paper; cardboard box Visible actions: hand holding wires; hand manipulating a wire connector Visible states: appliance disassembled; control panel lit with blue display Visible warnings: I'M NOT A PROFESSIONAL. DON'T TRY THIS AT HOME. | N9: 8 | O9: 0 | R9: The scene shows a disassembled air fryer with internal wiring and a control panel lit, but no visible or spoken content about setting temperature or time. The ASR discusses troubleshooting an error message and reassembling the unit, not operation settings. The OCR includes a warning and partial text unrelated to cooking settings. | S9: VLM|ASR|OCR | T9: low | U9: No evidence of temperature or time setting actions or instructions visible or audible in the scene. | V9: R1 | W9: 0 | Z9: no | AA9: 画面为拆解中的空气炸锅内部线路与控制板，与设置温度/时间无关。 | AC9: completed | AD9: 2026-07-27T22:01:40+08:00 | AE9: =IF(AC9<>"completed","",IF(W9=O9,"no","yes")) | AF9: =IF(AC9<>"completed","",IF(AND(X9=P9,Y9=Q9),"no","yes")) | AG9: =IF(AC9<>"completed","待复核",IF(OR(W9="",Z9="",AA9="",AD9=""),"缺少必填项",IF(AND(OR(AE9="yes",AF9="yes"),AB9=""),"修正原因缺失",IF(OR(W9=0,W9=1),IF(AND(X9="",Y9=""),"通过","0/1级时间应留空"),IF(AND(OR(W9=2,W9=3),X9<>"",Y9<>"",X9>=I9,Y9<=J9,Y9>X9),"通过","2/3级时间无效")))))
A10: VQ-001 | B10: 空气炸锅怎样设置烹饪温度和时间？ | C10: zh-CN | D10: Air Fryer | E10: operation | F10: development | G10: airfryer-002-scene-0001 | H10: airfryer-002 | I10: 0.0 | J10: 11.044 | K10: items/airfryer-002-scene-0001/clip.mp4 | L10: items/airfryer-002-scene-0001/thumbnail.jpg | M10: OCR: The Library Kitchen Lärary Kiehen Air I Fryer Oreos www.gloucesterva.info/publiclibrary Chef Library Kitchen Puff Pastry SHEETS OREO VLM: Visual summary: Three powdered pastries are on a white plate with a fork, overlaid with text identifying the content as 'The Library Kitchen' and 'Air Fryer Oreos'. 视觉摘要: 白色盘子上有三个撒了粉的糕点，旁边放着一把叉子，叠加的文字显示内容为“图书馆厨房”和“空气炸锅奥利奥”。 Visible product: Air Fryer Oreos Visible components: white plate; fork; pastries; powder; text overlay | N10: 9 | O10: 0 | R10: The scene shows prepared pastries with text overlay identifying the product as 'Air Fryer Oreos', but provides no visual, spoken, or OCR evidence of temperature or time settings for cooking. | S10: VLM|OCR | T10: low | U10: No evidence of cooking settings or instructions is present in the scene. | V10: R1 | W10: 0 | Z10: no | AA10: 画面仅展示成品甜点与文字“Air Fryer Oreos”，未出现空气炸锅本体、控制面板或温度/时间设置操作。 | AC10: completed | AD10: 2026-07-27T22:10:25+08:00 | AE10: =IF(AC10<>"completed","",IF(W10=O10,"no","yes")) | AF10: =IF(AC10<>"completed","",IF(AND(X10=P10,Y10=Q10),"no","yes")) | AG10: =IF(AC10<>"completed","待复核",IF(OR(W10="",Z10="",AA10="",AD10=""),"缺少必填项",IF(AND(OR(AE10="yes",AF10="yes"),AB10=""),"修正原因缺失",IF(OR(W10=0,W10=1),IF(AND(X10="",Y10=""),"通过","0/1级时间应留空"),IF(AND(OR(W10=2,W10=3),X10<>"",Y10<>"",X10>=I10,Y10<=J10,Y10>X10),"通过","2/3级时间无效")))))
A11: VQ-001 | B11: 空气炸锅怎样设置烹饪温度和时间？ | C11: zh-CN | D11: Air Fryer | E11: operation | F11: development | G11: airfryer-024-scene-0020 | H11: airfryer-024 | I11: 85.852 | J11: 93.56 | K11: items/airfryer-024-scene-0020/clip.mp4 | L11: items/airfryer-024-scene-0020/thumbnail.jpg | M11: ASR: Why settle for inaccurate knobs and analog dials? Just guessing. The New Wave Brio is the only air fryer with precise temperature control. Simply use the digital touchscreen and cook from 100 degrees to 400 degrees in 5 degree increments. OCR: PRECISE nuwave Temperature 360Y 360F 3007 Control 3 756 TM VLM: Visual summary: A hand is shown adjusting a dial on a kitchen appliance, followed by a finger pressing buttons on a digital air fryer control panel. 视觉摘要: 一只手正在调整厨房电器上的旋钮，随后手指按压空气炸锅控制面板上的按钮。 Visible product: nuwave Visible components: hand; dial; air fryer; digital display; control buttons; temperature settings; food icons Visible actions: adjusting a dial; pressing a button Visible states: digital display showing 375F; dial set to 5 | N11: 10 | O11: 3 | P11: 85.852 | Q11: 93.56 | R11: ASR states the air fryer has precise digital temperature control from 100 to 400 degrees in 5-degree increments. OCR shows temperature settings (360Y, 360F, 3007) and VLM shows hand adjusting dial and pressing buttons on digital panel with display showing 375F, confirming temperature setting action. | S11: ASR|OCR|VLM | T11: low | U11: All evidence directly supports setting temperature and time via digital interface with visible actions and text. | V11: R1 | W11: 3 | X11: 86.0 | Y11: 93.56 | Z11: no | AA11: 画面显示手指拨动/按压空气炸锅温度旋钮与数字面板，OCR可见380F/375F及PRECISE Temperature Control，ASR说明100-400度5度递增的精确温控，可直接回答温度设置。 | AB11: 时间按实际证据片段重定位 | AC11: completed | AD11: 2026-07-27T22:10:25+08:00 | AE11: =IF(AC11<>"completed","",IF(W11=O11,"no","yes")) | AF11: =IF(AC11<>"completed","",IF(AND(X11=P11,Y11=Q11),"no","yes")) | AG11: =IF(AC11<>"completed","待复核",IF(OR(W11="",Z11="",AA11="",AD11=""),"缺少必填项",IF(AND(OR(AE11="yes",AF11="yes"),AB11=""),"修正原因缺失",IF(OR(W11=0,W11=1),IF(AND(X11="",Y11=""),"通过","0/1级时间应留空"),IF(AND(OR(W11=2,W11=3),X11<>"",Y11<>"",X11>=I11,Y11<=J11,Y11>X11),"通过","2/3级时间无效")))))
A12: VQ-001 | B12: 空气炸锅怎样设置烹饪温度和时间？ | C12: zh-CN | D12: Air Fryer | E12: operation | F12: development | G12: airfryer-005-scene-0026 | H12: airfryer-005 | I12: 243.87 | J12: 266.222 | K12: items/airfryer-005-scene-0026/clip.mp4 | L12: items/airfryer-005-scene-0026/thumbnail.jpg | M12: ASR: Now, depending on your bacon, if it's really thick, you're going to want to probably cook it like you'll form it in like the basket and just put that by itself in the basket and cook it for a few minutes first, just because if it's really thick, 10 minutes is not long enough to cook it, cook it all the way. And any longer than 10 minutes is a little bit too long to cook the egg. OK, just keep that in mind. Just depends on the type of bacon that you're using. thing. VLM: Visual summary: A man in a kitchen stands behind a counter with an air fryer and its basket, gesturing as if explaining or demonstrating the appliance. 视觉摘要: 一名男子站在厨房的台面后，面前放着一个空气炸锅及其炸篮，他正在做手势，似乎在讲解或演示该设备。 Visible product: Air Fryer Visible components: air fryer; air fryer basket; refrigerator; white kitchen cabinets; glass jars; knife block; paper towel holder; sink; protein powder container; blue funnel Visible actions: man gesturing with hands; man speaking | N12: 11 | O12: 1 | R12: The ASR mentions cooking bacon for a few minutes or 10 minutes, implying a time setting, but does not specify how to set temperature or time on the air fryer. The VLM shows a man gesturing while explaining, but no visible interaction with controls or settings. | S12: VLM|ASR | T12: low | U12: No visible or spoken evidence of temperature or time setting on the air fryer controls. | V12: R1 | W12: 1 | Z12: no | AA12: 画面中只有主持人站立讲解，未见操作控制面板，ASR仅提到培根烹饪时间建议，未说明如何设置温度/时间。 | AC12: completed | AD12: 2026-07-27T22:10:25+08:00 | AE12: =IF(AC12<>"completed","",IF(W12=O12,"no","yes")) | AF12: =IF(AC12<>"completed","",IF(AND(X12=P12,Y12=Q12),"no","yes")) | AG12: =IF(AC12<>"completed","待复核",IF(OR(W12="",Z12="",AA12="",AD12=""),"缺少必填项",IF(AND(OR(AE12="yes",AF12="yes"),AB12=""),"修正原因缺失",IF(OR(W12=0,W12=1),IF(AND(X12="",Y12=""),"通过","0/1级时间应留空"),IF(AND(OR(W12=2,W12=3),X12<>"",Y12<>"",X12>=I12,Y12<=J12,Y12>X12),"通过","2/3级时间无效")))))
A13: VQ-001 | B13: 空气炸锅怎样设置烹饪温度和时间？ | C13: zh-CN | D13: Air Fryer | E13: operation | F13: development | G13: airfryer-005-scene-0025 | H13: airfryer-005 | I13: 239.199 | J13: 243.87 | K13: items/airfryer-005-scene-0025/clip.mp4 | L13: items/airfryer-005-scene-0025/thumbnail.jpg | M13: ASR: oil. Now, depending on your bacon, if it's really thick, you're VLM: Visual summary: Two pieces of bread with eggs and bacon are inside an air fryer basket. 视觉摘要: 两个夹有鸡蛋和培根的面包片放在空气炸锅篮子里。 Visible product: Air Fryer Visible components: air fryer basket; bread; egg; bacon; pepper | N13: 12 | O13: 1 | R13: The scene shows bread with eggs and bacon in an air fryer basket, indicating the product is present but no temperature or time settings are visible or mentioned. | S13: VLM | T13: low | U13: No evidence of temperature or time settings being set or discussed. | V13: R1 | W13: 1 | Z13: no | AA13: 画面仅展示炸篮内放有面包、鸡蛋和培根，未出现温度或时间设置界面/操作。 | AC13: completed | AD13: 2026-07-27T22:10:25+08:00 | AE13: =IF(AC13<>"completed","",IF(W13=O13,"no","yes")) | AF13: =IF(AC13<>"completed","",IF(AND(X13=P13,Y13=Q13),"no","yes")) | AG13: =IF(AC13<>"completed","待复核",IF(OR(W13="",Z13="",AA13="",AD13=""),"缺少必填项",IF(AND(OR(AE13="yes",AF13="yes"),AB13=""),"修正原因缺失",IF(OR(W13=0,W13=1),IF(AND(X13="",Y13=""),"通过","0/1级时间应留空"),IF(AND(OR(W13=2,W13=3),X13<>"",Y13<>"",X13>=I13,Y13<=J13,Y13>X13),"通过","2/3级时间无效")))))
A14: VQ-001 | B14: 空气炸锅怎样设置烹饪温度和时间？ | C14: zh-CN | D14: Air Fryer | E14: operation | F14: development | G14: airfryer-017-scene-0022 | H14: airfryer-017 | I14: 164.264 | J14: 172.005 | K14: items/airfryer-017-scene-0022/clip.mp4 | L14: items/airfryer-017-scene-0022/thumbnail.jpg | M14: ASR: The major problem, as I found out a few months ago, was that one time the door fell open while I was cooking. So I'll be sure to tighten up the door during this process. process. First thing I'm going to do is remove these cooking trays. There we go. You can see my OCR: 2 ESES VLM: Visual summary: A hand opens the lid of a black and stainless steel air fryer sitting on a dark wooden table in a dining room. 视觉摘要: 一只手在餐厅的深色木桌上打开一个黑色和不锈钢空气炸锅的盖子。 Visible product: Air Fryer Visible components: air fryer; stainless steel exterior; black lid; dark wooden table; chairs; window with blinds; wall decorations; stuffed animals; dollhouse Visible actions: hand opening the air fryer lid Visible states: air fryer lid open; air fryer interior visible | N14: 13 | O14: 0 | R14: The scene shows a hand opening the air fryer lid, but no temperature or time settings are visible, spoken, or indicated. | S14: VLM | T14: low | U14: No evidence of temperature or time settings being set or discussed. | V14: R1 | W14: 0 | Z14: no | AA14: 画面仅展示打开空气炸锅盖并取出烤盘，未出现温度/时间设置界面或操作。 | AC14: completed | AD14: 2026-07-27T22:12:04+08:00 | AE14: =IF(AC14<>"completed","",IF(W14=O14,"no","yes")) | AF14: =IF(AC14<>"completed","",IF(AND(X14=P14,Y14=Q14),"no","yes")) | AG14: =IF(AC14<>"completed","待复核",IF(OR(W14="",Z14="",AA14="",AD14=""),"缺少必填项",IF(AND(OR(AE14="yes",AF14="yes"),AB14=""),"修正原因缺失",IF(OR(W14=0,W14=1),IF(AND(X14="",Y14=""),"通过","0/1级时间应留空"),IF(AND(OR(W14=2,W14=3),X14<>"",Y14<>"",X14>=I14,Y14<=J14,Y14>X14),"通过","2/3级时间无效")))))
A15: VQ-001 | B15: 空气炸锅怎样设置烹饪温度和时间？ | C15: zh-CN | D15: Air Fryer | E15: operation | F15: development | G15: airfryer-017-scene-0059 | H15: airfryer-017 | I15: 690.49 | J15: 696.062 | K15: items/airfryer-017-scene-0059/clip.mp4 | L15: items/airfryer-017-scene-0059/thumbnail.jpg | M15: ASR: what you can find on eBay. I found two replacements that I guess had been scavenged from other units that were sold in a lot on eBay. The one on the left you see is the larger of the two. I thought OCR: FS Dud thermister +tive wome scrar I ditnit pw buek ind replaen the mister(3) neatng grate wonlert Fit afte I adjured meariy cknt t. acwOmlate A thermirtor Nov. 2022 2 VLM: Visual summary: A product listing for replacement thermistor temperature sensors for a Kalorik MAXX Air Fryer, priced at $19.95, with an image of the part and a 'Unit 8 Count' label appearing in one frame. 视觉摘要: 一个用于Kalorik MAXX空气炸锅的替换温度传感器（热敏电阻）的产品列表，价格为19.95美元，其中一帧显示了“8件装”的标签。 Visible product: Kalorik MAXX Air Fryer ~ REPLACEMENT PARTS ~ Thermistor - temperature sensors Visible components: image of two metal thermistor sensors with wires; text label 'UNIT 8 COUNT' Visual uncertainty: The 'UNIT 8 COUNT' label is only visible in the second frame, not the first. | N15: 14 | O15: 0 | R15: The scene shows a product listing for replacement thermistors for a Kalorik MAXX Air Fryer, not instructions on setting temperature and time. | S15: VLM|ASR|OCR | T15: low | U15: The evidence clearly shows a replacement part listing, not operational guidance for setting temperature or time. | V15: R1 | W15: 0 | Z15: no | AA15: 画面为 eBay 商品列表页（温度传感器替换件），非操作教学。 | AC15: completed | AD15: 2026-07-27T22:12:04+08:00 | AE15: =IF(AC15<>"completed","",IF(W15=O15,"no","yes")) | AF15: =IF(AC15<>"completed","",IF(AND(X15=P15,Y15=Q15),"no","yes")) | AG15: =IF(AC15<>"completed","待复核",IF(OR(W15="",Z15="",AA15="",AD15=""),"缺少必填项",IF(AND(OR(AE15="yes",AF15="yes"),AB15=""),"修正原因缺失",IF(OR(W15=0,W15=1),IF(AND(X15="",Y15=""),"通过","0/1级时间应留空"),IF(AND(OR(W15=2,W15=3),X15<>"",Y15<>"",X15>=I15,Y15<=J15,Y15>X15),"通过","2/3级时间无效")))))
A16: VQ-001 | B16: 空气炸锅怎样设置烹饪温度和时间？ | C16: zh-CN | D16: Air Fryer | E16: operation | F16: development | G16: airfryer-017-scene-0061 | H16: airfryer-017 | I16: 705.038 | J16: 724.891 | K16: items/airfryer-017-scene-0061/clip.mp4 | L16: items/airfryer-017-scene-0061/thumbnail.jpg | M16: ASR: two sizes. That's the one that's currently in my air fryer. I'm going to go ahead and test this this other replacement one that I haven't used yet for continuity, just to see. And since I'm not seeing any continuity on this thermistor, I'm not sure that that's something I should be looking for. Last time I replaced the thermistor just because I thought it was something I should do, but now I'm realizing that maybe I didn't even have to at the time. So I'm just going to replace the fuse by itself first and see if that does the trick. This is where getting deeper into OCR: TADIES 22 Frper Emeril Air parts USPS FIRST-CLASS PKG 2 Nov.22 F VLM: Visual summary: A person is using a multimeter to test a small blue electrical component held in their hand, with the component connected to wires. The setup is on a wooden table with various items including a USPS package labeled 'Emeril Air Fryer parts' and a red Staples box. 视觉摘要: 一个人正用万用表测试手中拿着的一个小蓝色电气元件，该元件连接着电线。设置在一张木桌上，周围有各种物品，包括一个标有“Emeril Air Fryer parts”的USPS包裹和一个红色的Staples盒子。 Visible product: Air Fryer Visible components: multimeter; blue electrical component; wires; USPS package; Staples box; wooden table Visible actions: person holding component; person using multimeter probes | N16: 15 | O16: 0 | R16: The scene shows troubleshooting of an air fryer component (thermistor/fuse) using a multimeter, not setting temperature or time. | S16: VLM|ASR|OCR | T16: low | U16: No evidence of temperature or time setting actions or instructions. | V16: R1 | W16: 0 | Z16: no | AA16: 画面为用万用表检测温度保险丝/热敏电阻，未涉及温度或时间设置。 | AC16: completed | AD16: 2026-07-27T22:12:04+08:00 | AE16: =IF(AC16<>"completed","",IF(W16=O16,"no","yes")) | AF16: =IF(AC16<>"completed","",IF(AND(X16=P16,Y16=Q16),"no","yes")) | AG16: =IF(AC16<>"completed","待复核",IF(OR(W16="",Z16="",AA16="",AD16=""),"缺少必填项",IF(AND(OR(AE16="yes",AF16="yes"),AB16=""),"修正原因缺失",IF(OR(W16=0,W16=1),IF(AND(X16="",Y16=""),"通过","0/1级时间应留空"),IF(AND(OR(W16=2,W16=3),X16<>"",Y16<>"",X16>=I16,Y16<=J16,Y16>X16),"通过","2/3级时间无效")))))
A17: VQ-001 | B17: 空气炸锅怎样设置烹饪温度和时间？ | C17: zh-CN | D17: Air Fryer | E17: operation | F17: development | G17: airfryer-032-scene-0040 | H17: airfryer-032 | I17: 179.167 | J17: 182.167 | K17: items/airfryer-032-scene-0040/clip.mp4 | L17: items/airfryer-032-scene-0040/thumbnail.jpg | M17: ASR: to ten minutes at 400 degrees. You might have to do this a few times before the smell goes away. If the smell is too bothersome, you can set it outside in a safe spot and run it out there for VLM: Visual summary: A hand opens the drawer of a black air fryer, revealing a small bowl inside the basket. 视觉摘要: 一只手打开黑色空气炸锅的抽屉，露出篮子内的一只小碗。 Visible product: Air Fryer Visible components: black air fryer; air fryer basket; air fryer drawer handle; small bowl; green bottle; marble countertop Visible actions: hand pulling open drawer Visible states: drawer open; basket revealed | N17: 16 | O17: 1 | R17: ASR mentions temperature (400 degrees) and time (10 minutes) for air fryer operation, but VLM shows only drawer opening with no temperature or time setting action; no visible or spoken evidence of setting temperature/time in this scene. | S17: ASR|VLM | T17: low | U17: ASR provides temperature and time values but no visual evidence of setting them; VLM shows no interaction with controls. | V17: R1 | W17: 1 | Z17: no | AA17: ASR提到400度10分钟，但画面仅展示拉开抽屉，未展示设置温度/时间的操作。 | AC17: completed | AD17: 2026-07-27T22:12:04+08:00 | AE17: =IF(AC17<>"completed","",IF(W17=O17,"no","yes")) | AF17: =IF(AC17<>"completed","",IF(AND(X17=P17,Y17=Q17),"no","yes")) | AG17: =IF(AC17<>"completed","待复核",IF(OR(W17="",Z17="",AA17="",AD17=""),"缺少必填项",IF(AND(OR(AE17="yes",AF17="yes"),AB17=""),"修正原因缺失",IF(OR(W17=0,W17=1),IF(AND(X17="",Y17=""),"通过","0/1级时间应留空"),IF(AND(OR(W17=2,W17=3),X17<>"",Y17<>"",X17>=I17,Y17<=J17,Y17>X17),"通过","2/3级时间无效")))))
A18: VQ-001 | B18: 空气炸锅怎样设置烹饪温度和时间？ | C18: zh-CN | D18: Air Fryer | E18: operation | F18: development | G18: airfryer-005-scene-0027 | H18: airfryer-005 | I18: 266.222 | J18: 270.142 | K18: items/airfryer-005-scene-0027/clip.mp4 | L18: items/airfryer-005-scene-0027/thumbnail.jpg | M18: ASR: thing. And that is just awesome. And now I'm going to just grab this. VLM: Visual summary: Two pieces of bread with eggs and bacon are placed inside an air fryer basket. 视觉摘要: 两个放有鸡蛋和培根的面包片放在空气炸锅篮子里。 Visible product: Air Fryer Visible components: air fryer basket; bread; egg; bacon; seasoning Visible actions: hand holding air fryer handle | N18: 17 | O18: 1 | R18: The scene shows bread with eggs and bacon placed in an air fryer basket, indicating the product is being prepared for cooking, but no temperature or time settings are visible or mentioned. | S18: VLM | T18: low | U18: No evidence of temperature or time settings being adjusted or displayed. | V18: R1 | W18: 1 | Z18: no | AA18: 画面仅展示炸篮内放有面包、鸡蛋和培根，未展示温度或时间设置。 | AC18: completed | AD18: 2026-07-27T22:14:31+08:00 | AE18: =IF(AC18<>"completed","",IF(W18=O18,"no","yes")) | AF18: =IF(AC18<>"completed","",IF(AND(X18=P18,Y18=Q18),"no","yes")) | AG18: =IF(AC18<>"completed","待复核",IF(OR(W18="",Z18="",AA18="",AD18=""),"缺少必填项",IF(AND(OR(AE18="yes",AF18="yes"),AB18=""),"修正原因缺失",IF(OR(W18=0,W18=1),IF(AND(X18="",Y18=""),"通过","0/1级时间应留空"),IF(AND(OR(W18=2,W18=3),X18<>"",Y18<>"",X18>=I18,Y18<=J18,Y18>X18),"通过","2/3级时间无效")))))
A19: VQ-001 | B19: 空气炸锅怎样设置烹饪温度和时间？ | C19: zh-CN | D19: Air Fryer | E19: operation | F19: development | G19: airfryer-006-scene-0001 | H19: airfryer-006 | I19: 0.0 | J19: 4.538 | K19: items/airfryer-006-scene-0001/clip.mp4 | L19: items/airfryer-006-scene-0001/thumbnail.jpg | M19: ASR: Hi, good morning, America. It's Babs making air fryer Oreos. Step one, crescent rolls. OCR: GMA making Air Fryer Oreos! VLM: Visual summary: A woman in a pink shirt is speaking to the camera in a kitchen setting, introducing herself as 'Babs' and mentioning she is making 'Air Fryer Oreos'. 视觉摘要: 一位穿着粉色衬衫的女士在厨房环境中对着镜头讲话，介绍自己为“Babs”，并提到她正在制作“空气炸锅奥利奥”。 Visible product: Air Fryer Visible components: woman; pink shirt; glasses; kitchen counter; stacked plates; wooden shelf; GMA logo Visible actions: speaking; looking at camera | N19: 18 | O19: 1 | R19: The scene introduces the product (Air Fryer) and the creator (Babs) but does not show or mention any temperature or time settings for cooking. | S19: VLM|ASR|OCR | T19: low | U19: No evidence of temperature or time settings being discussed or demonstrated. | V19: R1 | W19: 0 | Z19: no | AA19: 画面为人物开场白与手持食材，未见空气炸锅本体或温度/时间设置操作。 | AB19: AI原判为1级，但画面中无空气炸锅实体，仅为食谱引入，故降为0级。 | AC19: completed | AD19: 2026-07-27T22:14:31+08:00 | AE19: =IF(AC19<>"completed","",IF(W19=O19,"no","yes")) | AF19: =IF(AC19<>"completed","",IF(AND(X19=P19,Y19=Q19),"no","yes")) | AG19: =IF(AC19<>"completed","待复核",IF(OR(W19="",Z19="",AA19="",AD19=""),"缺少必填项",IF(AND(OR(AE19="yes",AF19="yes"),AB19=""),"修正原因缺失",IF(OR(W19=0,W19=1),IF(AND(X19="",Y19=""),"通过","0/1级时间应留空"),IF(AND(OR(W19=2,W19=3),X19<>"",Y19<>"",X19>=I19,Y19<=J19,Y19>X19),"通过","2/3级时间无效")))))
A20: VQ-001 | B20: 空气炸锅怎样设置烹饪温度和时间？ | C20: zh-CN | D20: Air Fryer | E20: operation | F20: development | G20: airfryer-033-scene-0157 | H20: airfryer-033 | I20: 1391.658 | J20: 1408.108 | K20: items/airfryer-033-scene-0157/clip.mp4 | L20: items/airfryer-033-scene-0157/thumbnail.jpg | M20: ASR: Cheguei, de banhozinho tomado OCR: PHILIPS WALITA D K VLM: Visual summary: A black air fryer with a digital display is shown, with the temperature and timer settings changing on the screen. 视觉摘要: 一台黑色空气炸锅，其数字显示屏上的温度和计时器设置正在变化。 Visible product: Air Fryer Visible components: digital display; temperature control buttons; timer control buttons; power button; brand name 'PHILIPS WALITA'; air fryer basket; control panel; power cord Visible actions: temperature setting changing; timer setting changing Visible states: display showing '200°'; display showing '5'; display showing '0' | N20: 19 | O20: 3 | P20: 1391.658 | Q20: 1408.108 | R20: The air fryer's digital display shows temperature and timer settings changing, including '200°' and '5', indicating direct demonstration of setting temperature and time. | S20: VLM|ASR|OCR | T20: low | U20: No ambiguity in visible actions or displayed values; full scene interval is supported by visual and OCR evidence. | V20: R1 | W20: 2 | X20: 1391.7 | Y20: 1408.1 | Z20: no | AA20: 6帧中飞利浦空气炸锅数字显示屏持续可见并显示变化数字，但未清晰呈现手指按压温度/时间按键的设置动作。 | AB20: 第三轮双复核一致修正：R1=3→indep=2：画面仅展示数字屏上的设置结果/倒计时，未完整演示“如何设置”温度与时间的按键操作。 | AC20: completed | AD20: 2026-07-28T20:35:21+08:00 | AE20: =IF(AC20<>"completed","",IF(W20=O20,"no","yes")) | AF20: =IF(AC20<>"completed","",IF(AND(X20=P20,Y20=Q20),"no","yes")) | AG20: =IF(AC20<>"completed","待复核",IF(OR(W20="",Z20="",AA20="",AD20=""),"缺少必填项",IF(AND(OR(AE20="yes",AF20="yes"),AB20=""),"修正原因缺失",IF(OR(W20=0,W20=1),IF(AND(X20="",Y20=""),"通过","0/1级时间应留空"),IF(AND(OR(W20=2,W20=3),X20<>"",Y20<>"",X20>=I20,Y20<=J20,Y20>X20),"通过","2/3级时间无效")))))
A21: VQ-001 | B21: 空气炸锅怎样设置烹饪温度和时间？ | C21: zh-CN | D21: Air Fryer | E21: operation | F21: development | G21: airfryer-029-scene-0008 | H21: airfryer-029 | I21: 38.0 | J21: 43.92 | K21: items/airfryer-029-scene-0008/clip.mp4 | L21: items/airfryer-029-scene-0008/thumbnail.jpg | M21: ASR: air fryer also. With Philips air fryer unique rapid air technology you can fry OCR: PHILIPS VLM: Visual summary: A close-up of a black Philips air fryer with its control dial and a partially visible basket. 视觉摘要: 一台黑色飞利浦空气炸锅的特写，显示其控制旋钮和部分可见的炸篮。 Visible product: Air Fryer Visible components: Philips brand logo; control dial; air fryer basket; temperature and time settings label Visible states: air fryer basket partially open | N21: 20 | O21: 1 | R21: The scene shows the air fryer's control dial and temperature/time settings label, indicating the product is visible but no actual setting or adjustment is demonstrated. | S21: VLM | T21: low | U21: No action of setting temperature or time is shown; only the interface is visible. | V21: R1 | W21: 1 | Z21: no | AA21: 画面展示飞利浦空气炸锅的控制旋钮与温度/时间刻度，但未演示实际调节动作。 | AC21: completed | AD21: 2026-07-27T22:14:31+08:00 | AE21: =IF(AC21<>"completed","",IF(W21=O21,"no","yes")) | AF21: =IF(AC21<>"completed","",IF(AND(X21=P21,Y21=Q21),"no","yes")) | AG21: =IF(AC21<>"completed","待复核",IF(OR(W21="",Z21="",AA21="",AD21=""),"缺少必填项",IF(AND(OR(AE21="yes",AF21="yes"),AB21=""),"修正原因缺失",IF(OR(W21=0,W21=1),IF(AND(X21="",Y21=""),"通过","0/1级时间应留空"),IF(AND(OR(W21=2,W21=3),X21<>"",Y21<>"",X21>=I21,Y21<=J21,Y21>X21),"通过","2/3级时间无效")))))
A22: VQ-001 | B22: 空气炸锅怎样设置烹饪温度和时间？ | C22: zh-CN | D22: Air Fryer | E22: operation | F22: development | G22: airfryer-002-scene-0008 | H22: airfryer-002 | I22: 191.625 | J22: 241.808 | K22: items/airfryer-002-scene-0008/clip.mp4 | L22: items/airfryer-002-scene-0008/thumbnail.jpg | M22: ASR: bend that seal over and underneath on the bottom of the cookie. At that point you're going to put up just a little bit of an egg wash on the top and continue with all of your cookies. So I'm finishing up making my last cookie to put into the air fryer and you're going to want to preheat your fryer to 350 degrees and we're going to cook these for about seven minutes. So let's get that turned on and preheat it to 350. so our air fryer is preheated to 350 degrees we're going to take the basket out and spray it with a little non-stick spray we're now going to place our cookies in the basket seam side down we're going to cook OCR: Chef Library Kitchen Puff Pastry SHEETS OREO Lhrary Kitche Tray Library Kitchen VLM: Visual summary: A man in a blue apron is preparing food in a kitchen, with ingredients and an air fryer on the counter. 视觉摘要: 一名穿着蓝色围裙的男子在厨房准备食物，台面上有食材和空气炸锅。 Visible product: Air Fryer Visible components: air fryer; puff pastry box; OREO cookies package; powdered sugar container; silicone mat; plate with cookies; apron; glasses Visible actions: man shaping dough; man holding a spray can and a pan Visible states: dough pieces on mat; cookies on plate | N22: 21 | O22: 3 | P22: 230.0 | Q22: 235.0 | R22: ASR states: 'you're going to want to preheat your fryer to 350 degrees and we're going to cook these for about seven minutes.' This directly specifies temperature (350 degrees) and time (7 minutes) for air fryer operation. | S22: ASR | T22: low | U22: The ASR text clearly and fully specifies both temperature and time for the air fryer, with no ambiguity or missing context. | V22: R1 | W22: 3 | X22: 230.0 | Y22: 235.0 | Z22: no | AA22: ASR明确说明需预热至350度并烹饪约7分钟，给出具体温度与时间参数。 | AC22: completed | AD22: 2026-07-27T22:17:08+08:00 | AE22: =IF(AC22<>"completed","",IF(W22=O22,"no","yes")) | AF22: =IF(AC22<>"completed","",IF(AND(X22=P22,Y22=Q22),"no","yes")) | AG22: =IF(AC22<>"completed","待复核",IF(OR(W22="",Z22="",AA22="",AD22=""),"缺少必填项",IF(AND(OR(AE22="yes",AF22="yes"),AB22=""),"修正原因缺失",IF(OR(W22=0,W22=1),IF(AND(X22="",Y22=""),"通过","0/1级时间应留空"),IF(AND(OR(W22=2,W22=3),X22<>"",Y22<>"",X22>=I22,Y22<=J22,Y22>X22),"通过","2/3级时间无效")))))
A23: VQ-001 | B23: 空气炸锅怎样设置烹饪温度和时间？ | C23: zh-CN | D23: Air Fryer | E23: operation | F23: development | G23: airfryer-032-scene-0006 | H23: airfryer-032 | I23: 14.767 | J23: 16.767 | K23: items/airfryer-032-scene-0006/clip.mp4 | L23: items/airfryer-032-scene-0006/thumbnail.jpg | M23: ASR: this. Hey there my name is Kathy from fabulouslyfrugal.com and every Sunday morning I'm sharing VLM: Visual summary: A close-up view of the interior of an appliance showing a spiral heating element on a metal cooking surface. 视觉摘要: 一个电器内部的特写，显示一个螺旋形加热元件位于金属烹饪表面上。 Visible product: Air Fryer Visible components: spiral heating element; metal cooking surface; metal interior walls; ventilation slots; screws Visual uncertainty: The product is labeled as an air fryer, but the visible components do not clearly indicate air frying functionality such as a fan or basket. | N23: 22 | O23: 1 | R23: The visual shows an air fryer's interior with a spiral heating element, but no visible controls, display, or instructions for setting temperature and time. | S23: VLM | T23: low | U23: No evidence of temperature or time setting interface or instructions shown in the scene. | V23: R1 | W23: 1 | Z23: no | AA23: 画面展示打开机体露出加热元件，但未展示控制面板或温度/时间设置。 | AC23: completed | AD23: 2026-07-27T22:17:08+08:00 | AE23: =IF(AC23<>"completed","",IF(W23=O23,"no","yes")) | AF23: =IF(AC23<>"completed","",IF(AND(X23=P23,Y23=Q23),"no","yes")) | AG23: =IF(AC23<>"completed","待复核",IF(OR(W23="",Z23="",AA23="",AD23=""),"缺少必填项",IF(AND(OR(AE23="yes",AF23="yes"),AB23=""),"修正原因缺失",IF(OR(W23=0,W23=1),IF(AND(X23="",Y23=""),"通过","0/1级时间应留空"),IF(AND(OR(W23=2,W23=3),X23<>"",Y23<>"",X23>=I23,Y23<=J23,Y23>X23),"通过","2/3级时间无效")))))
A24: VQ-001 | B24: 空气炸锅怎样设置烹饪温度和时间？ | C24: zh-CN | D24: Air Fryer | E24: operation | F24: development | G24: airfryer-024-scene-0009 | H24: airfryer-024 | I24: 36.536 | J24: 40.974 | K24: items/airfryer-024-scene-0009/clip.mp4 | L24: items/airfryer-024-scene-0009/thumbnail.jpg | M24: ASR: The optional preheat function makes grilling, searing, and broiling easy and fast, with perfect results each and every time. OCR: PERFECT RESULTS Every Time! VLM: Visual summary: A close-up of an air fryer's digital control panel displaying a temperature of 375°F, with text indicating an 'Optional PREHEAT FUNCTION' and 'Patent Pending'. The scene then transitions to show three cooking modes: grilling, searing, and broiling, each with food items inside the air fryer basket. 视觉摘要: 一台空气炸锅的数字控制面板特写，显示温度为375°F，配有“可选预热功能”和“专利待定”字样。随后画面切换，展示三种烹饪模式：烧烤、煎制和烘烤，每个模式下都有食物在炸篮中。 Visible product: Air Fryer Visible components: digital display; temperature reading; control buttons; cooking mode icons; air fryer basket; food items (steaks, scallops, chicken, sweet potatoes) Visible states: temperature set to 375°F; preheat function indicated; food being cooked in different modes | N24: 23 | O24: 2 | P24: 36.536 | Q24: 40.974 | R24: The scene shows the air fryer's digital display set to 375°F and demonstrates cooking modes (grilling, searing, broiling) with food items, indicating how temperature and mode selection are used, though it does not explicitly show time setting. | S24: VLM|ASR|OCR | T24: low | U24: No explicit mention or visual of time setting functionality. | V24: R1 | W24: 2 | X24: 36.536 | Y24: 40.974 | Z24: no | AA24: 数字屏显示375°F及PREHEAT FUNCTION，展示了温度设置，但未明确展示时间设置。 | AC24: completed | AD24: 2026-07-27T22:17:08+08:00 | AE24: =IF(AC24<>"completed","",IF(W24=O24,"no","yes")) | AF24: =IF(AC24<>"completed","",IF(AND(X24=P24,Y24=Q24),"no","yes")) | AG24: =IF(AC24<>"completed","待复核",IF(OR(W24="",Z24="",AA24="",AD24=""),"缺少必填项",IF(AND(OR(AE24="yes",AF24="yes"),AB24=""),"修正原因缺失",IF(OR(W24=0,W24=1),IF(AND(X24="",Y24=""),"通过","0/1级时间应留空"),IF(AND(OR(W24=2,W24=3),X24<>"",Y24<>"",X24>=I24,Y24<=J24,Y24>X24),"通过","2/3级时间无效")))))
A25: VQ-001 | B25: 空气炸锅怎样设置烹饪温度和时间？ | C25: zh-CN | D25: Air Fryer | E25: operation | F25: development | G25: pressure-006-scene-0010 | H25: pressure-006 | I25: 29.458 | J25: 34.083 | K25: items/pressure-006-scene-0010/clip.mp4 | L25: items/pressure-006-scene-0010/thumbnail.jpg | M25: ASR: • 360-degree hot air baking, wrapping heating, original flavor, 1500W high power, rapid heating OCR: 1500 W high-power rapid heating VLM: Visual summary: Food items are cooking inside an air fryer, with text overlays indicating '360 air cooking' and '1500 W high-power rapid heating'. 视觉摘要: 食物在空气炸锅内烹饪，画面中有文字叠加显示“360空气烹饪”和“1500W高功率快速加热”。 Visible product: Air Fryer Visible components: food items; air fryer basket; text overlay Visible states: food is cooking; air fryer is operating Visual uncertainty: The specific model or brand of the air fryer is not visible. The exact type of food is not clearly identifiable. | N25: 24 | O25: 1 | R25: The scene shows an air fryer operating with text overlays indicating '360 air cooking' and '1500W high-power rapid heating', but no explicit instruction or setting of temperature or time is shown or mentioned. | S25: VLM|ASR|OCR | T25: low | U25: No visible or spoken evidence of temperature or time settings being adjusted or displayed. | V25: R1 | W25: 1 | Z25: no | AA25: 画面展示食物在空炸锅内烹饪，叠加“360 air cooking”等文字，但未展示具体温度/时间设置。 | AC25: completed | AD25: 2026-07-27T22:17:08+08:00 | AE25: =IF(AC25<>"completed","",IF(W25=O25,"no","yes")) | AF25: =IF(AC25<>"completed","",IF(AND(X25=P25,Y25=Q25),"no","yes")) | AG25: =IF(AC25<>"completed","待复核",IF(OR(W25="",Z25="",AA25="",AD25=""),"缺少必填项",IF(AND(OR(AE25="yes",AF25="yes"),AB25=""),"修正原因缺失",IF(OR(W25=0,W25=1),IF(AND(X25="",Y25=""),"通过","0/1级时间应留空"),IF(AND(OR(W25=2,W25=3),X25<>"",Y25<>"",X25>=I25,Y25<=J25,Y25>X25),"通过","2/3级时间无效")))))
A26: VQ-001 | B26: 空气炸锅怎样设置烹饪温度和时间？ | C26: zh-CN | D26: Air Fryer | E26: operation | F26: development | G26: airfryer-002-scene-0010 | H26: airfryer-002 | I26: 257.424 | J26: 283.851 | K26: items/airfryer-002-scene-0010/clip.mp4 | L26: items/airfryer-002-scene-0010/thumbnail.jpg | M26: ASR: spray we're now going to place our cookies in the basket seam side down we're going to cook for seven minutes so it's been about seven minutes and i believe our cookies are about done So as you can see, the puff pastry is golden brown with a cookie in the middle. OCR: Lirary Riden Puff Pastry SHEETS OREO Chef Library Kitchen wnen VLM: Visual summary: A man in a blue apron stands behind a kitchen counter with an air fryer, ingredients, and kitchen tools. He gestures and interacts with the air fryer basket. 视觉摘要: 一名穿着蓝色围裙的男子站在厨房操作台前，台面上有空气炸锅、食材和厨具。他做出手势并与空气炸锅的篮子互动。 Visible product: Air Fryer Visible components: air fryer; air fryer basket; puff pastry sheets; OREO cookies; powdered sugar container; spray bottle; silicone mat; white plate; red placemat; chef apron; glasses; watch Visible actions: gesturing with hand; holding air fryer basket; pointing at air fryer basket; placing hand on counter Visible states: man smiling; air fryer basket being held; ingredients arranged on counter | N26: 25 | O26: 1 | R26: ASR mentions cooking for seven minutes, but does not specify how to set temperature or time on the air fryer; VLM shows interaction with the air fryer basket but no visible setting of temperature or time. | S26: ASR|VLM | T26: low | U26: No visible or spoken evidence of temperature or time setting on the air fryer control panel. | V26: R1 | W26: 1 | Z26: no | AA26: ASR提到烹饪7分钟，但未在画面中展示温度/时间设置操作。 | AC26: completed | AD26: 2026-07-27T22:20:03+08:00 | AE26: =IF(AC26<>"completed","",IF(W26=O26,"no","yes")) | AF26: =IF(AC26<>"completed","",IF(AND(X26=P26,Y26=Q26),"no","yes")) | AG26: =IF(AC26<>"completed","待复核",IF(OR(W26="",Z26="",AA26="",AD26=""),"缺少必填项",IF(AND(OR(AE26="yes",AF26="yes"),AB26=""),"修正原因缺失",IF(OR(W26=0,W26=1),IF(AND(X26="",Y26=""),"通过","0/1级时间应留空"),IF(AND(OR(W26=2,W26=3),X26<>"",Y26<>"",X26>=I26,Y26<=J26,Y26>X26),"通过","2/3级时间无效")))))
A27: VQ-001 | B27: 空气炸锅怎样设置烹饪温度和时间？ | C27: zh-CN | D27: Air Fryer | E27: operation | F27: development | G27: airfryer-006-scene-0005 | H27: airfryer-006 | I27: 16.817 | J27: 19.92 | K27: items/airfryer-006-scene-0005/clip.mp4 | L27: items/airfryer-006-scene-0005/thumbnail.jpg | M27: ASR: Your air fryer, 350, four minutes for the first side. Here it goes. VLM: Visual summary: A woman in a pink shirt is standing in a kitchen next to a white air fryer, gesturing with her hand while speaking. 视觉摘要: 一位穿着粉色衬衫的女士站在厨房里，旁边是一台白色空气炸锅，她正用手势配合说话。 Visible product: Air Fryer Visible components: white air fryer; digital display; control buttons; brand name 'COSORI'; temperature setting '350°'; shelf with plates; plant Visible actions: woman gesturing with her right hand; woman speaking | N27: 26 | O27: 3 | P27: 16.817 | Q27: 19.92 | R27: ASR states 'Your air fryer, 350, four minutes for the first side', and VLM shows the air fryer with visible temperature setting '350°', directly indicating how to set temperature and time. | S27: ASR|VLM | T27: low | U27: No ambiguity in the ASR text or VLM visual evidence regarding the temperature and time setting. | V27: R1 | W27: 3 | X27: 16.817 | Y27: 19.92 | Z27: no | AA27: 画面中白色空气炸锅显示屏显示350°F，并叠加文字“AIR FRY AT 350°F FOR 4 MINUTES”，直接给出温度与时间设置。 | AC27: completed | AD27: 2026-07-27T22:20:03+08:00 | AE27: =IF(AC27<>"completed","",IF(W27=O27,"no","yes")) | AF27: =IF(AC27<>"completed","",IF(AND(X27=P27,Y27=Q27),"no","yes")) | AG27: =IF(AC27<>"completed","待复核",IF(OR(W27="",Z27="",AA27="",AD27=""),"缺少必填项",IF(AND(OR(AE27="yes",AF27="yes"),AB27=""),"修正原因缺失",IF(OR(W27=0,W27=1),IF(AND(X27="",Y27=""),"通过","0/1级时间应留空"),IF(AND(OR(W27=2,W27=3),X27<>"",Y27<>"",X27>=I27,Y27<=J27,Y27>X27),"通过","2/3级时间无效")))))
A28: VQ-001 | B28: 空气炸锅怎样设置烹饪温度和时间？ | C28: zh-CN | D28: Air Fryer | E28: operation | F28: development | G28: airfryer-017-scene-0112 | H28: airfryer-017 | I28: 1506.839 | J28: 1523.722 | K28: items/airfryer-017-scene-0112/clip.mp4 | L28: items/airfryer-017-scene-0112/thumbnail.jpg | M28: ASR: so there we go we're back in action i'll let you know if it breaks again and if i fix it again OCR: 2 VLM: Visual summary: A person is interacting with a silver air fryer on a kitchen counter, next to a toaster and red containers. 视觉摘要: 一个人在厨房台面上与一台银色空气炸锅互动，旁边有一个烤面包机和红色容器。 Visible product: Air Fryer Visible components: silver air fryer; toaster; red containers; black tiled backsplash; white cabinets; digital display; control panel Visible actions: person pressing a button on the air fryer; person bending over the counter Visible states: air fryer display shows 'OFF' Visual uncertainty: The person's face and full body are not visible. The contents inside the air fryer are not clearly identifiable. | N28: 27 | O28: 1 | R28: The scene shows a person interacting with an air fryer, but no temperature or time settings are visible or mentioned; the display shows 'OFF' and no actionable settings are demonstrated. | S28: VLM | T28: low | U28: No evidence of temperature or time setting actions or values is present. | V28: R1 | W28: 1 | Z28: no | AA28: 画面显示空气炸锅显示屏为OFF，未展示温度/时间设置。 | AC28: completed | AD28: 2026-07-27T22:20:03+08:00 | AE28: =IF(AC28<>"completed","",IF(W28=O28,"no","yes")) | AF28: =IF(AC28<>"completed","",IF(AND(X28=P28,Y28=Q28),"no","yes")) | AG28: =IF(AC28<>"completed","待复核",IF(OR(W28="",Z28="",AA28="",AD28=""),"缺少必填项",IF(AND(OR(AE28="yes",AF28="yes"),AB28=""),"修正原因缺失",IF(OR(W28=0,W28=1),IF(AND(X28="",Y28=""),"通过","0/1级时间应留空"),IF(AND(OR(W28=2,W28=3),X28<>"",Y28<>"",X28>=I28,Y28<=J28,Y28>X28),"通过","2/3级时间无效")))))
A29: VQ-001 | B29: 空气炸锅怎样设置烹饪温度和时间？ | C29: zh-CN | D29: Air Fryer | E29: operation | F29: development | G29: airfryer-024-scene-0021 | H29: airfryer-024 | I29: 93.56 | J29: 99.8 | K29: items/airfryer-024-scene-0021/clip.mp4 | L29: items/airfryer-024-scene-0021/thumbnail.jpg | M29: ASR: Simply use the digital touchscreen and cook from 100 degrees to 400 degrees in 5 degree increments. The Brio's 3 quart capacity can make meals for one or the whole family. OCR: nuwave Temperature Range 360F 100°- 400° 360°F 360'F In 5º 390F Increments 15-22mnins 3907 6-10mins 5-10mns VLM: Visual summary: A hand is interacting with the digital touchscreen of a NuWave air fryer, adjusting the temperature setting. 视觉摘要: 一只手正在操作一台NuWave空气炸锅的数字触摸屏，调整温度设置。 Visible product: NuWave Visible components: digital touchscreen; temperature display; touch buttons; temperature icons; product branding Visible actions: hand touching screen Visible states: temperature displayed as 105°F; temperature displayed as 215°F | N29: 28 | O29: 3 | P29: 93.56 | Q29: 99.8 | R29: The ASR explicitly states how to set temperature (100-400°F in 5° increments) and mentions time ranges (15-22 mins, 6-10 mins, 5-10 mins) for specific temperatures. The VLM shows a hand adjusting temperature on the touchscreen, and OCR confirms the temperature range and increments. All evidence directly answers the question. | S29: VLM|ASR|OCR | T29: low | U29: All evidence is complete and directly addresses the question without ambiguity. | V29: R1 | W29: 2 | X29: 93.56 | Y29: 99.8 | Z29: no | AA29: 六帧清晰展示手指操作Nuwave空气炸锅数字触摸屏，屏幕温度在100°F→125°F→155°F→215°F之间变化，叠加'Temperature Range 100°-400° In 5° Increments'与'DIGITAL Touch Screen'字幕；但仅演示温度调节流程，未演示时间/定时设置步骤。 | AB29: 第三轮双复核一致修正：R1=3→独立=2：query问'温度与时间'两步，画面只回答温度设置未演示时间设置，无法构成完整回答；时间区间一致。 | AC29: completed | AD29: 2026-07-28T20:35:21+08:00 | AE29: =IF(AC29<>"completed","",IF(W29=O29,"no","yes")) | AF29: =IF(AC29<>"completed","",IF(AND(X29=P29,Y29=Q29),"no","yes")) | AG29: =IF(AC29<>"completed","待复核",IF(OR(W29="",Z29="",AA29="",AD29=""),"缺少必填项",IF(AND(OR(AE29="yes",AF29="yes"),AB29=""),"修正原因缺失",IF(OR(W29=0,W29=1),IF(AND(X29="",Y29=""),"通过","0/1级时间应留空"),IF(AND(OR(W29=2,W29=3),X29<>"",Y29<>"",X29>=I29,Y29<=J29,Y29>X29),"通过","2/3级时间无效")))))
A30: VQ-001 | B30: 空气炸锅怎样设置烹饪温度和时间？ | C30: zh-CN | D30: Air Fryer | E30: operation | F30: development | G30: airfryer-029-scene-0045 | H30: airfryer-029 | I30: 272.4 | J30: 276.6 | K30: items/airfryer-029-scene-0045/clip.mp4 | L30: items/airfryer-029-scene-0045/thumbnail.jpg | M30: ASR: temperature whereas meats usually I prefer to cook at high temperature so I'm going to preheat at 200 degree centigrade for around 5 minutes. The built in timer of the OCR: Philips SUPER CHEF VLM: Visual summary: A person is operating a black Philips air fryer, adjusting its control dial. 视觉摘要: 一个人正在操作一台黑色的飞利浦空气炸锅，调整其控制旋钮。 Visible product: Philips Visible components: air fryer; control dial; temperature indicator; recipe guide label; brand logo Visible actions: hand adjusting control dial; hand on top lid Visible states: air fryer in use; control dial set to a specific setting Visual uncertainty: The exact setting on the control dial is not clearly readable, and the specific food being cooked is not visible. | N30: 29 | O30: 2 | P30: 272.4 | Q30: 276.6 | R30: ASR mentions setting temperature to 200 degrees Celsius and preheating for 5 minutes, which directly relates to the question. VLM shows hand adjusting the control dial, indicating temperature/time setting action, though exact values are not visible. | S30: ASR|VLM | T30: medium | U30: The exact temperature and time values are not fully visible in the VLM, and the ASR is partially cut off, leaving ambiguity about whether the full setting process is covered. | V30: R1 | W30: 3 | X30: 272.4 | Y30: 276.6 | Z30: no | AA30: 画面中手指正在调节飞利浦空气炸锅的温度/时间旋钮，ASR明确说明预热200°C约5分钟，直接展示设置过程。 | AB30: AI=2→R1=3 | AC30: completed | AD30: 2026-07-27T22:23:08+08:00 | AE30: =IF(AC30<>"completed","",IF(W30=O30,"no","yes")) | AF30: =IF(AC30<>"completed","",IF(AND(X30=P30,Y30=Q30),"no","yes")) | AG30: =IF(AC30<>"completed","待复核",IF(OR(W30="",Z30="",AA30="",AD30=""),"缺少必填项",IF(AND(OR(AE30="yes",AF30="yes"),AB30=""),"修正原因缺失",IF(OR(W30=0,W30=1),IF(AND(X30="",Y30=""),"通过","0/1级时间应留空"),IF(AND(OR(W30=2,W30=3),X30<>"",Y30<>"",X30>=I30,Y30<=J30,Y30>X30),"通过","2/3级时间无效")))))
A31: VQ-001 | B31: 空气炸锅怎样设置烹饪温度和时间？ | C31: zh-CN | D31: Air Fryer | E31: operation | F31: development | G31: pressure-006-scene-0009 | H31: pressure-006 | I31: 26.042 | J31: 29.458 | K31: items/pressure-006-scene-0009/clip.mp4 | L31: items/pressure-006-scene-0009/thumbnail.jpg | M31: ASR: • 360-degree hot air baking, wrapping heating, original flavor, 1500W high power, rapid heating VLM: Visual summary: A hand interacts with the control panel of a yellow air fryer with a black front panel and digital display. 视觉摘要: 一只手正在操作一台黄色空气炸锅的黑色控制面板和数字显示屏。 Visible product: Air Fryer Visible components: yellow body; black front panel; digital display; control buttons; hand Visible actions: touching the control panel Visible states: digital display showing '888' | N31: 30 | O31: 1 | R31: The scene shows a hand interacting with the air fryer's control panel, which implies potential temperature or time setting, but no specific temperature or time values are visible or mentioned. | S31: VLM | T31: low | U31: No explicit temperature or time settings are shown or mentioned in the evidence. | V31: R1 | W31: 1 | Z31: no | AA31: 画面展示手指触碰控制面板，但未显示具体温度/时间数值。 | AC31: completed | AD31: 2026-07-27T22:23:08+08:00 | AE31: =IF(AC31<>"completed","",IF(W31=O31,"no","yes")) | AF31: =IF(AC31<>"completed","",IF(AND(X31=P31,Y31=Q31),"no","yes")) | AG31: =IF(AC31<>"completed","待复核",IF(OR(W31="",Z31="",AA31="",AD31=""),"缺少必填项",IF(AND(OR(AE31="yes",AF31="yes"),AB31=""),"修正原因缺失",IF(OR(W31=0,W31=1),IF(AND(X31="",Y31=""),"通过","0/1级时间应留空"),IF(AND(OR(W31=2,W31=3),X31<>"",Y31<>"",X31>=I31,Y31<=J31,Y31>X31),"通过","2/3级时间无效")))))
A32: VQ-001 | B32: 空气炸锅怎样设置烹饪温度和时间？ | C32: zh-CN | D32: Air Fryer | E32: operation | F32: development | G32: airfryer-005-scene-0023 | H32: airfryer-005 | I32: 227.314 | J32: 232.694 | K32: items/airfryer-005-scene-0023/clip.mp4 | L32: items/airfryer-005-scene-0023/thumbnail.jpg | M32: ASR: And when the timer goes off, you can take it out and look at that nice golden brown toast with a basket of bacon and egg VLM: Visual summary: A person opens an air fryer and reveals two cooked food items inside. 视觉摘要: 一个人打开空气炸锅，露出里面的两个熟食。 Visible product: Air Fryer Visible components: air fryer; air fryer basket; white plate; person's hand; person's sleeve Visible actions: opening the air fryer; holding the air fryer handle Visible states: air fryer open; food cooked inside air fryer Visual uncertainty: The exact type of food is not clearly identifiable, and the person's face and full body are not visible. | N32: 31 | O32: 1 | R32: The scene shows the air fryer after cooking, with food inside, but does not show any temperature or time settings being adjusted. | S32: VLM | T32: low | U32: No evidence of setting temperature or time is visible or audible. | V32: R1 | W32: 1 | Z32: no | AA32: 画面展示烹饪完成后取出炸篮，未显示温度/时间设置。 | AC32: completed | AD32: 2026-07-27T22:23:08+08:00 | AE32: =IF(AC32<>"completed","",IF(W32=O32,"no","yes")) | AF32: =IF(AC32<>"completed","",IF(AND(X32=P32,Y32=Q32),"no","yes")) | AG32: =IF(AC32<>"completed","待复核",IF(OR(W32="",Z32="",AA32="",AD32=""),"缺少必填项",IF(AND(OR(AE32="yes",AF32="yes"),AB32=""),"修正原因缺失",IF(OR(W32=0,W32=1),IF(AND(X32="",Y32=""),"通过","0/1级时间应留空"),IF(AND(OR(W32=2,W32=3),X32<>"",Y32<>"",X32>=I32,Y32<=J32,Y32>X32),"通过","2/3级时间无效")))))
A33: VQ-001 | B33: 空气炸锅怎样设置烹饪温度和时间？ | C33: zh-CN | D33: Air Fryer | E33: operation | F33: development | G33: airfryer-033-scene-0034 | H33: airfryer-033 | I33: 251.818 | J33: 257.024 | K33: items/airfryer-033-scene-0034/clip.mp4 | L33: items/airfryer-033-scene-0034/thumbnail.jpg | M33: ASR: Ela dispara um relêzinho E é bom desligar Tem hora que ela liga, tem hora que ela não liga Vou ter que desmontar ela todinha VLM: Visual summary: A black air fryer with its top cover removed, revealing internal components, is shown on a white surface. The digital display shows a temperature of 200 degrees. 视觉摘要: 一台黑色空气炸锅，其上盖被移开，露出内部组件，放置在白色表面上。数字显示屏显示温度为200度。 Visible product: Air Fryer Visible components: digital display; temperature reading; control buttons; brand name 'PHILIPS WALITA'; internal heating element; power cord; handle Visible states: top cover removed; digital display active | N33: 32 | O33: 2 | P33: 251.818 | Q33: 257.024 | R33: The air fryer's digital display shows a temperature of 200 degrees, indicating a visible temperature setting, but no time setting or explicit instruction on how to set temperature and time is shown or spoken. | S33: VLM | T33: low | U33: No explicit instruction or demonstration of setting time is present; only temperature is visible. | V33: R1 | W33: 2 | X33: 251.818 | Y33: 257.024 | Z33: no | AA33: 画面展示拆机后的空气炸锅显示屏显示200°，但未展示设置过程。 | AC33: completed | AD33: 2026-07-27T22:23:08+08:00 | AE33: =IF(AC33<>"completed","",IF(W33=O33,"no","yes")) | AF33: =IF(AC33<>"completed","",IF(AND(X33=P33,Y33=Q33),"no","yes")) | AG33: =IF(AC33<>"completed","待复核",IF(OR(W33="",Z33="",AA33="",AD33=""),"缺少必填项",IF(AND(OR(AE33="yes",AF33="yes"),AB33=""),"修正原因缺失",IF(OR(W33=0,W33=1),IF(AND(X33="",Y33=""),"通过","0/1级时间应留空"),IF(AND(OR(W33=2,W33=3),X33<>"",Y33<>"",X33>=I33,Y33<=J33,Y33>X33),"通过","2/3级时间无效")))))
A34: VQ-001 | B34: 空气炸锅怎样设置烹饪温度和时间？ | C34: zh-CN | D34: Air Fryer | E34: operation | F34: development | G34: airfryer-032-scene-0113 | H34: airfryer-032 | I34: 522.967 | J34: 525.6 | K34: items/airfryer-032-scene-0113/clip.mp4 | L34: items/airfryer-032-scene-0113/thumbnail.jpg | M34: ASR: airflow of the vents then I let it sit overnight to dry before we used it again if you like these VLM: Visual summary: A person is holding a black air fryer basket while standing next to a black air fryer on a kitchen countertop. 视觉摘要: 一个人正拿着一个黑色空气炸锅篮子，站在厨房台面上的黑色空气炸锅旁边。 Visible product: Air Fryer Visible components: black air fryer basket; black air fryer; kitchen countertop; person's hand; person's arm; red sleeve Visible actions: person holding air fryer basket | N34: 33 | O34: 1 | R34: The scene shows a person holding an air fryer basket next to the air fryer, but no temperature or time settings are visible or mentioned. | S34: VLM | T34: low | U34: No evidence of temperature or time setting actions or instructions is present. | V34: R1 | W34: 1 | Z34: no | AA34: 所有6帧（t=523.0s-525.6s）显示手持有空炸篮站在空气炸锅旁，但控制面板/温度/时间数字均不可见，ASR仅涉及通风口和干燥过夜。 | AC34: completed | AD34: 2026-07-28T01:18:39+08:00 | AE34: =IF(AC34<>"completed","",IF(W34=O34,"no","yes")) | AF34: =IF(AC34<>"completed","",IF(AND(X34=P34,Y34=Q34),"no","yes")) | AG34: =IF(AC34<>"completed","待复核",IF(OR(W34="",Z34="",AA34="",AD34=""),"缺少必填项",IF(AND(OR(AE34="yes",AF34="yes"),AB34=""),"修正原因缺失",IF(OR(W34=0,W34=1),IF(AND(X34="",Y34=""),"通过","0/1级时间应留空"),IF(AND(OR(W34=2,W34=3),X34<>"",Y34<>"",X34>=I34,Y34<=J34,Y34>X34),"通过","2/3级时间无效")))))
A35: VQ-001 | B35: 空气炸锅怎样设置烹饪温度和时间？ | C35: zh-CN | D35: Air Fryer | E35: operation | F35: development | G35: airfryer-033-scene-0149 | H35: airfryer-033 | I35: 1314.581 | J35: 1319.119 | K35: items/airfryer-033-scene-0149/clip.mp4 | L35: items/airfryer-033-scene-0149/thumbnail.jpg | M35: ASR: tá, abrindo a minha gaveta, tá também o problema é que tá querendo dar uma beiçada vamos botar a batata rústica OCR: 200 POILIPS WALTA VLM: Visual summary: A black air fryer with its basket open, displaying a digital temperature of 200°C on its control panel. 视觉摘要: 一台黑色空气炸锅，篮子打开，控制面板显示温度为200°C。 Visible product: Air Fryer Visible components: digital display; temperature reading; control buttons; air fryer basket; air fryer body; brand name Visible states: basket open; temperature set to 200°C | N35: 34 | O35: 3 | P35: 1314.581 | Q35: 1319.119 | R35: The air fryer's digital display shows a temperature setting of 200°C, and the basket is open, indicating the user is setting or preparing to cook with a specific temperature and time (implied by context of cooking potatoes). | S35: VLM|ASR|OCR | T35: low | U35: The visual and OCR evidence clearly show the temperature setting, and the ASR mentions preparing food, which aligns with the question about setting temperature and time. | V35: R1 | W35: 2 | X35: 1314.6 | Y35: 1319.119 | Z35: no | AA35: 第1-6帧（t=1314.6s-1319.2s）黑色WALITA空气炸锅控制面板显示'200°C'及温度图标，但无时间数字可见也未演示设置过程；ASR仅说打开抽屉放土豆。 | AB35: AI=3→R1=2：仅显示温度结果'200°C'且无时间、无线下设置步骤，无法直接回答'如何设置温度和时间'，故判为部分。 | AC35: completed | AD35: 2026-07-28T01:18:39+08:00 | AE35: =IF(AC35<>"completed","",IF(W35=O35,"no","yes")) | AF35: =IF(AC35<>"completed","",IF(AND(X35=P35,Y35=Q35),"no","yes")) | AG35: =IF(AC35<>"completed","待复核",IF(OR(W35="",Z35="",AA35="",AD35=""),"缺少必填项",IF(AND(OR(AE35="yes",AF35="yes"),AB35=""),"修正原因缺失",IF(OR(W35=0,W35=1),IF(AND(X35="",Y35=""),"通过","0/1级时间应留空"),IF(AND(OR(W35=2,W35=3),X35<>"",Y35<>"",X35>=I35,Y35<=J35,Y35>X35),"通过","2/3级时间无效")))))
A36: VQ-001 | B36: 空气炸锅怎样设置烹饪温度和时间？ | C36: zh-CN | D36: Air Fryer | E36: operation | F36: development | G36: airfryer-033-scene-0152 | H36: airfryer-033 | I36: 1338.539 | J36: 1375.409 | K36: items/airfryer-033-scene-0152/clip.mp4 | L36: items/airfryer-033-scene-0152/thumbnail.jpg | M36: ASR: Aqui é 9 minutos meu parceiro 9 não Está com problema no display Do nada Olha a contagem Ele começa 1, 2, 3, 4 O 4 já vira um tetri O 5 já zoado O 6 O 8 morreu O 8 vira 3 O 9 vira 3 Vou botar 12 minutos 12 minutos e deu a rodada eu vou deixar gravando aqui vou deixar OCR: D wALTA SUNG WALITA a NG VLM: Visual summary: A hand interacts with a black air fryer placed on top of a washing machine, adjusting its control panel. 视觉摘要: 一只手与放在洗衣机上的黑色空气炸锅互动，调整其控制面板。 Visible product: Air Fryer Visible components: black air fryer; control panel with illuminated buttons; clothespin on top of air fryer; washing machine; gray bag; white bucket Visible actions: hand touching air fryer; hand pressing buttons on control panel Visible states: air fryer displaying time; air fryer displaying temperature | N36: 35 | O36: 2 | P36: 1338.539 | Q36: 1375.409 | R36: The video shows a hand adjusting the air fryer's control panel, with visible time and temperature display, and ASR mentions setting time (e.g., '9 minutos', '12 minutos'), indicating a step in setting cooking time, but no explicit temperature setting is shown or mentioned. | S36: VLM|ASR | T36: low | U36: No explicit temperature setting is shown or mentioned in the evidence, only time settings. | V36: R1 | W36: 2 | X36: 1345.9 | Y36: 1368.0 | Z36: no | AA36: 第2-5帧（t=1345.9s-1368.0s）显示手按压WALITA空气炸锅触摸按钮，ASR明确说'Aqui é 9 minutos'、'Vou botar 12 minutos'涉及时间设置，但未见温度设置演示。 | AB36: AI时间1338.539-1375.409→R1时间1345.9s-1368.0s（按接触表帧标签），AI=X范围过大。 | AC36: completed | AD36: 2026-07-28T01:18:39+08:00 | AE36: =IF(AC36<>"completed","",IF(W36=O36,"no","yes")) | AF36: =IF(AC36<>"completed","",IF(AND(X36=P36,Y36=Q36),"no","yes")) | AG36: =IF(AC36<>"completed","待复核",IF(OR(W36="",Z36="",AA36="",AD36=""),"缺少必填项",IF(AND(OR(AE36="yes",AF36="yes"),AB36=""),"修正原因缺失",IF(OR(W36=0,W36=1),IF(AND(X36="",Y36=""),"通过","0/1级时间应留空"),IF(AND(OR(W36=2,W36=3),X36<>"",Y36<>"",X36>=I36,Y36<=J36,Y36>X36),"通过","2/3级时间无效")))))
A37: VQ-001 | B37: 空气炸锅怎样设置烹饪温度和时间？ | C37: zh-CN | D37: Air Fryer | E37: operation | F37: development | G37: airfryer-032-scene-0039 | H37: airfryer-032 | I37: 176.367 | J37: 179.167 | K37: items/airfryer-032-scene-0039/clip.mp4 | L37: items/airfryer-032-scene-0039/thumbnail.jpg | M37: ASR: about a tablespoon or two of lemon juice, place it in the air fryer basket, and run it for five to ten minutes at 400 degrees. You might have to do this a few times before the smell goes away. VLM: Visual summary: A close-up of a black COSORI air fryer's control panel, showing a digital display reading 400°F and a finger pressing a button. 视觉摘要: 一台黑色COSORI空气炸锅的控制面板特写，显示屏显示400°F，一根手指正在按压按钮。 Visible product: COSORI Visible components: digital display; touch buttons; brand logo; finger Visible actions: pressing a button Visible states: display showing 400°F; display showing '5.' | N37: 36 | O37: 3 | P37: 176.367 | Q37: 179.167 | R37: The VLM shows a digital display reading 400°F and a finger pressing a button, while ASR confirms setting the air fryer to 400 degrees for 5-10 minutes, directly demonstrating how to set temperature and time. | S37: VLM|ASR | T37: low | U37: Full scene evidence clearly shows temperature setting (400°F) and time setting (5-10 minutes) with visual and audio confirmation. | V37: R1 | W37: 3 | X37: 177.5 | Y37: 178.6 | Z37: no | AA37: 第3-5帧（t=177.5s-178.6s）COSORI空气炸锅显示屏清晰显示'400°F'与数字'5'，且ASR同步说明'run it for five to ten minutes at 400 degrees'，直接回答温度与时间设置。 | AB37: 时间按实际证据片段重定位 | AC37: completed | AD37: 2026-07-28T01:18:39+08:00 | AE37: =IF(AC37<>"completed","",IF(W37=O37,"no","yes")) | AF37: =IF(AC37<>"completed","",IF(AND(X37=P37,Y37=Q37),"no","yes")) | AG37: =IF(AC37<>"completed","待复核",IF(OR(W37="",Z37="",AA37="",AD37=""),"缺少必填项",IF(AND(OR(AE37="yes",AF37="yes"),AB37=""),"修正原因缺失",IF(OR(W37=0,W37=1),IF(AND(X37="",Y37=""),"通过","0/1级时间应留空"),IF(AND(OR(W37=2,W37=3),X37<>"",Y37<>"",X37>=I37,Y37<=J37,Y37>X37),"通过","2/3级时间无效")))))
A38: VQ-001 | B38: 空气炸锅怎样设置烹饪温度和时间？ | C38: zh-CN | D38: Air Fryer | E38: operation | F38: development | G38: airfryer-027-scene-0001 | H38: airfryer-027 | I38: 0.0 | J38: 7.508 | K38: items/airfryer-027-scene-0001/clip.mp4 | L38: items/airfryer-027-scene-0001/thumbnail.jpg | M38: OCR: Air Fryer vs. Baked Buffalo Wings? First, oven cooked wings VLM: Visual summary: A video title card introduces a comparison between air fryer and baked buffalo wings, followed by a slide indicating the first method is oven cooking. 视觉摘要: 视频标题卡介绍了空气炸锅与烤制的布法罗鸡翅的对比，随后显示第一种方法是烤箱烹饪。 Visible product: Air Fryer | N38: 37 | O38: 0 | R38: 视频仅介绍空气炸锅与烤箱烹饪的对比，未展示如何设置温度和时间。 | S38: VLM | T38: low | U38: 无任何关于设置温度或时间的操作步骤或视觉/语音证据。 | V38: R1 | W38: 0 | Z38: no | AA38: 0-80%帧仅显示标题字幕'Air Fryer vs. Baked Buffalo Wings?'；100%帧（t=7.5s）显示烤盘上的生鸡翅文字'First, oven cooked wings'，画面无空气炸锅操作内容。 | AC38: completed | AD38: 2026-07-28T01:18:39+08:00 | AE38: =IF(AC38<>"completed","",IF(W38=O38,"no","yes")) | AF38: =IF(AC38<>"completed","",IF(AND(X38=P38,Y38=Q38),"no","yes")) | AG38: =IF(AC38<>"completed","待复核",IF(OR(W38="",Z38="",AA38="",AD38=""),"缺少必填项",IF(AND(OR(AE38="yes",AF38="yes"),AB38=""),"修正原因缺失",IF(OR(W38=0,W38=1),IF(AND(X38="",Y38=""),"通过","0/1级时间应留空"),IF(AND(OR(W38=2,W38=3),X38<>"",Y38<>"",X38>=I38,Y38<=J38,Y38>X38),"通过","2/3级时间无效")))))
A39: VQ-001 | B39: 空气炸锅怎样设置烹饪温度和时间？ | C39: zh-CN | D39: Air Fryer | E39: operation | F39: development | G39: airfryer-002-scene-0009 | H39: airfryer-002 | I39: 241.808 | J39: 257.424 | K39: items/airfryer-002-scene-0009/clip.mp4 | L39: items/airfryer-002-scene-0009/thumbnail.jpg | M39: ASR: spray we're now going to place our cookies in the basket seam side down we're going to cook OCR: •ner Library Kitchen Chef itchen Puff Pastry SHEETS OREO VLM: Visual summary: A person wearing a blue apron holds an air fryer basket containing several round, pale yellow food items, with a yellow spray can on a silicone mat nearby. 视觉摘要: 一个人穿着蓝色围裙，手持一个装有数个圆形淡黄色食物的空气炸锅篮子，旁边硅胶垫上放着一个黄色喷雾罐。 Visible product: Air Fryer Visible components: air fryer basket; silicone mat; yellow spray can; blue apron with text; watch Visible actions: holding the air fryer basket; placing food items into the basket Visible states: food items inside the basket; basket being held open | N39: 38 | O39: 1 | R39: The scene shows food being placed into the air fryer basket but does not show any temperature or time settings being adjusted or displayed. | S39: VLM|ASR | T39: low | U39: No evidence of temperature or time settings being configured or shown. | V39: R1 | W39: 1 | Z39: no | AA39: 画面显示人手把圆形食物放入黑色空气炸篮，但空气炸锅控制面板/温度/时间均不在画面中，ASR仅说'place our cookies in the basket seam side down'，未涉及温度/时间设置。 | AC39: completed | AD39: 2026-07-28T01:18:39+08:00 | AE39: =IF(AC39<>"completed","",IF(W39=O39,"no","yes")) | AF39: =IF(AC39<>"completed","",IF(AND(X39=P39,Y39=Q39),"no","yes")) | AG39: =IF(AC39<>"completed","待复核",IF(OR(W39="",Z39="",AA39="",AD39=""),"缺少必填项",IF(AND(OR(AE39="yes",AF39="yes"),AB39=""),"修正原因缺失",IF(OR(W39=0,W39=1),IF(AND(X39="",Y39=""),"通过","0/1级时间应留空"),IF(AND(OR(W39=2,W39=3),X39<>"",Y39<>"",X39>=I39,Y39<=J39,Y39>X39),"通过","2/3级时间无效")))))
A40: VQ-001 | B40: 空气炸锅怎样设置烹饪温度和时间？ | C40: zh-CN | D40: Air Fryer | E40: operation | F40: development | G40: airfryer-006-scene-0006 | H40: airfryer-006 | I40: 19.92 | J40: 24.358 | K40: items/airfryer-006-scene-0006/clip.mp4 | L40: items/airfryer-006-scene-0006/thumbnail.jpg | M40: ASR: Here it goes. Flip and cook for maybe a minute or two more till brown. Come with powdered sugar, ready to serve. OCR: GMA 5 FLIP AND COOK FOR AN ADDITIONAL 1-2 MINUTES VLM: Visual summary: A hand is shown interacting with an air fryer, first pulling out a drawer, then using tongs to flip food items inside the basket. 视觉摘要: 一只手正在操作空气炸锅，先是拉出抽屉，然后用夹子翻动锅内的食物。 Visible product: Air Fryer Visible components: air fryer; drawer; basket; tongs; food items; GMA logo Visible actions: pulling out drawer; flipping food with tongs Visible states: food items in basket; drawer partially open Visible warnings: 5 FLIP AND COOK FOR AN ADDITIONAL 1-2 MINUTES | N40: 39 | O40: 1 | R40: The scene shows flipping food and a timer instruction (1-2 minutes), but no temperature or time setting is shown or mentioned. | S40: ASR|OCR|VLM | T40: low | U40: No evidence of temperature or time setting action or display. | V40: R1 | W40: 1 | Z40: no | AA40: 第1帧 t=19.9s 炸篮中已有面团，第3-5帧 t=21.7s-23.5s 显示用夹子翻动食物，但全程未出现温度或时间设置界面/操作。 | AC40: completed | AD40: 2026-07-28T01:18:39+08:00 | AE40: =IF(AC40<>"completed","",IF(W40=O40,"no","yes")) | AF40: =IF(AC40<>"completed","",IF(AND(X40=P40,Y40=Q40),"no","yes")) | AG40: =IF(AC40<>"completed","待复核",IF(OR(W40="",Z40="",AA40="",AD40=""),"缺少必填项",IF(AND(OR(AE40="yes",AF40="yes"),AB40=""),"修正原因缺失",IF(OR(W40=0,W40=1),IF(AND(X40="",Y40=""),"通过","0/1级时间应留空"),IF(AND(OR(W40=2,W40=3),X40<>"",Y40<>"",X40>=I40,Y40<=J40,Y40>X40),"通过","2/3级时间无效")))))
A41: VQ-001 | B41: 空气炸锅怎样设置烹饪温度和时间？ | C41: zh-CN | D41: Air Fryer | E41: operation | F41: development | G41: airfryer-026-scene-0001 | H41: airfryer-026 | I41: 0.0 | J41: 213.46 | K41: items/airfryer-026-scene-0001/clip.mp4 | L41: items/airfryer-026-scene-0001/thumbnail.jpg | M41: ASR: Montana Happy New Year and today we're going to be making air fryer doughnuts. For the doughnuts the ingredients are flour, baking powder, salt, and yogurt. Your first step is to combine your flour, baking powder, and salt and then mix well. Add your vanilla yogurt and then mix well. Now that it's all combined knead with your hands. Now that you have your dough in a bowl divide into four equal parts. Now with each ball roll into six to eight inch ropes. Now that the ropes are done, spray the inside of your air fryer basket and then you want to preheat it to 350. Now that your air fryer is preheating, lightly spray your ropes. Now shape them like a donut. Now put them in your air fryer and then set a timer for eight minutes. At four minutes flip over your donuts. The The ingredients for the doughnut glaze are powdered sugar, melted butter, vanilla, and hot water. Now combine all your glaze frosting ingredients. Now that they're done, take them out and let them slightly cool before you glaze. Now dip the top of your doughnut in your glaze and then let it drip. Now that it's all done, let's give it a try. That's good. OCR: MONTEREY play! RECREATION That's Good! with Montana 2 NONTEREY CA 3 REY MONTION DA REC 2n2n oq MONREY RECRTION RECATION NOUAD 2020 MONEREY RECRITION TNOA LBURVMO MONIREY BEHONEREY OPT RECRTION 2MC DRE MO RE MONCREY DRECATN BENGUA 2n120 20MC on BINGRADE IBURVIMD N O DEMONTEREY TRECRATION 2n20 12 IONTEREY ECREATION M( Montana E 1889 SAMS a IONVIVD UNGADE CARECREATION ILIGRADE LSURVIVED HONTEREY DA RECREATION Air Fryer Donuts 1 cup all-purpose flour 1 1/2 teaspoons baking powder 1/2 teaspoon salt 3/4 cup Greek yoqurt (plain or vanilla) Gaze 2 tablespoons butter, melted 1/2 cup powdered sugar 1/2 teaspoon vanilla 1/2 tablespoon hot water #showushowyouplayMonterey Thank you for watching! VLM: Visual summary: A person in a kitchen is preparing dough for donuts, with a recipe for 'Air Fryer Donuts' displayed on screen. 视觉摘要: 一个人在厨房里准备制作甜甜圈的面团，屏幕上显示了“空气炸锅甜甜圈”的食谱。 Visible product: Air Fryer Visible components: wooden cutting board; dough; air fryer; refrigerator; wooden cabinets; apron; beanie; recipe text Visible actions: person shaping dough into a ring; person standing in kitchen Visible states: dough shaped into rings and sticks; recipe displayed on screen | N41: 40 | O41: 2 | P41: 107.2 | Q41: 113.8 | R41: ASR states: 'you want to preheat it to 350' and 'set a timer for eight minutes', which directly addresses setting temperature and time for air fryer operation. | S41: ASR | T41: low | U41: The ASR text clearly specifies temperature (350) and time (8 minutes) for the air fryer, matching the question's intent. | V41: R1 | W41: 1 | Z41: no | AA41: 联系表第3帧 t=85.4s 仅见人物在空气炸锅旁，第4帧 t=128.1s 展示将食物放入炸篮，但所有帧均未展示温度/时间设置操作或界面。 | AB41: AI等级为2，但联系表未出现设置温度/时间的画面，提供的ASR文本也未完整展示具体设置内容，不能评为2。 | AC41: completed | AD41: 2026-07-28T01:18:39+08:00 | AE41: =IF(AC41<>"completed","",IF(W41=O41,"no","yes")) | AF41: =IF(AC41<>"completed","",IF(AND(X41=P41,Y41=Q41),"no","yes")) | AG41: =IF(AC41<>"completed","待复核",IF(OR(W41="",Z41="",AA41="",AD41=""),"缺少必填项",IF(AND(OR(AE41="yes",AF41="yes"),AB41=""),"修正原因缺失",IF(OR(W41=0,W41=1),IF(AND(X41="",Y41=""),"通过","0/1级时间应留空"),IF(AND(OR(W41=2,W41=3),X41<>"",Y41<>"",X41>=I41,Y41<=J41,Y41>X41),"通过","2/3级时间无效")))))
A42: VQ-001 | B42: 空气炸锅怎样设置烹饪温度和时间？ | C42: zh-CN | D42: Air Fryer | E42: operation | F42: development | G42: airfryer-024-scene-0025 | H42: airfryer-024 | I42: 109.109 | J42: 112.846 | K42: items/airfryer-024-scene-0025/clip.mp4 | L42: items/airfryer-024-scene-0025/thumbnail.jpg | M42: ASR: the New Wave Brio Digital Air Fryer is the undisputed leader. With features, technology, and value, no other air fryer comes close. OCR: Brio Time Lapse Roasted Vegetables 20 minutes VLM: Visual summary: A hand holds the basket of an air fryer containing roasted vegetables, with a time-lapse overlay indicating the cooking process is complete. 视觉摘要: 一只手拿着空气炸锅的篮子，里面装着烤蔬菜，叠加的时间快照显示烹饪过程已完成。 Visible product: Air Fryer Visible components: air fryer basket; roasted vegetables; hand; text overlay Visible actions: holding the air fryer basket Visible states: cooking complete (indicated by text overlay) | N42: 41 | O42: 1 | R42: The scene shows the air fryer basket with roasted vegetables and a time-lapse overlay indicating '20 minutes' as the cooking time, but no explicit instruction or setting of temperature or time is shown or spoken. | S42: VLM|OCR|ASR | T42: low | U42: No visible or spoken evidence of temperature setting or time adjustment during operation. | V42: R1 | W42: 1 | Z42: no | AA42: 所有帧均显示'Brio Time Lapse Roasted Vegetables 20 minutes'文字及烤好的蔬菜，未出现温度设置或时间调节操作。 | AC42: completed | AD42: 2026-07-28T01:18:39+08:00 | AE42: =IF(AC42<>"completed","",IF(W42=O42,"no","yes")) | AF42: =IF(AC42<>"completed","",IF(AND(X42=P42,Y42=Q42),"no","yes")) | AG42: =IF(AC42<>"completed","待复核",IF(OR(W42="",Z42="",AA42="",AD42=""),"缺少必填项",IF(AND(OR(AE42="yes",AF42="yes"),AB42=""),"修正原因缺失",IF(OR(W42=0,W42=1),IF(AND(X42="",Y42=""),"通过","0/1级时间应留空"),IF(AND(OR(W42=2,W42=3),X42<>"",Y42<>"",X42>=I42,Y42<=J42,Y42>X42),"通过","2/3级时间无效")))))
A43: VQ-002 | B43: How should food be loaded into an air-fryer basket? | C43: en | D43: Air Fryer | E43: operation | F43: development | G43: airfryer-026-scene-0001 | H43: airfryer-026 | I43: 0.0 | J43: 213.46 | K43: items/airfryer-026-scene-0001/clip.mp4 | L43: items/airfryer-026-scene-0001/thumbnail.jpg | M43: ASR: Montana Happy New Year and today we're going to be making air fryer doughnuts. For the doughnuts the ingredients are flour, baking powder, salt, and yogurt. Your first step is to combine your flour, baking powder, and salt and then mix well. Add your vanilla yogurt and then mix well. Now that it's all combined knead with your hands. Now that you have your dough in a bowl divide into four equal parts. Now with each ball roll into six to eight inch ropes. Now that the ropes are done, spray the inside of your air fryer basket and then you want to preheat it to 350. Now that your air fryer is preheating, lightly spray your ropes. Now shape them like a donut. Now put them in your air fryer and then set a timer for eight minutes. At four minutes flip over your donuts. The The ingredients for the doughnut glaze are powdered sugar, melted butter, vanilla, and hot water. Now combine all your glaze frosting ingredients. Now that they're done, take them out and let them slightly cool before you glaze. Now dip the top of your doughnut in your glaze and then let it drip. Now that it's all done, let's give it a try. That's good. OCR: MONTEREY play! RECREATION That's Good! with Montana 2 NONTEREY CA 3 REY MONTION DA REC 2n2n oq MONREY RECRTION RECATION NOUAD 2020 MONEREY RECRITION TNOA LBURVMO MONIREY BEHONEREY OPT RECRTION 2MC DRE MO RE MONCREY DRECATN BENGUA 2n120 20MC on BINGRADE IBURVIMD N O DEMONTEREY TRECRATION 2n20 12 IONTEREY ECREATION M( Montana E 1889 SAMS a IONVIVD UNGADE CARECREATION ILIGRADE LSURVIVED HONTEREY DA RECREATION Air Fryer Donuts 1 cup all-purpose flour 1 1/2 teaspoons baking powder 1/2 teaspoon salt 3/4 cup Greek yoqurt (plain or vanilla) Gaze 2 tablespoons butter, melted 1/2 cup powdered sugar 1/2 teaspoon vanilla 1/2 tablespoon hot water #showushowyouplayMonterey Thank you for watching! VLM: Visual summary: A person in a kitchen is preparing dough for donuts, with a recipe for 'Air Fryer Donuts' displayed on screen. 视觉摘要: 一个人在厨房里准备制作甜甜圈的面团，屏幕上显示了“空气炸锅甜甜圈”的食谱。 Visible product: Air Fryer Visible components: wooden cutting board; dough; air fryer; refrigerator; wooden cabinets; apron; beanie; recipe text Visible actions: person shaping dough into a ring; person standing in kitchen Visible states: dough shaped into rings and sticks; recipe displayed on screen | N43: 1 | O43: 2 | P43: 112.0 | Q43: 120.0 | R43: ASR states: 'spray the inside of your air fryer basket and then you want to preheat it to 350.' This indicates a preparatory step for loading food, but does not show how food is loaded into the basket. | S43: ASR | T43: low | U43: The evidence describes spraying the basket and preheating, but does not show the actual loading of food into the basket. | V43: R1 | W43: 2 | X43: 128.1 | Y43: 170.7 | Z43: no | AA43: 第4帧 t=128.1s 清晰展示将食物放入空气炸锅炸篮，第5帧 t=170.7s 仍在烹饪过程中，可认为装载状态持续。 | AB43: AI将时间标为112.0-120.0s，但联系表仅在128.1s清晰展示装载动作，故调整X/Y。 | AC43: completed | AD43: 2026-07-28T01:18:39+08:00 | AE43: =IF(AC43<>"completed","",IF(W43=O43,"no","yes")) | AF43: =IF(AC43<>"completed","",IF(AND(X43=P43,Y43=Q43),"no","yes")) | AG43: =IF(AC43<>"completed","待复核",IF(OR(W43="",Z43="",AA43="",AD43=""),"缺少必填项",IF(AND(OR(AE43="yes",AF43="yes"),AB43=""),"修正原因缺失",IF(OR(W43=0,W43=1),IF(AND(X43="",Y43=""),"通过","0/1级时间应留空"),IF(AND(OR(W43=2,W43=3),X43<>"",Y43<>"",X43>=I43,Y43<=J43,Y43>X43),"通过","2/3级时间无效")))))
A44: VQ-002 | B44: How should food be loaded into an air-fryer basket? | C44: en | D44: Air Fryer | E44: operation | F44: development | G44: airfryer-032-scene-0036 | H44: airfryer-032 | I44: 166.9 | J44: 171.667 | K44: items/airfryer-032-scene-0036/clip.mp4 | L44: items/airfryer-032-scene-0036/thumbnail.jpg | M44: ASR: ago simply get an oven safe bowl and pour about half to a cup of white vinegar in it then add OCR: Realemon 100 LEMON jUIC! VLM: Visual summary: A person is pouring liquid from a white jug into a small glass bowl, then placing the bowl inside an open air fryer basket. 视觉摘要: 一个人将液体从白色壶中倒入一个小玻璃碗，然后将碗放入打开的空气炸锅篮中。 Visible product: Air Fryer Visible components: air fryer; air fryer basket; glass bowl; white jug; marble countertop; wooden chairs Visible actions: pouring liquid; holding bowl; placing bowl in basket Visible states: air fryer open; liquid in bowl; bowl inside basket | N44: 2 | O44: 2 | P44: 166.9 | Q44: 171.667 | R44: The visual shows a bowl being placed inside the air fryer basket, which is an adjacent step to loading food, but the action is not loading food itself and the bowl contains vinegar, not food. | S44: VLM | T44: low | U44: The action of placing a bowl inside the basket is visually present, but the bowl does not contain food, so it does not directly answer how food should be loaded. | V44: R1 | W44: 1 | Z44: no | AA44: 第1-6帧 t=166.9s-171.7s 显示将液体倒入小碗后把小碗放进炸篮，未见食物装载。 | AB44: AI等级为2，但画面展示的是放入盛有液体的碗而非食物，不能回答如何装载食物。 | AC44: completed | AD44: 2026-07-28T01:18:39+08:00 | AE44: =IF(AC44<>"completed","",IF(W44=O44,"no","yes")) | AF44: =IF(AC44<>"completed","",IF(AND(X44=P44,Y44=Q44),"no","yes")) | AG44: =IF(AC44<>"completed","待复核",IF(OR(W44="",Z44="",AA44="",AD44=""),"缺少必填项",IF(AND(OR(AE44="yes",AF44="yes"),AB44=""),"修正原因缺失",IF(OR(W44=0,W44=1),IF(AND(X44="",Y44=""),"通过","0/1级时间应留空"),IF(AND(OR(W44=2,W44=3),X44<>"",Y44<>"",X44>=I44,Y44<=J44,Y44>X44),"通过","2/3级时间无效")))))
A45: VQ-002 | B45: How should food be loaded into an air-fryer basket? | C45: en | D45: Air Fryer | E45: operation | F45: development | G45: airfryer-033-scene-0039 | H45: airfryer-033 | I45: 276.043 | J45: 281.014 | K45: items/airfryer-033-scene-0039/clip.mp4 | L45: items/airfryer-033-scene-0039/thumbnail.jpg | M45: ASR: Então, sim Vou tirar essas coisas aqui aqui vou botar lá já vou lavar entendeu isso aqui eu vou tirar na real dá para tirar tudo VLM: Visual summary: A close-up view of an air fryer with its basket partially pulled out, showing food remnants inside the basket and the interior of the appliance. 视觉摘要: 空气炸锅的特写，其篮子部分拉出，篮子内和炸锅内部可见食物残渣。 Visible product: Air Fryer Visible components: air fryer basket; air fryer interior; air fryer handle; food remnants; brand name 'PHILIPS' and 'WALLA' on the appliance Visible actions: a hand is holding the air fryer handle Visible states: air fryer basket partially pulled out; food remnants inside the basket | N45: 3 | O45: 2 | P45: 276.043 | Q45: 281.014 | R45: The basket is partially pulled out and contains food remnants, and the ASR indicates the speaker is removing items and preparing to load or wash, suggesting the context of loading food into the basket. | S45: VLM|ASR | T45: low | U45: The visual shows the basket partially pulled out with food remnants, and the ASR implies removal and preparation for loading, but does not explicitly show the correct method of loading food. | V45: R1 | W45: 0 | Z45: no | AA45: 第1-6帧 t=276.0s-281.0s 展示炸篮被拉出，篮内及底部有食物残渣和油渍，属于餐后清理而非装载。 | AB45: AI等级为2，但画面展示的是烹饪结束后取出/清理炸篮，与'如何装入食物'方向相反，不能作为相邻步骤回答。 | AC45: completed | AD45: 2026-07-28T01:18:39+08:00 | AE45: =IF(AC45<>"completed","",IF(W45=O45,"no","yes")) | AF45: =IF(AC45<>"completed","",IF(AND(X45=P45,Y45=Q45),"no","yes")) | AG45: =IF(AC45<>"completed","待复核",IF(OR(W45="",Z45="",AA45="",AD45=""),"缺少必填项",IF(AND(OR(AE45="yes",AF45="yes"),AB45=""),"修正原因缺失",IF(OR(W45=0,W45=1),IF(AND(X45="",Y45=""),"通过","0/1级时间应留空"),IF(AND(OR(W45=2,W45=3),X45<>"",Y45<>"",X45>=I45,Y45<=J45,Y45>X45),"通过","2/3级时间无效")))))
A46: VQ-002 | B46: How should food be loaded into an air-fryer basket? | C46: en | D46: Air Fryer | E46: operation | F46: development | G46: airfryer-029-scene-0050 | H46: airfryer-029 | I46: 307.84 | J46: 311.96 | K46: items/airfryer-029-scene-0050/clip.mp4 | L46: items/airfryer-029-scene-0050/thumbnail.jpg | M46: ASR: pull the basket out and in this you know just arrange the chicken pieces in such a way they kind of in a standing position kind of thing and if something OCR: HILIDS VLM: Visual summary: A person is placing seasoned food into the basket of a black air fryer on a kitchen counter. 视觉摘要: 一个人正在将调味好的食物放入黑色空气炸锅的篮子中，位于厨房台面上。 Visible product: Air Fryer Visible components: air fryer; air fryer basket; green plate; hand; Philips logo; Philips Super Chef logo; kitchen counter; refrigerator; blender; rice cooker; cabinet Visible actions: placing food into air fryer basket; reaching for food on plate Visible states: food coated in seasoning; air fryer basket partially filled | N46: 4 | O46: 2 | P46: 307.84 | Q46: 311.96 | R46: The ASR describes arranging chicken pieces in a standing position in the basket, and the VLM shows food being placed into the basket, indicating a loading method, though not explicitly detailing how to load food. | S46: VLM|ASR | T46: low | U46: The ASR provides partial instruction on arrangement, and VLM confirms the action of loading food into the basket, but does not specify loading technique for all food types or basket capacity. | V46: R1 | W46: 3 | X46: 307.84 | Y46: 311.96 | Z46: no | AA46: 第1-6帧 t=307.8s-312.0s 连续显示手将鸡块竖立摆放在炸篮中，ASR同步说明要竖立摆放。 | AB46: AI等级为2，但画面与语音从首帧到末帧持续展示并说明竖立摆放鸡肉的装载方式，应评为3。 | AC46: completed | AD46: 2026-07-28T01:18:39+08:00 | AE46: =IF(AC46<>"completed","",IF(W46=O46,"no","yes")) | AF46: =IF(AC46<>"completed","",IF(AND(X46=P46,Y46=Q46),"no","yes")) | AG46: =IF(AC46<>"completed","待复核",IF(OR(W46="",Z46="",AA46="",AD46=""),"缺少必填项",IF(AND(OR(AE46="yes",AF46="yes"),AB46=""),"修正原因缺失",IF(OR(W46=0,W46=1),IF(AND(X46="",Y46=""),"通过","0/1级时间应留空"),IF(AND(OR(W46=2,W46=3),X46<>"",Y46<>"",X46>=I46,Y46<=J46,Y46>X46),"通过","2/3级时间无效")))))
A47: VQ-002 | B47: How should food be loaded into an air-fryer basket? | C47: en | D47: Air Fryer | E47: operation | F47: development | G47: airfryer-005-scene-0021 | H47: airfryer-005 | I47: 202.502 | J47: 207.465 | K47: items/airfryer-005-scene-0021/clip.mp4 | L47: items/airfryer-005-scene-0021/thumbnail.jpg | M47: ASR: air fryer, the basket goes and then we set the temperature VLM: Visual summary: A person is placing an air fryer basket containing food into an air fryer appliance on a white countertop. 视觉摘要: 一个人将装有食物的空气炸锅篮子放入空气炸锅中，置于白色台面上。 Visible product: Air Fryer Visible components: air fryer basket; air fryer appliance; white countertop; white cutting board; glass bowl; eggshells Visible actions: placing air fryer basket into air fryer appliance | N47: 5 | O47: 2 | P47: 202.502 | Q47: 207.465 | R47: The visual shows a person placing an air fryer basket containing food into the air fryer appliance, which demonstrates the loading action, though no explicit instruction or step-by-step guidance is provided. | S47: VLM | T47: low | U47: The action is visible but lacks explicit verbal instruction or detailed guidance on how food should be loaded (e.g., arrangement, quantity, orientation). | V47: R1 | W47: 2 | X47: 202.502 | Y47: 207.465 | Z47: no | AA47: 画面全程为将已盛放食物的炸篮推入空气炸锅机身，展示的是炸篮入机动作，未展示食物如何摆入炸篮内部（无分层、朝向或装载技巧），属于相邻步骤。 | AC47: completed | AD47: 2026-07-27T22:01:34+08:00 | AE47: =IF(AC47<>"completed","",IF(W47=O47,"no","yes")) | AF47: =IF(AC47<>"completed","",IF(AND(X47=P47,Y47=Q47),"no","yes")) | AG47: =IF(AC47<>"completed","待复核",IF(OR(W47="",Z47="",AA47="",AD47=""),"缺少必填项",IF(AND(OR(AE47="yes",AF47="yes"),AB47=""),"修正原因缺失",IF(OR(W47=0,W47=1),IF(AND(X47="",Y47=""),"通过","0/1级时间应留空"),IF(AND(OR(W47=2,W47=3),X47<>"",Y47<>"",X47>=I47,Y47<=J47,Y47>X47),"通过","2/3级时间无效")))))
A48: VQ-002 | B48: How should food be loaded into an air-fryer basket? | C48: en | D48: Air Fryer | E48: operation | F48: development | G48: airfryer-005-scene-0015 | H48: airfryer-005 | I48: 162.344 | J48: 172.394 | K48: items/airfryer-005-scene-0015/clip.mp4 | L48: items/airfryer-005-scene-0015/thumbnail.jpg | M48: ASR: We will just pour it right there in the middle and then that should be contained. Pretty much if it spills over a little bit, that's OK. And do this other egg and come in here right in the basket, VLM: Visual summary: A man in a kitchen is preparing food in the basket of a black air fryer. 视觉摘要: 一名男子在厨房里，正在将食物放入黑色空气炸锅的篮子中。 Visible product: Air Fryer Visible components: black air fryer; air fryer basket; refrigerator; white kitchen cabinets; microwave; toaster oven; glass jars; knife block; sink; whey protein container Visible actions: man pouring liquid from a bottle into the air fryer basket; man cracking an egg into the air fryer basket Visible states: food in the air fryer basket; man holding an egg | N48: 6 | O48: 2 | P48: 162.344 | Q48: 172.394 | R48: The man is shown pouring liquid and cracking an egg into the air fryer basket, with ASR confirming food is poured 'right there in the middle' and minor spillage is acceptable. | S48: VLM|ASR | T48: low | U48: The visual and ASR evidence together show the action of loading food into the basket, but do not explicitly state 'how' to load it (e.g., layering, spacing, quantity limits). | V48: R1 | W48: 3 | X48: 162.344 | Y48: 172.394 | Z48: no | AA48: Frames show a man in a kitchen pouring liquid from a glass directly into the center of the air fryer basket (visible at t=162.3s, t=164.4s, t=172.4s) and holding a raw egg above the basket ready to crack it in (t=168.4s); ASR confirms 'pour it right there in the middle' of the basket. | AB48: Upgrade from 2 to 3: the scene directly demonstrates loading food (liquid + egg) into the air fryer basket with explicit placement guidance ('right there in the middle'), which is a complete visual answer to the query. | AC48: completed | AD48: 2026-07-28T01:18:39+08:00 | AE48: =IF(AC48<>"completed","",IF(W48=O48,"no","yes")) | AF48: =IF(AC48<>"completed","",IF(AND(X48=P48,Y48=Q48),"no","yes")) | AG48: =IF(AC48<>"completed","待复核",IF(OR(W48="",Z48="",AA48="",AD48=""),"缺少必填项",IF(AND(OR(AE48="yes",AF48="yes"),AB48=""),"修正原因缺失",IF(OR(W48=0,W48=1),IF(AND(X48="",Y48=""),"通过","0/1级时间应留空"),IF(AND(OR(W48=2,W48=3),X48<>"",Y48<>"",X48>=I48,Y48<=J48,Y48>X48),"通过","2/3级时间无效")))))
A49: VQ-002 | B49: How should food be loaded into an air-fryer basket? | C49: en | D49: Air Fryer | E49: operation | F49: development | G49: airfryer-006-scene-0004 | H49: airfryer-006 | I49: 10.878 | J49: 16.817 | K49: items/airfryer-006-scene-0004/clip.mp4 | L49: items/airfryer-006-scene-0004/thumbnail.jpg | M49: ASR: Your Oreos and crescent rolls. Make a little blanket. Press and make sure there's no air bubbles. Your air fryer, 350, four minutes for the first side. OCR: GMA AIR FRY AT 350°F FOR 4 MINUTES VLM: Visual summary: A person is wrapping Oreo cookies in crescent roll dough on a wooden cutting board. 视觉摘要: 一个人正在木制砧板上用牛角面包面团包裹奥利奥饼干。 Visible product: unknown Visible components: wooden cutting board; crescent roll dough; Oreo cookie; human hands Visible actions: wrapping; pressing Visible states: dough being wrapped around cookie; dough shaped into round form Visual uncertainty: The specific product being prepared is not identified, only the action of wrapping cookies in dough. | N49: 7 | O49: 0 | R49: The scene shows wrapping cookies in dough and mentions air-frying temperature and time, but does not show or describe loading food into an air-fryer basket. | S49: VLM|ASR|OCR | T49: low | U49: No evidence of air-fryer basket or loading action into it. | V49: R1 | W49: 0 | Z49: no | AA49: All six frames show hands wrapping Oreo cookies in crescent roll dough on a wooden cutting board; no air fryer device is visible in any frame, and no basket-loading action occurs. | AC49: completed | AD49: 2026-07-28T01:18:39+08:00 | AE49: =IF(AC49<>"completed","",IF(W49=O49,"no","yes")) | AF49: =IF(AC49<>"completed","",IF(AND(X49=P49,Y49=Q49),"no","yes")) | AG49: =IF(AC49<>"completed","待复核",IF(OR(W49="",Z49="",AA49="",AD49=""),"缺少必填项",IF(AND(OR(AE49="yes",AF49="yes"),AB49=""),"修正原因缺失",IF(OR(W49=0,W49=1),IF(AND(X49="",Y49=""),"通过","0/1级时间应留空"),IF(AND(OR(W49=2,W49=3),X49<>"",Y49<>"",X49>=I49,Y49<=J49,Y49>X49),"通过","2/3级时间无效")))))
A50: VQ-002 | B50: How should food be loaded into an air-fryer basket? | C50: en | D50: Air Fryer | E50: operation | F50: development | G50: airfryer-002-scene-0008 | H50: airfryer-002 | I50: 191.625 | J50: 241.808 | K50: items/airfryer-002-scene-0008/clip.mp4 | L50: items/airfryer-002-scene-0008/thumbnail.jpg | M50: ASR: bend that seal over and underneath on the bottom of the cookie. At that point you're going to put up just a little bit of an egg wash on the top and continue with all of your cookies. So I'm finishing up making my last cookie to put into the air fryer and you're going to want to preheat your fryer to 350 degrees and we're going to cook these for about seven minutes. So let's get that turned on and preheat it to 350. so our air fryer is preheated to 350 degrees we're going to take the basket out and spray it with a little non-stick spray we're now going to place our cookies in the basket seam side down we're going to cook OCR: Chef Library Kitchen Puff Pastry SHEETS OREO Lhrary Kitche Tray Library Kitchen VLM: Visual summary: A man in a blue apron is preparing food in a kitchen, with ingredients and an air fryer on the counter. 视觉摘要: 一名穿着蓝色围裙的男子在厨房准备食物，台面上有食材和空气炸锅。 Visible product: Air Fryer Visible components: air fryer; puff pastry box; OREO cookies package; powdered sugar container; silicone mat; plate with cookies; apron; glasses Visible actions: man shaping dough; man holding a spray can and a pan Visible states: dough pieces on mat; cookies on plate | N50: 8 | O50: 2 | P50: 191.625 | Q50: 241.808 | R50: ASR states 'we're going to place our cookies in the basket seam side down' and VLM shows cookies on a plate and man holding a spray can and pan, indicating preparation for loading into air fryer basket. | S50: ASR|VLM | T50: low | U50: No explicit visual or spoken instruction on how to arrange or load the food into the basket beyond 'place our cookies in the basket seam side down'. | V50: R1 | W50: 1 | Z50: no | AA50: 全部6帧（t=191.6s–241.8s）均为男子在台面上制作饼干（持饼、涂蛋液等），空气炸锅仅在背景中出现，全程无炸篮装载动作。 | AB50: 时间按实际证据片段重定位 | 第三轮双复核一致修正：等级不一致：R1=2→独立=1。该场景无任何食物装入炸篮的画面，仅产品出现在背景中。 | AC50: completed | AD50: 2026-07-28T20:35:21+08:00 | AE50: =IF(AC50<>"completed","",IF(W50=O50,"no","yes")) | AF50: =IF(AC50<>"completed","",IF(AND(X50=P50,Y50=Q50),"no","yes")) | AG50: =IF(AC50<>"completed","待复核",IF(OR(W50="",Z50="",AA50="",AD50=""),"缺少必填项",IF(AND(OR(AE50="yes",AF50="yes"),AB50=""),"修正原因缺失",IF(OR(W50=0,W50=1),IF(AND(X50="",Y50=""),"通过","0/1级时间应留空"),IF(AND(OR(W50=2,W50=3),X50<>"",Y50<>"",X50>=I50,Y50<=J50,Y50>X50),"通过","2/3级时间无效")))))
A51: VQ-002 | B51: How should food be loaded into an air-fryer basket? | C51: en | D51: Air Fryer | E51: operation | F51: development | G51: airfryer-017-scene-0022 | H51: airfryer-017 | I51: 164.264 | J51: 172.005 | K51: items/airfryer-017-scene-0022/clip.mp4 | L51: items/airfryer-017-scene-0022/thumbnail.jpg | M51: ASR: The major problem, as I found out a few months ago, was that one time the door fell open while I was cooking. So I'll be sure to tighten up the door during this process. process. First thing I'm going to do is remove these cooking trays. There we go. You can see my OCR: 2 ESES VLM: Visual summary: A hand opens the lid of a black and stainless steel air fryer sitting on a dark wooden table in a dining room. 视觉摘要: 一只手在餐厅的深色木桌上打开一个黑色和不锈钢空气炸锅的盖子。 Visible product: Air Fryer Visible components: air fryer; stainless steel exterior; black lid; dark wooden table; chairs; window with blinds; wall decorations; stuffed animals; dollhouse Visible actions: hand opening the air fryer lid Visible states: air fryer lid open; air fryer interior visible | N51: 9 | O51: 1 | R51: The scene shows the air fryer lid being opened, but no food loading action or instruction is visible or mentioned. | S51: VLM | T51: low | U51: No evidence of food being loaded into the basket. | V51: R1 | W51: 1 | Z51: no | AA51: 画面展示打开盖子与取出烤盘，但未展示往炸篮中放入食物的动作。 | AC51: completed | AD51: 2026-07-27T22:12:04+08:00 | AE51: =IF(AC51<>"completed","",IF(W51=O51,"no","yes")) | AF51: =IF(AC51<>"completed","",IF(AND(X51=P51,Y51=Q51),"no","yes")) | AG51: =IF(AC51<>"completed","待复核",IF(OR(W51="",Z51="",AA51="",AD51=""),"缺少必填项",IF(AND(OR(AE51="yes",AF51="yes"),AB51=""),"修正原因缺失",IF(OR(W51=0,W51=1),IF(AND(X51="",Y51=""),"通过","0/1级时间应留空"),IF(AND(OR(W51=2,W51=3),X51<>"",Y51<>"",X51>=I51,Y51<=J51,Y51>X51),"通过","2/3级时间无效")))))
A52: VQ-002 | B52: How should food be loaded into an air-fryer basket? | C52: en | D52: Air Fryer | E52: operation | F52: development | G52: airfryer-032-scene-0017 | H52: airfryer-032 | I52: 62.567 | J52: 65.333 | K52: items/airfryer-032-scene-0017/clip.mp4 | L52: items/airfryer-032-scene-0017/thumbnail.jpg | M52: ASR: an unexpected surprise left by one of my teenage boys here's a pro tip before you turn the preheat VLM: Visual summary: A black air fryer with its basket partially pulled out, showing some food residue inside. 视觉摘要: 一个黑色空气炸锅，其篮子部分拉出，内部可见一些食物残渣。 Visible product: Air Fryer Visible components: air fryer body; air fryer basket; perforated basket bottom; countertop Visible states: basket partially pulled out; food residue visible in basket | N52: 10 | O52: 1 | R52: The basket is partially pulled out and shows food residue, indicating it is not empty or clean before loading, but no instruction or demonstration of how to load food is visible or audible. | S52: VLM | T52: low | U52: No evidence of food being loaded or instructions given on loading procedure. | V52: R1 | W52: 1 | Z52: no | AA52: A hand pulls the air fryer basket open revealing food residue inside (t=63.1s–t=65.4s); the basket component is visible but no loading instruction or demonstration occurs — ASR references a 'pro tip before preheat' about leftover residue, not about loading food. | AC52: completed | AD52: 2026-07-28T01:18:39+08:00 | AE52: =IF(AC52<>"completed","",IF(W52=O52,"no","yes")) | AF52: =IF(AC52<>"completed","",IF(AND(X52=P52,Y52=Q52),"no","yes")) | AG52: =IF(AC52<>"completed","待复核",IF(OR(W52="",Z52="",AA52="",AD52=""),"缺少必填项",IF(AND(OR(AE52="yes",AF52="yes"),AB52=""),"修正原因缺失",IF(OR(W52=0,W52=1),IF(AND(X52="",Y52=""),"通过","0/1级时间应留空"),IF(AND(OR(W52=2,W52=3),X52<>"",Y52<>"",X52>=I52,Y52<=J52,Y52>X52),"通过","2/3级时间无效")))))
A53: VQ-002 | B53: How should food be loaded into an air-fryer basket? | C53: en | D53: Air Fryer | E53: operation | F53: development | G53: airfryer-017-scene-0067 | H53: airfryer-017 | I53: 840.273 | J53: 881.147 | K53: items/airfryer-017-scene-0067/clip.mp4 | L53: items/airfryer-017-scene-0067/thumbnail.jpg | M53: ASR: able to actually take these two halves of the top half of the unit apart, I'm actually just prying open the side and trying to pull it as far apart as I can, bend it apart without actually taking the two halves apart, if that makes any sense. So to get inside of this crack, I'm just stretching it sort of as far as the plastic allows me to stretch since I can't actually take these two pieces apart like I should be able to. And I'm going to actually do what I did last time. I'm going to pry these as far apart as I can and I'm going to hold it open with this deck of cards. This is sort of my zen and the art of motorcycle maintenance moment where anything that will do the job will do. It doesn't have to be sexy. I think the reason I chose a deck of cards last time was because I could make it as thick or as thin as I needed to for the job and then I could OCR: Visit us .co lewa 25th ZEN Amuiversary Edition AND THE ART SNOF MOTORCYCLE MAINTENANCE An Inquiry into Values With a New Introduction by the Author ROBERT M. PIRSIG newa Anniversary 11 OF An Inquiry into Values M. . PIRSIG VLM: Visual summary: A person is disassembling or repairing an electronic device with exposed internal components and wiring. 视觉摘要: 一个人正在拆卸或修理一个露出内部组件和电线的电子设备。 Visible product: Air Fryer Visible components: black plastic casing; electronic circuit board; wires; screwdriver; white ribbon cable; plastic component with number 11 Visible actions: using a screwdriver; handling internal components Visible states: device is partially disassembled Visual uncertainty: The specific model or brand of the air fryer is not visible. The exact purpose of the action is not clear from the frames. | N53: 11 | O53: 0 | R53: The scene shows disassembly of an electronic device with internal components, not loading food into an air-fryer basket. | S53: VLM | T53: low | U53: The visual evidence clearly depicts repair or disassembly, not food loading. | V53: R1 | W53: 0 | Z53: no | AA53: All six frames show hands using a screwdriver to disassemble a plastic electronic device casing, exposing internal wires and components; a 'Zen and the Art of Motorcycle Maintenance' book cover is visible at t=873.0s. This is electronics repair, completely unrelated to air fryers or food loading. | AC53: completed | AD53: 2026-07-28T01:18:39+08:00 | AE53: =IF(AC53<>"completed","",IF(W53=O53,"no","yes")) | AF53: =IF(AC53<>"completed","",IF(AND(X53=P53,Y53=Q53),"no","yes")) | AG53: =IF(AC53<>"completed","待复核",IF(OR(W53="",Z53="",AA53="",AD53=""),"缺少必填项",IF(AND(OR(AE53="yes",AF53="yes"),AB53=""),"修正原因缺失",IF(OR(W53=0,W53=1),IF(AND(X53="",Y53=""),"通过","0/1级时间应留空"),IF(AND(OR(W53=2,W53=3),X53<>"",Y53<>"",X53>=I53,Y53<=J53,Y53>X53),"通过","2/3级时间无效")))))
A54: VQ-002 | B54: How should food be loaded into an air-fryer basket? | C54: en | D54: Air Fryer | E54: operation | F54: development | G54: airfryer-002-scene-0010 | H54: airfryer-002 | I54: 257.424 | J54: 283.851 | K54: items/airfryer-002-scene-0010/clip.mp4 | L54: items/airfryer-002-scene-0010/thumbnail.jpg | M54: ASR: spray we're now going to place our cookies in the basket seam side down we're going to cook for seven minutes so it's been about seven minutes and i believe our cookies are about done So as you can see, the puff pastry is golden brown with a cookie in the middle. OCR: Lirary Riden Puff Pastry SHEETS OREO Chef Library Kitchen wnen VLM: Visual summary: A man in a blue apron stands behind a kitchen counter with an air fryer, ingredients, and kitchen tools. He gestures and interacts with the air fryer basket. 视觉摘要: 一名穿着蓝色围裙的男子站在厨房操作台前，台面上有空气炸锅、食材和厨具。他做出手势并与空气炸锅的篮子互动。 Visible product: Air Fryer Visible components: air fryer; air fryer basket; puff pastry sheets; OREO cookies; powdered sugar container; spray bottle; silicone mat; white plate; red placemat; chef apron; glasses; watch Visible actions: gesturing with hand; holding air fryer basket; pointing at air fryer basket; placing hand on counter Visible states: man smiling; air fryer basket being held; ingredients arranged on counter | N54: 12 | O54: 1 | R54: The visual shows the man interacting with the air fryer basket but does not show how food is loaded into it; no loading action is visible or described. | S54: VLM | T54: low | U54: No evidence of food being loaded into the basket is present in the frozen evidence. | V54: R1 | W54: 1 | Z54: no | AA54: ASR说明将饼干放入炸篮的方向，但画面未完整展示放入动作。 | AC54: completed | AD54: 2026-07-27T22:20:03+08:00 | AE54: =IF(AC54<>"completed","",IF(W54=O54,"no","yes")) | AF54: =IF(AC54<>"completed","",IF(AND(X54=P54,Y54=Q54),"no","yes")) | AG54: =IF(AC54<>"completed","待复核",IF(OR(W54="",Z54="",AA54="",AD54=""),"缺少必填项",IF(AND(OR(AE54="yes",AF54="yes"),AB54=""),"修正原因缺失",IF(OR(W54=0,W54=1),IF(AND(X54="",Y54=""),"通过","0/1级时间应留空"),IF(AND(OR(W54=2,W54=3),X54<>"",Y54<>"",X54>=I54,Y54<=J54,Y54>X54),"通过","2/3级时间无效")))))
A55: VQ-002 | B55: How should food be loaded into an air-fryer basket? | C55: en | D55: Air Fryer | E55: operation | F55: development | G55: airfryer-017-scene-0015 | H55: airfryer-017 | I55: 125.025 | J55: 133.433 | K55: items/airfryer-017-scene-0015/clip.mp4 | L55: items/airfryer-017-scene-0015/thumbnail.jpg | M55: ASR: but this time it should be easier because I've already done it once and I know how to do it. I left some of the screws out last time when I was reassembling it. So it's less to take apart. OCR: out of order Asain -Anryed Dad CLASSILA Nia TAINED VLM: Visual summary: A man is seated at a table, pointing at a stainless steel air fryer with a handwritten note on it. The note reads 'Out of Order Again! - Annoyed Dad'. 视觉摘要: 一名男子坐在桌前，指着一台贴有便条的不锈钢空气炸锅。便条上写着‘又坏了！- 生气的老爸’。 Visible product: Air Fryer Visible components: stainless steel air fryer; handwritten note; wooden table; window with blinds; wall-mounted display cases; man's t-shirt with Nintendo controller graphic Visible actions: man pointing at the air fryer; man speaking Visible states: air fryer is stationary; note is attached to the air fryer | N55: 13 | O55: 0 | R55: The scene shows a man pointing at an air fryer with a note saying 'Out of Order Again!', and the ASR mentions reassembling screws, indicating the air fryer is broken and being discussed in context of repair, not food loading. | S55: VLM|ASR|OCR | T55: low | U55: No evidence of food being loaded into the basket or any step related to loading food. | V55: R1 | W55: 0 | Z55: no | AA55: A man sits at a table next to a stainless steel air fryer with a handwritten note reading 'Out of Order Again!' taped to it; ASR discusses reassembling screws after prior repair. The appliance is broken and the topic is repair, not food loading. | AC55: completed | AD55: 2026-07-28T01:18:39+08:00 | AE55: =IF(AC55<>"completed","",IF(W55=O55,"no","yes")) | AF55: =IF(AC55<>"completed","",IF(AND(X55=P55,Y55=Q55),"no","yes")) | AG55: =IF(AC55<>"completed","待复核",IF(OR(W55="",Z55="",AA55="",AD55=""),"缺少必填项",IF(AND(OR(AE55="yes",AF55="yes"),AB55=""),"修正原因缺失",IF(OR(W55=0,W55=1),IF(AND(X55="",Y55=""),"通过","0/1级时间应留空"),IF(AND(OR(W55=2,W55=3),X55<>"",Y55<>"",X55>=I55,Y55<=J55,Y55>X55),"通过","2/3级时间无效")))))
A56: VQ-002 | B56: How should food be loaded into an air-fryer basket? | C56: en | D56: Air Fryer | E56: operation | F56: development | G56: pressure-006-scene-0010 | H56: pressure-006 | I56: 29.458 | J56: 34.083 | K56: items/pressure-006-scene-0010/clip.mp4 | L56: items/pressure-006-scene-0010/thumbnail.jpg | M56: ASR: • 360-degree hot air baking, wrapping heating, original flavor, 1500W high power, rapid heating OCR: 1500 W high-power rapid heating VLM: Visual summary: Food items are cooking inside an air fryer, with text overlays indicating '360 air cooking' and '1500 W high-power rapid heating'. 视觉摘要: 食物在空气炸锅内烹饪，画面中有文字叠加显示“360空气烹饪”和“1500W高功率快速加热”。 Visible product: Air Fryer Visible components: food items; air fryer basket; text overlay Visible states: food is cooking; air fryer is operating Visual uncertainty: The specific model or brand of the air fryer is not visible. The exact type of food is not clearly identifiable. | N56: 14 | O56: 0 | R56: The scene shows food cooking inside an air fryer but provides no visual, spoken, or OCR evidence of how food is loaded into the basket. | S56: VLM|ASR|OCR | T56: low | U56: No evidence of loading action or instruction is present in the frozen evidence. | V56: R1 | W56: 0 | Z56: no | AA56: 画面为食物烹饪中，未展示放入炸篮的动作。 | AC56: completed | AD56: 2026-07-27T22:17:08+08:00 | AE56: =IF(AC56<>"completed","",IF(W56=O56,"no","yes")) | AF56: =IF(AC56<>"completed","",IF(AND(X56=P56,Y56=Q56),"no","yes")) | AG56: =IF(AC56<>"completed","待复核",IF(OR(W56="",Z56="",AA56="",AD56=""),"缺少必填项",IF(AND(OR(AE56="yes",AF56="yes"),AB56=""),"修正原因缺失",IF(OR(W56=0,W56=1),IF(AND(X56="",Y56=""),"通过","0/1级时间应留空"),IF(AND(OR(W56=2,W56=3),X56<>"",Y56<>"",X56>=I56,Y56<=J56,Y56>X56),"通过","2/3级时间无效")))))
A57: VQ-002 | B57: How should food be loaded into an air-fryer basket? | C57: en | D57: Air Fryer | E57: operation | F57: development | G57: airfryer-017-scene-0026 | H57: airfryer-017 | I57: 230.697 | J57: 236.403 | K57: items/airfryer-017-scene-0026/clip.mp4 | L57: items/airfryer-017-scene-0026/thumbnail.jpg | M57: ASR: things grouped. I will turn the unit upside down so that I can work on the bottom. First I'm going VLM: Visual summary: A person is handling a small, black and silver air fryer on a wooden table, with a dollhouse visible in the background. 视觉摘要: 一个人在木桌上操作一个黑色和银色的小型空气炸锅，背景中有一个玩偶屋。 Visible product: Air Fryer Visible components: air fryer; wooden table; dollhouse Visible actions: person opening air fryer door; person lifting air fryer Visible states: air fryer door open; air fryer being lifted | N57: 15 | O57: 1 | R57: The ASR mentions turning the unit upside down to work on the bottom, which implies a step related to loading, but no actual loading action or instruction is shown or described. The VLM shows the air fryer being lifted and door opened, which is preparatory but not loading. | S57: VLM|ASR | T57: low | U57: No evidence of food being loaded into the basket. | V57: R1 | W57: 1 | Z57: no | AA57: A person opens the door of a small black/silver air fryer toaster oven and reaches inside (t=231.8s–t=233.0s), then begins tilting the unit upside down (t=234.1s–t=236.4s); ASR states 'turn the unit upside down so that I can work on the bottom.' The product is correct and door interaction is shown, but the context is repair/disassembly, not food loading. | AC57: completed | AD57: 2026-07-28T01:18:39+08:00 | AE57: =IF(AC57<>"completed","",IF(W57=O57,"no","yes")) | AF57: =IF(AC57<>"completed","",IF(AND(X57=P57,Y57=Q57),"no","yes")) | AG57: =IF(AC57<>"completed","待复核",IF(OR(W57="",Z57="",AA57="",AD57=""),"缺少必填项",IF(AND(OR(AE57="yes",AF57="yes"),AB57=""),"修正原因缺失",IF(OR(W57=0,W57=1),IF(AND(X57="",Y57=""),"通过","0/1级时间应留空"),IF(AND(OR(W57=2,W57=3),X57<>"",Y57<>"",X57>=I57,Y57<=J57,Y57>X57),"通过","2/3级时间无效")))))
A58: VQ-002 | B58: How should food be loaded into an air-fryer basket? | C58: en | D58: Air Fryer | E58: operation | F58: development | G58: airfryer-005-scene-0031 | H58: airfryer-005 | I58: 280.4 | J58: 283.653 | K58: items/airfryer-005-scene-0031/clip.mp4 | L58: items/airfryer-005-scene-0031/thumbnail.jpg | M58: ASR: I normally just grab it and put it on my plate like that. VLM: Visual summary: A person is placing food items onto a white plate next to an open air fryer basket. 视觉摘要: 一个人正在将食物放在一个白色盘子上，旁边是一个打开的空气炸锅篮子。 Visible product: Air Fryer Visible components: air fryer basket; white plate; bread with egg and ham; person's hand; person's teal sleeve Visible actions: placing food on a plate Visible states: air fryer basket is open; food is on the plate | N58: 16 | O58: 0 | R58: The visual and audio evidence shows food being placed on a plate, not into the air-fryer basket, and does not demonstrate how food should be loaded into the basket. | S58: VLM|ASR | T58: low | U58: No evidence of food being loaded into the air-fryer basket is present. | V58: R1 | W58: 1 | Z58: no | AA58: At t=280.4s, the video shows a hand placing food onto a white plate next to an open air fryer basket, not into the basket. | AB58: Scene clearly shows the air fryer product and basket, so it is same-product rather than unrelated. | AC58: completed | AD58: 2026-07-28T01:18:39+08:00 | AE58: =IF(AC58<>"completed","",IF(W58=O58,"no","yes")) | AF58: =IF(AC58<>"completed","",IF(AND(X58=P58,Y58=Q58),"no","yes")) | AG58: =IF(AC58<>"completed","待复核",IF(OR(W58="",Z58="",AA58="",AD58=""),"缺少必填项",IF(AND(OR(AE58="yes",AF58="yes"),AB58=""),"修正原因缺失",IF(OR(W58=0,W58=1),IF(AND(X58="",Y58=""),"通过","0/1级时间应留空"),IF(AND(OR(W58=2,W58=3),X58<>"",Y58<>"",X58>=I58,Y58<=J58,Y58>X58),"通过","2/3级时间无效")))))
A59: VQ-002 | B59: How should food be loaded into an air-fryer basket? | C59: en | D59: Air Fryer | E59: operation | F59: development | G59: airfryer-002-scene-0009 | H59: airfryer-002 | I59: 241.808 | J59: 257.424 | K59: items/airfryer-002-scene-0009/clip.mp4 | L59: items/airfryer-002-scene-0009/thumbnail.jpg | M59: ASR: spray we're now going to place our cookies in the basket seam side down we're going to cook OCR: •ner Library Kitchen Chef itchen Puff Pastry SHEETS OREO VLM: Visual summary: A person wearing a blue apron holds an air fryer basket containing several round, pale yellow food items, with a yellow spray can on a silicone mat nearby. 视觉摘要: 一个人穿着蓝色围裙，手持一个装有数个圆形淡黄色食物的空气炸锅篮子，旁边硅胶垫上放着一个黄色喷雾罐。 Visible product: Air Fryer Visible components: air fryer basket; silicone mat; yellow spray can; blue apron with text; watch Visible actions: holding the air fryer basket; placing food items into the basket Visible states: food items inside the basket; basket being held open | N59: 17 | O59: 2 | P59: 241.808 | Q59: 257.424 | R59: The ASR mentions placing cookies in the basket seam side down, and the VLM shows food items being placed into the basket, indicating a loading action, though no explicit instruction on orientation or basket filling method is fully visible. | S59: VLM|ASR | T59: medium | U59: The ASR only mentions 'seam side down' for cookies, which may not apply to all foods, and the VLM does not show the full loading process or specify how food should be arranged in the basket. | V59: R1 | W59: 3 | X59: 244.9 | Y59: 257.424 | Z59: no | AA59: 第2-6帧（t=244.9s-257.5s）清晰显示人手从纸盒取出圆形饼放入空气炸篮，且ASR明确说明'place our cookies in the basket seam side down'，直接给出装入方法。 | AB59: AI=2→R1=3：ASR明确告知'接缝面朝下'的装载方式且画面持续演示装入动作，已能完整回答'如何装入空气炸篮'。 | AC59: completed | AD59: 2026-07-28T01:18:39+08:00 | AE59: =IF(AC59<>"completed","",IF(W59=O59,"no","yes")) | AF59: =IF(AC59<>"completed","",IF(AND(X59=P59,Y59=Q59),"no","yes")) | AG59: =IF(AC59<>"completed","待复核",IF(OR(W59="",Z59="",AA59="",AD59=""),"缺少必填项",IF(AND(OR(AE59="yes",AF59="yes"),AB59=""),"修正原因缺失",IF(OR(W59=0,W59=1),IF(AND(X59="",Y59=""),"通过","0/1级时间应留空"),IF(AND(OR(W59=2,W59=3),X59<>"",Y59<>"",X59>=I59,Y59<=J59,Y59>X59),"通过","2/3级时间无效")))))
A60: VQ-002 | B60: How should food be loaded into an air-fryer basket? | C60: en | D60: Air Fryer | E60: operation | F60: development | G60: airfryer-005-scene-0010 | H60: airfryer-005 | I60: 108.674 | J60: 119.766 | K60: items/airfryer-005-scene-0010/clip.mp4 | L60: items/airfryer-005-scene-0010/thumbnail.jpg | M60: ASR: And what I'll do is I'm going to take my slices of bread and just put them right in there. There's no need to spray the air fryer or anything like that. that, put those right in there and then we will take our nice OCR: COPEAPPRAC CAACABOBR BOGRAAARED GORGGAPAPC BRCERARPPO VLM: Visual summary: A person places slices of bread into the basket of an open air fryer, with bacon, an egg, and a cracked egg on a cutting board nearby. 视觉摘要: 一个人将面包片放入打开的空气炸锅篮中，旁边切菜板上放着培根、一个鸡蛋和一个已敲开的鸡蛋。 Visible product: Air Fryer Visible components: air fryer basket; air fryer lid; bread; bacon; egg; cracked egg; cutting board Visible actions: placing bread into air fryer basket Visible states: air fryer lid open; egg cracked in bowl | N60: 18 | O60: 2 | P60: 108.674 | Q60: 119.766 | R60: The person places bread slices directly into the air fryer basket, indicating a method of loading food, though no explicit instruction on spacing or arrangement is shown. | S60: VLM|ASR | T60: low | U60: No explicit mention of spacing, layering, or avoiding overcrowding, which are common considerations in air fryer loading. | V60: R1 | W60: 3 | X60: 108.7 | Y60: 119.766 | Z60: no | AA60: From t=108.7s to t=119.8s, the person places slices of bread directly into the air fryer basket while saying 'put them right in there'. | AB60: Visual and speech directly demonstrate loading bread into the basket, so grade 3 is more accurate than grade 2. | AC60: completed | AD60: 2026-07-28T01:18:39+08:00 | AE60: =IF(AC60<>"completed","",IF(W60=O60,"no","yes")) | AF60: =IF(AC60<>"completed","",IF(AND(X60=P60,Y60=Q60),"no","yes")) | AG60: =IF(AC60<>"completed","待复核",IF(OR(W60="",Z60="",AA60="",AD60=""),"缺少必填项",IF(AND(OR(AE60="yes",AF60="yes"),AB60=""),"修正原因缺失",IF(OR(W60=0,W60=1),IF(AND(X60="",Y60=""),"通过","0/1级时间应留空"),IF(AND(OR(W60=2,W60=3),X60<>"",Y60<>"",X60>=I60,Y60<=J60,Y60>X60),"通过","2/3级时间无效")))))
A61: VQ-002 | B61: How should food be loaded into an air-fryer basket? | C61: en | D61: Air Fryer | E61: operation | F61: development | G61: airfryer-024-scene-0005 | H61: airfryer-024 | I61: 16.149 | J61: 19.953 | K61: items/airfryer-024-scene-0005/clip.mp4 | L61: items/airfryer-024-scene-0005/thumbnail.jpg | M61: ASR: Introducing the revolutionary New Wave Brio Digital Air Fryer. Now make crispy air fried French fries in just 8 minutes, VLM: Visual summary: A black NuWave Brio digital air fryer is shown stationary on a wooden surface against a white background. 视觉摘要: 一台黑色的NuWave Brio数字空气炸锅静止放置在木质表面上，背景为白色。 Visible product: NuWave Brio Visible components: control panel; digital display; buttons; brand logo; product name text; wooden surface; white background | N61: 19 | O61: 0 | R61: The scene shows the air fryer product but does not depict or describe how food is loaded into the basket. | S61: VLM|ASR | T61: low | U61: No visual or spoken evidence of loading food into the basket is present. | V61: R1 | W61: 1 | Z61: no | AA61: At t=16.1s, only the closed exterior of a NuWave Brio air fryer is shown, with no basket loading demonstration. | AB61: The scene is a product showcase of the same air fryer, not unrelated content. | AC61: completed | AD61: 2026-07-28T01:18:39+08:00 | AE61: =IF(AC61<>"completed","",IF(W61=O61,"no","yes")) | AF61: =IF(AC61<>"completed","",IF(AND(X61=P61,Y61=Q61),"no","yes")) | AG61: =IF(AC61<>"completed","待复核",IF(OR(W61="",Z61="",AA61="",AD61=""),"缺少必填项",IF(AND(OR(AE61="yes",AF61="yes"),AB61=""),"修正原因缺失",IF(OR(W61=0,W61=1),IF(AND(X61="",Y61=""),"通过","0/1级时间应留空"),IF(AND(OR(W61=2,W61=3),X61<>"",Y61<>"",X61>=I61,Y61<=J61,Y61>X61),"通过","2/3级时间无效")))))
A62: VQ-002 | B62: How should food be loaded into an air-fryer basket? | C62: en | D62: Air Fryer | E62: operation | F62: development | G62: airfryer-024-scene-0024 | H62: airfryer-024 | I62: 106.773 | J62: 109.109 | K62: items/airfryer-024-scene-0024/clip.mp4 | L62: items/airfryer-024-scene-0024/thumbnail.jpg | M62: ASR: Don't be fooled by imitators. the New Wave Brio Digital Air Fryer is the undisputed leader. VLM: Visual summary: A hand is holding the handle of an open air fryer containing cooked golden-brown food items. 视觉摘要: 一只手正拿着打开的空气炸锅的把手，锅内装有金黄色的熟食。 Visible product: Air Fryer Visible components: air fryer; handle; food items; digital display; control buttons Visible actions: holding the handle Visible states: air fryer open; food cooked | N62: 20 | O62: 1 | R62: The scene shows an air fryer with cooked food, but no action of loading food is depicted; the hand is holding the handle, not placing food into the basket. | S62: VLM | T62: low | U62: No evidence of food being loaded into the basket is present. | V62: R1 | W62: 1 | Z62: no | AA62: At t=108.2s, the basket already contains cooked golden-brown food and a hand is pulling the handle, not loading food. | AC62: completed | AD62: 2026-07-28T01:18:39+08:00 | AE62: =IF(AC62<>"completed","",IF(W62=O62,"no","yes")) | AF62: =IF(AC62<>"completed","",IF(AND(X62=P62,Y62=Q62),"no","yes")) | AG62: =IF(AC62<>"completed","待复核",IF(OR(W62="",Z62="",AA62="",AD62=""),"缺少必填项",IF(AND(OR(AE62="yes",AF62="yes"),AB62=""),"修正原因缺失",IF(OR(W62=0,W62=1),IF(AND(X62="",Y62=""),"通过","0/1级时间应留空"),IF(AND(OR(W62=2,W62=3),X62<>"",Y62<>"",X62>=I62,Y62<=J62,Y62>X62),"通过","2/3级时间无效")))))
A63: VQ-002 | B63: How should food be loaded into an air-fryer basket? | C63: en | D63: Air Fryer | E63: operation | F63: development | G63: airfryer-032-scene-0077 | H63: airfryer-032 | I63: 364.033 | J63: 376.0 | K63: items/airfryer-032-scene-0077/clip.mp4 | L63: items/airfryer-032-scene-0077/thumbnail.jpg | M63: ASR: use some little cotton swabs to clean in between every little grate in the basket. Of course, your air fryer basket will look a little bit different than mine, so just use anything that will help you get in any little crevices you'll be surprised at how much food and gunk you find there i mean honestly look at all the cotton swabs i used oh it's so gross then i grabbed my VLM: Visual summary: A hand uses a cotton swab to clean the inside of a black air fryer basket. 视觉摘要: 一只手用棉签清洁黑色空气炸锅篮子的内部。 Visible product: Air Fryer Visible components: black air fryer basket; cotton swab; hand Visible actions: cleaning with a cotton swab; holding the basket Visible states: cotton swab with residue; dirty basket | N63: 21 | O63: 0 | R63: The evidence shows cleaning the air fryer basket with a cotton swab, not loading food. | S63: VLM|ASR | T63: low | U63: No evidence of food loading or related actions. | V63: R1 | W63: 1 | Z63: no | AA63: At t=364.0s, a hand is cleaning the basket grates with a cotton swab, not placing food inside. | AB63: Same air fryer basket is shown, but the action is cleaning rather than loading food. | AC63: completed | AD63: 2026-07-28T01:18:39+08:00 | AE63: =IF(AC63<>"completed","",IF(W63=O63,"no","yes")) | AF63: =IF(AC63<>"completed","",IF(AND(X63=P63,Y63=Q63),"no","yes")) | AG63: =IF(AC63<>"completed","待复核",IF(OR(W63="",Z63="",AA63="",AD63=""),"缺少必填项",IF(AND(OR(AE63="yes",AF63="yes"),AB63=""),"修正原因缺失",IF(OR(W63=0,W63=1),IF(AND(X63="",Y63=""),"通过","0/1级时间应留空"),IF(AND(OR(W63=2,W63=3),X63<>"",Y63<>"",X63>=I63,Y63<=J63,Y63>X63),"通过","2/3级时间无效")))))
A64: VQ-002 | B64: How should food be loaded into an air-fryer basket? | C64: en | D64: Air Fryer | E64: operation | F64: development | G64: airfryer-029-scene-0052 | H64: airfryer-029 | I64: 313.96 | J64: 317.76 | K64: items/airfryer-029-scene-0052/clip.mp4 | L64: items/airfryer-029-scene-0052/thumbnail.jpg | M64: ASR: like this there like this so they can get even heat all the pieces look at OCR: PHILIPS SUPER CHEF VLM: Visual summary: A chef in a red uniform is placing food into a black air fryer on a kitchen counter. 视觉摘要: 一位穿着红色制服的厨师正在将食物放入厨房台面上的黑色空气炸锅中。 Visible product: Air Fryer Visible components: black air fryer; chef's uniform; green plate; yellow wall; Philips SUPER CHEF logo; refrigerator; blender; rice cooker; cabinet Visible actions: placing food into the air fryer; using a utensil to handle food Visible states: food being placed into the air fryer basket | N64: 22 | O64: 2 | P64: 313.96 | Q64: 317.76 | R64: The visual shows food being placed into the air fryer basket, and the ASR mentions arranging food for even heat, indicating a relevant adjacent step to loading. | S64: VLM|ASR | T64: low | U64: No explicit instruction on loading method (e.g., single layer, spacing) is visible or audible. | V64: R1 | W64: 3 | X64: 314.0 | Y64: 317.6 | Z64: no | AA64: From t=314.0s to t=317.6s, the chef places food pieces into the black air fryer basket while saying 'like this so they can get even heat'. | AB64: Visual and speech directly show loading food into the basket and arranging for even heat, warranting grade 3. | AC64: completed | AD64: 2026-07-28T01:18:39+08:00 | AE64: =IF(AC64<>"completed","",IF(W64=O64,"no","yes")) | AF64: =IF(AC64<>"completed","",IF(AND(X64=P64,Y64=Q64),"no","yes")) | AG64: =IF(AC64<>"completed","待复核",IF(OR(W64="",Z64="",AA64="",AD64=""),"缺少必填项",IF(AND(OR(AE64="yes",AF64="yes"),AB64=""),"修正原因缺失",IF(OR(W64=0,W64=1),IF(AND(X64="",Y64=""),"通过","0/1级时间应留空"),IF(AND(OR(W64=2,W64=3),X64<>"",Y64<>"",X64>=I64,Y64<=J64,Y64>X64),"通过","2/3级时间无效")))))
A65: VQ-002 | B65: How should food be loaded into an air-fryer basket? | C65: en | D65: Air Fryer | E65: operation | F65: development | G65: pressure-006-scene-0003 | H65: pressure-006 | I65: 4.833 | J65: 7.5 | K65: items/pressure-006-scene-0003/clip.mp4 | L65: items/pressure-006-scene-0003/thumbnail.jpg | M65: ASR: Hefung Multifunctional Air Fryer, One-Click Cover Opening, Automatic Lifting, Easy to Use, 6L Super Large Capacity, Can Accommodate the Whole Chicken, Intelligent Buttons on the Top, OCR: 6 L ultra-large capacity VLM: Visual summary: A person is preparing food, handling a raw chicken in a bowl next to a yellow air fryer with its basket visible and a plate of sliced fruit nearby. 视觉摘要: 一个人正在准备食物，手处理着碗里的生鸡，旁边是一个黄色的空气炸锅，其篮子可见，还有一盘切好的水果。 Visible product: Air Fryer Visible components: yellow air fryer; air fryer basket; glass bowl; plate; raw chicken; sliced fruit Visible actions: person handling raw chicken; person holding chicken in bowl Visible states: air fryer lid open; air fryer basket empty | N65: 23 | O65: 1 | R65: The scene shows a person handling raw chicken next to an air fryer with its basket visible and empty, but no action of loading food into the basket is shown. | S65: VLM | T65: low | U65: No evidence of food being loaded into the basket is present. | V65: R1 | W65: 3 | X65: 6.5 | Y65: 7.5 | Z65: no | AA65: Frame at t=7.0s shows a hand placing raw chicken into the air-fryer basket, directly demonstrating food loading. | AB65: AI graded 1, but the scene visually demonstrates loading raw chicken into the basket at t=6.5s-7.5s. | AC65: completed | AD65: 2026-07-28T01:18:39+08:00 | AE65: =IF(AC65<>"completed","",IF(W65=O65,"no","yes")) | AF65: =IF(AC65<>"completed","",IF(AND(X65=P65,Y65=Q65),"no","yes")) | AG65: =IF(AC65<>"completed","待复核",IF(OR(W65="",Z65="",AA65="",AD65=""),"缺少必填项",IF(AND(OR(AE65="yes",AF65="yes"),AB65=""),"修正原因缺失",IF(OR(W65=0,W65=1),IF(AND(X65="",Y65=""),"通过","0/1级时间应留空"),IF(AND(OR(W65=2,W65=3),X65<>"",Y65<>"",X65>=I65,Y65<=J65,Y65>X65),"通过","2/3级时间无效")))))
A66: VQ-002 | B66: How should food be loaded into an air-fryer basket? | C66: en | D66: Air Fryer | E66: operation | F66: development | G66: airfryer-032-scene-0113 | H66: airfryer-032 | I66: 522.967 | J66: 525.6 | K66: items/airfryer-032-scene-0113/clip.mp4 | L66: items/airfryer-032-scene-0113/thumbnail.jpg | M66: ASR: airflow of the vents then I let it sit overnight to dry before we used it again if you like these VLM: Visual summary: A person is holding a black air fryer basket while standing next to a black air fryer on a kitchen countertop. 视觉摘要: 一个人正拿着一个黑色空气炸锅篮子，站在厨房台面上的黑色空气炸锅旁边。 Visible product: Air Fryer Visible components: black air fryer basket; black air fryer; kitchen countertop; person's hand; person's arm; red sleeve Visible actions: person holding air fryer basket | N66: 24 | O66: 1 | R66: The scene shows a person holding an air fryer basket, which is relevant to the product class, but no action of loading food into the basket is visible or described. | S66: VLM | T66: low | U66: No evidence of food being loaded into the basket or any instruction related to loading food. | V66: R1 | W66: 1 | Z66: no | AA66: 画面仅显示持有空炸篮，未展示任何向篮中装入食物的动作，ASR未提及装篮方法。 | AC66: completed | AD66: 2026-07-28T01:18:39+08:00 | AE66: =IF(AC66<>"completed","",IF(W66=O66,"no","yes")) | AF66: =IF(AC66<>"completed","",IF(AND(X66=P66,Y66=Q66),"no","yes")) | AG66: =IF(AC66<>"completed","待复核",IF(OR(W66="",Z66="",AA66="",AD66=""),"缺少必填项",IF(AND(OR(AE66="yes",AF66="yes"),AB66=""),"修正原因缺失",IF(OR(W66=0,W66=1),IF(AND(X66="",Y66=""),"通过","0/1级时间应留空"),IF(AND(OR(W66=2,W66=3),X66<>"",Y66<>"",X66>=I66,Y66<=J66,Y66>X66),"通过","2/3级时间无效")))))
A67: VQ-002 | B67: How should food be loaded into an air-fryer basket? | C67: en | D67: Air Fryer | E67: operation | F67: development | G67: pressure-006-scene-0001 | H67: pressure-006 | I67: 0.0 | J67: 2.208 | K67: items/pressure-006-scene-0001/clip.mp4 | L67: items/pressure-006-scene-0001/thumbnail.jpg | M67: ASR: Hefung Multifunctional Air Fryer, One-Click Cover Opening, Automatic Lifting, Easy to Use, 6L Super Large Capacity, Can Accommodate the Whole Chicken, Intelligent Buttons on the Top, OCR: One click cover opening VLM: Visual summary: A person is holding a yellow and black air fryer on a kitchen counter surrounded by various food items. 视觉摘要: 一个人拿着一个黄黑相间的空气炸锅，站在摆满各种食物的厨房台面上。 Visible product: Air Fryer Visible components: yellow and black appliance; basket with baguettes; bell peppers; tomatoes; mushrooms; chicken pieces; sliced meat; rosemary; pepper grinder; plate with food Visible actions: person holding the air fryer | N67: 25 | O67: 1 | R67: The scene shows an air fryer and food items around it, but no action of loading food into the basket is visible or described. | S67: VLM|ASR | T67: low | U67: No evidence of food being loaded into the basket is present. | V67: R1 | W67: 1 | Z67: no | AA67: Frames t=0.0s-2.2s only show a person holding and displaying the air fryer, with no food-loading action. | AC67: completed | AD67: 2026-07-28T01:18:39+08:00 | AE67: =IF(AC67<>"completed","",IF(W67=O67,"no","yes")) | AF67: =IF(AC67<>"completed","",IF(AND(X67=P67,Y67=Q67),"no","yes")) | AG67: =IF(AC67<>"completed","待复核",IF(OR(W67="",Z67="",AA67="",AD67=""),"缺少必填项",IF(AND(OR(AE67="yes",AF67="yes"),AB67=""),"修正原因缺失",IF(OR(W67=0,W67=1),IF(AND(X67="",Y67=""),"通过","0/1级时间应留空"),IF(AND(OR(W67=2,W67=3),X67<>"",Y67<>"",X67>=I67,Y67<=J67,Y67>X67),"通过","2/3级时间无效")))))
A68: VQ-002 | B68: How should food be loaded into an air-fryer basket? | C68: en | D68: Air Fryer | E68: operation | F68: development | G68: airfryer-024-scene-0006 | H68: airfryer-024 | I68: 19.953 | J68: 22.689 | K68: items/airfryer-024-scene-0006/clip.mp4 | L68: items/airfryer-024-scene-0006/thumbnail.jpg | M68: ASR: Now make crispy air fried French fries in just 8 minutes, crunchy onion rings in 10 minutes, OCR: AIR-FRIED French Fries only 8 Minutes VLM: Visual summary: A person is pouring cooked French fries from an air fryer basket into a red and white checkered paper-lined basket. 视觉摘要: 一个人正将从空气炸锅篮子里倒出的炸薯条倒入一个红白格子纸衬的篮子中。 Visible product: Air Fryer Visible components: air fryer basket; red and white checkered paper liner; paper bag; white cup; text overlay: AIR-FRIED French Fries Visible actions: pouring French fries; holding air fryer basket Visible states: French fries being transferred; fries in basket; fries in air fryer basket | N68: 26 | O68: 1 | R68: The scene shows French fries being poured out of the air fryer basket, indicating the basket was used to hold food, but does not show how food is loaded into it. | S68: VLM|ASR|OCR | T68: low | U68: The action shown is unloading, not loading; no evidence of loading procedure is visible or described. | V68: R1 | W68: 1 | Z68: no | AA68: Frames t=20.0s-22.7s show cooked fries being poured out of the basket, not loaded into it. | AC68: completed | AD68: 2026-07-28T01:18:39+08:00 | AE68: =IF(AC68<>"completed","",IF(W68=O68,"no","yes")) | AF68: =IF(AC68<>"completed","",IF(AND(X68=P68,Y68=Q68),"no","yes")) | AG68: =IF(AC68<>"completed","待复核",IF(OR(W68="",Z68="",AA68="",AD68=""),"缺少必填项",IF(AND(OR(AE68="yes",AF68="yes"),AB68=""),"修正原因缺失",IF(OR(W68=0,W68=1),IF(AND(X68="",Y68=""),"通过","0/1级时间应留空"),IF(AND(OR(W68=2,W68=3),X68<>"",Y68<>"",X68>=I68,Y68<=J68,Y68>X68),"通过","2/3级时间无效")))))
A69: VQ-002 | B69: How should food be loaded into an air-fryer basket? | C69: en | D69: Air Fryer | E69: operation | F69: development | G69: airfryer-024-scene-0015 | H69: airfryer-024 | I69: 70.137 | J69: 73.974 | K69: items/airfryer-024-scene-0015/clip.mp4 | L69: items/airfryer-024-scene-0015/thumbnail.jpg | M69: ASR: And when the Brio is done cooking, it shuts off automatically so your food doesn't burn. Breakfast, lunch, after-school snacks, family dinner, even a poolside party are all part of why the New Wave Brio will quickly become your favorite cooking appliance. VLM: Visual summary: A cooked, golden-brown food item is shown being removed from an air fryer basket and then placed onto a plate with green beans. 视觉摘要: 一个金黄色的熟食从空气炸锅篮中取出，然后放在装有青豆的盘子上。 Visible product: Air Fryer Visible components: air fryer basket; air fryer; plate; green beans; text overlay: Auto Shut-Off Visible actions: removing food from air fryer; placing food on plate Visible states: food cooked and golden-brown; air fryer basket being lifted Visible warnings: Auto Shut-Off | N69: 27 | O69: 1 | R69: The scene shows food being removed from the air fryer basket after cooking, not how food is loaded into it. | S69: VLM | T69: low | U69: No evidence of loading food into the basket is present. | V69: R1 | W69: 1 | Z69: no | AA69: Frames t=70.1s-74.0s show cooked food being removed from the basket, not loaded into it. | AC69: completed | AD69: 2026-07-28T01:18:39+08:00 | AE69: =IF(AC69<>"completed","",IF(W69=O69,"no","yes")) | AF69: =IF(AC69<>"completed","",IF(AND(X69=P69,Y69=Q69),"no","yes")) | AG69: =IF(AC69<>"completed","待复核",IF(OR(W69="",Z69="",AA69="",AD69=""),"缺少必填项",IF(AND(OR(AE69="yes",AF69="yes"),AB69=""),"修正原因缺失",IF(OR(W69=0,W69=1),IF(AND(X69="",Y69=""),"通过","0/1级时间应留空"),IF(AND(OR(W69=2,W69=3),X69<>"",Y69<>"",X69>=I69,Y69<=J69,Y69>X69),"通过","2/3级时间无效")))))
A70: VQ-002 | B70: How should food be loaded into an air-fryer basket? | C70: en | D70: Air Fryer | E70: operation | F70: development | G70: airfryer-029-scene-0051 | H70: airfryer-029 | I70: 311.96 | J70: 313.96 | K70: items/airfryer-029-scene-0051/clip.mp4 | L70: items/airfryer-029-scene-0051/thumbnail.jpg | M70: ASR: a way they kind of in a standing position kind of thing and if something like this there like this so they can get even heat all the pieces look at VLM: Visual summary: A hand places seasoned chicken pieces into the basket of a black air fryer. 视觉摘要: 一只手将调味鸡块放入黑色空气炸锅的篮子中。 Visible product: Air Fryer Visible components: black air fryer; air fryer basket; air fryer control knob; green plate; seasoned chicken pieces; hand Visible actions: placing chicken into air fryer basket Visible states: chicken pieces coated in seasoning; air fryer basket partially filled | N70: 28 | O70: 3 | P70: 311.96 | Q70: 313.96 | R70: A hand places seasoned chicken pieces into the air fryer basket, visually demonstrating how food should be loaded, with ASR mentioning arranging for even heat distribution. | S70: VLM|ASR | T70: low | U70: The visual and ASR evidence together clearly show the loading action and imply the intent to distribute food for even heating, directly answering the question. | V70: R1 | W70: 3 | X70: 312 | Y70: 313.96 | Z70: no | AA70: Frames t=312.0s-314.0s show a hand placing seasoned chicken pieces into the air-fryer basket. | AB70: 时间按实际证据片段重定位 | AC70: completed | AD70: 2026-07-28T01:18:39+08:00 | AE70: =IF(AC70<>"completed","",IF(W70=O70,"no","yes")) | AF70: =IF(AC70<>"completed","",IF(AND(X70=P70,Y70=Q70),"no","yes")) | AG70: =IF(AC70<>"completed","待复核",IF(OR(W70="",Z70="",AA70="",AD70=""),"缺少必填项",IF(AND(OR(AE70="yes",AF70="yes"),AB70=""),"修正原因缺失",IF(OR(W70=0,W70=1),IF(AND(X70="",Y70=""),"通过","0/1级时间应留空"),IF(AND(OR(W70=2,W70=3),X70<>"",Y70<>"",X70>=I70,Y70<=J70,Y70>X70),"通过","2/3级时间无效")))))
A71: VQ-002 | B71: How should food be loaded into an air-fryer basket? | C71: en | D71: Air Fryer | E71: operation | F71: development | G71: airfryer-027-scene-0001 | H71: airfryer-027 | I71: 0.0 | J71: 7.508 | K71: items/airfryer-027-scene-0001/clip.mp4 | L71: items/airfryer-027-scene-0001/thumbnail.jpg | M71: OCR: Air Fryer vs. Baked Buffalo Wings? First, oven cooked wings VLM: Visual summary: A video title card introduces a comparison between air fryer and baked buffalo wings, followed by a slide indicating the first method is oven cooking. 视觉摘要: 视频标题卡介绍了空气炸锅与烤制的布法罗鸡翅的对比，随后显示第一种方法是烤箱烹饪。 Visible product: Air Fryer | N71: 29 | O71: 0 | R71: The scene introduces a comparison between air fryer and oven cooking, with no visual or spoken instruction on how to load food into an air fryer basket. | S71: VLM|OCR | T71: low | U71: No evidence of food loading into an air fryer basket is present. | V71: R1 | W71: 0 | Z71: no | AA71: 画面仅是比较标题与烤鸡翅导引，无空气炸篮装载食物的操作内容。 | AC71: completed | AD71: 2026-07-28T01:18:39+08:00 | AE71: =IF(AC71<>"completed","",IF(W71=O71,"no","yes")) | AF71: =IF(AC71<>"completed","",IF(AND(X71=P71,Y71=Q71),"no","yes")) | AG71: =IF(AC71<>"completed","待复核",IF(OR(W71="",Z71="",AA71="",AD71=""),"缺少必填项",IF(AND(OR(AE71="yes",AF71="yes"),AB71=""),"修正原因缺失",IF(OR(W71=0,W71=1),IF(AND(X71="",Y71=""),"通过","0/1级时间应留空"),IF(AND(OR(W71=2,W71=3),X71<>"",Y71<>"",X71>=I71,Y71<=J71,Y71>X71),"通过","2/3级时间无效")))))
A72: VQ-002 | B72: How should food be loaded into an air-fryer basket? | C72: en | D72: Air Fryer | E72: operation | F72: development | G72: airfryer-011-scene-0001 | H72: airfryer-011 | I72: 0.0 | J72: 107.95 | K72: items/airfryer-011-scene-0001/clip.mp4 | L72: items/airfryer-011-scene-0001/thumbnail.jpg | M72: ASR: Hi, welcome back to Montana, and today we're going to be making another one of my favorite air fryer recipes, grilled cheese. The ingredients are white bread, salted butter, sharp cheddar cheese, and Italian blend cheese. Your first step is to add some of your cheddar into the middle of your bread, and then sprinkle some Italian blend on top. Then butter the exterior of your bread. Put your grilled cheese inside of your air fryer, and then cook for four minutes. Now flip it over and then cook for another three minutes. Now that the three minutes is up, take it out of the air fryer, cut it, and give it a try. OCR: That's Good! WITH MONTANA MONTEREY play! RECREATION NG 5<S HONTEREY BINGA ISUR VF 2000 CA QUAS IONTEREY DECREATION BINCNAE 1SUS VIV ). 2021 ONTREY DECRATION DA REC ONTEREY ECREATION /V 20MON REC MONNEY A RECR TION 202 252 MO DA RE 1S8V 2120 BREC 2n2 MON MONTREYY DA Air Fryer Grilled Cheese 2 slices white bread Sharp Cheddar & Italian Blend Cheeses Salted butter X #showushowyouplayMonterey VLM: Visual summary: A young man in a kitchen prepares to make a grilled cheese sandwich using an air fryer. 视觉摘要: 一名年轻男子在厨房里准备使用空气炸锅制作烤奶酪三明治。 Visible product: Air Fryer Visible components: air fryer; refrigerator; wooden cabinets; countertop; knife block; coffee maker; glass jars; mug; red cutting board; bread; apron Visible actions: man standing; man handling bread | N72: 30 | O72: 1 | R72: The ASR describes adding cheese to bread, buttering the exterior, and placing the sandwich in the air fryer, but does not specify how food is loaded into the basket (e.g., arrangement, layering, or basket orientation). The OCR and VLM confirm the product is an air fryer and show bread being handled, but no loading instruction is visible or explicitly stated. | S72: ASR|OCR|VLM | T72: low | U72: The ASR mentions placing the sandwich 'inside of your air fryer' but does not describe the loading process into the basket, which is the specific question. No visual or textual evidence shows how food is loaded into the basket. | V72: R1 | W72: 1 | Z72: no | AA72: 画面64.7s帧展示将三明治放入空气炸锅，但这是将食物放入机身而非演示如何装入炸篮内部（无分层、朝向说明），无法直接回答。 | AC72: completed | AD72: 2026-07-27T22:01:34+08:00 | AE72: =IF(AC72<>"completed","",IF(W72=O72,"no","yes")) | AF72: =IF(AC72<>"completed","",IF(AND(X72=P72,Y72=Q72),"no","yes")) | AG72: =IF(AC72<>"completed","待复核",IF(OR(W72="",Z72="",AA72="",AD72=""),"缺少必填项",IF(AND(OR(AE72="yes",AF72="yes"),AB72=""),"修正原因缺失",IF(OR(W72=0,W72=1),IF(AND(X72="",Y72=""),"通过","0/1级时间应留空"),IF(AND(OR(W72=2,W72=3),X72<>"",Y72<>"",X72>=I72,Y72<=J72,Y72>X72),"通过","2/3级时间无效")))))
A73: VQ-002 | B73: How should food be loaded into an air-fryer basket? | C73: en | D73: Air Fryer | E73: operation | F73: development | G73: airfryer-006-scene-0005 | H73: airfryer-006 | I73: 16.817 | J73: 19.92 | K73: items/airfryer-006-scene-0005/clip.mp4 | L73: items/airfryer-006-scene-0005/thumbnail.jpg | M73: ASR: Your air fryer, 350, four minutes for the first side. Here it goes. VLM: Visual summary: A woman in a pink shirt is standing in a kitchen next to a white air fryer, gesturing with her hand while speaking. 视觉摘要: 一位穿着粉色衬衫的女士站在厨房里，旁边是一台白色空气炸锅，她正用手势配合说话。 Visible product: Air Fryer Visible components: white air fryer; digital display; control buttons; brand name 'COSORI'; temperature setting '350°'; shelf with plates; plant Visible actions: woman gesturing with her right hand; woman speaking | N73: 31 | O73: 1 | R73: The ASR mentions 'Your air fryer, 350, four minutes for the first side' and the VLM shows a woman gesturing while speaking next to the air fryer, but neither describes how food should be loaded into the basket. | S73: VLM|ASR | T73: low | U73: No visual or spoken evidence shows the loading process into the basket. | V73: R1 | W73: 1 | Z73: no | AA73: 画面仅展示温度设置与文字说明，未展示放入食物动作。 | AC73: completed | AD73: 2026-07-27T22:20:03+08:00 | AE73: =IF(AC73<>"completed","",IF(W73=O73,"no","yes")) | AF73: =IF(AC73<>"completed","",IF(AND(X73=P73,Y73=Q73),"no","yes")) | AG73: =IF(AC73<>"completed","待复核",IF(OR(W73="",Z73="",AA73="",AD73=""),"缺少必填项",IF(AND(OR(AE73="yes",AF73="yes"),AB73=""),"修正原因缺失",IF(OR(W73=0,W73=1),IF(AND(X73="",Y73=""),"通过","0/1级时间应留空"),IF(AND(OR(W73=2,W73=3),X73<>"",Y73<>"",X73>=I73,Y73<=J73,Y73>X73),"通过","2/3级时间无效")))))
A74: VQ-002 | B74: How should food be loaded into an air-fryer basket? | C74: en | D74: Air Fryer | E74: operation | F74: development | G74: airfryer-032-scene-0013 | H74: airfryer-032 | I74: 47.6 | J74: 49.6 | K74: items/airfryer-032-scene-0013/clip.mp4 | L74: items/airfryer-032-scene-0013/thumbnail.jpg | M74: ASR: cooking is to clean it every time when you are done cooking with it once it's cooled simply wipe out any grease residue or leftover food with a paper towel and throw that away then you just VLM: Visual summary: A close-up view of a black air fryer basket with a perforated bottom, showing residue and grease stains, resting on a speckled countertop. 视觉摘要: 一个黑色空气炸锅篮子的特写，底部有穿孔，可见残留物和油渍，放在斑点台面上。 Visible product: Air Fryer Visible components: air fryer basket; perforated basket bottom; countertop Visible states: basket has grease stains; basket has food residue | N74: 32 | O74: 0 | R74: The evidence shows a dirty air fryer basket with grease and food residue, and ASR discusses cleaning after cooking, not loading food. No information is provided about how to load food into the basket. | S74: VLM|ASR | T74: low | U74: The evidence does not contain any instruction or visual demonstration of loading food into the air fryer basket. | V74: R1 | W74: 0 | Z74: no | AA74: Frames t=47.6s-49.6s show only a dirty basket with grease residue, with no food-loading action. | AC74: completed | AD74: 2026-07-28T01:18:39+08:00 | AE74: =IF(AC74<>"completed","",IF(W74=O74,"no","yes")) | AF74: =IF(AC74<>"completed","",IF(AND(X74=P74,Y74=Q74),"no","yes")) | AG74: =IF(AC74<>"completed","待复核",IF(OR(W74="",Z74="",AA74="",AD74=""),"缺少必填项",IF(AND(OR(AE74="yes",AF74="yes"),AB74=""),"修正原因缺失",IF(OR(W74=0,W74=1),IF(AND(X74="",Y74=""),"通过","0/1级时间应留空"),IF(AND(OR(W74=2,W74=3),X74<>"",Y74<>"",X74>=I74,Y74<=J74,Y74>X74),"通过","2/3级时间无效")))))
A75: VQ-002 | B75: How should food be loaded into an air-fryer basket? | C75: en | D75: Air Fryer | E75: operation | F75: development | G75: pressure-006-scene-0008 | H75: pressure-006 | I75: 22.417 | J75: 26.042 | K75: items/pressure-006-scene-0008/clip.mp4 | L75: items/pressure-006-scene-0008/thumbnail.jpg | M75: ASR: • 360-degree hot air baking, wrapping heating, original flavor, 1500W high power, rapid heating OCR: 8.8.8 Te 0 T0 VLM: Visual summary: A hand uses tongs to place chicken wings onto a perforated metal tray inside an air fryer basket. 视觉摘要: 一只手用夹子将鸡翅放在空气炸锅的金属网篮上。 Visible product: Air Fryer Visible components: air fryer basket; perforated metal tray; tongs; chicken wings Visible actions: placing chicken wings with tongs Visible states: chicken wings being arranged on tray | N75: 33 | O75: 2 | P75: 22.417 | Q75: 26.042 | R75: The video shows a hand using tongs to place chicken wings onto a perforated metal tray inside an air fryer basket, demonstrating a method of loading food into the basket. | S75: VLM | T75: low | U75: The action is clearly visible and directly related to loading food into the air fryer basket, though the specific technique (e.g., layering, spacing) is not detailed. | V75: R1 | W75: 3 | X75: 23.1 | Y75: 25.3 | Z75: no | AA75: Frames from t=23.1 s to t=25.3 s show tongs placing chicken wings onto the perforated tray inside the air fryer basket. | AB75: Visuals directly demonstrate loading food; raised from AI grade 2 to 3. | AC75: completed | AD75: 2026-07-28T01:18:39+08:00 | AE75: =IF(AC75<>"completed","",IF(W75=O75,"no","yes")) | AF75: =IF(AC75<>"completed","",IF(AND(X75=P75,Y75=Q75),"no","yes")) | AG75: =IF(AC75<>"completed","待复核",IF(OR(W75="",Z75="",AA75="",AD75=""),"缺少必填项",IF(AND(OR(AE75="yes",AF75="yes"),AB75=""),"修正原因缺失",IF(OR(W75=0,W75=1),IF(AND(X75="",Y75=""),"通过","0/1级时间应留空"),IF(AND(OR(W75=2,W75=3),X75<>"",Y75<>"",X75>=I75,Y75<=J75,Y75>X75),"通过","2/3级时间无效")))))
A76: VQ-002 | B76: How should food be loaded into an air-fryer basket? | C76: en | D76: Air Fryer | E76: operation | F76: development | G76: airfryer-006-scene-0006 | H76: airfryer-006 | I76: 19.92 | J76: 24.358 | K76: items/airfryer-006-scene-0006/clip.mp4 | L76: items/airfryer-006-scene-0006/thumbnail.jpg | M76: ASR: Here it goes. Flip and cook for maybe a minute or two more till brown. Come with powdered sugar, ready to serve. OCR: GMA 5 FLIP AND COOK FOR AN ADDITIONAL 1-2 MINUTES VLM: Visual summary: A hand is shown interacting with an air fryer, first pulling out a drawer, then using tongs to flip food items inside the basket. 视觉摘要: 一只手正在操作空气炸锅，先是拉出抽屉，然后用夹子翻动锅内的食物。 Visible product: Air Fryer Visible components: air fryer; drawer; basket; tongs; food items; GMA logo Visible actions: pulling out drawer; flipping food with tongs Visible states: food items in basket; drawer partially open Visible warnings: 5 FLIP AND COOK FOR AN ADDITIONAL 1-2 MINUTES | N76: 34 | O76: 2 | P76: 19.92 | Q76: 24.358 | R76: The scene shows a hand using tongs to flip food items inside the air fryer basket, which is an adjacent step to loading food, and includes text instruction 'FLIP AND COOK FOR AN ADDITIONAL 1-2 MINUTES' indicating the context of food handling in the basket. | S76: VLM|ASR|OCR | T76: low | U76: The evidence shows flipping food, not loading, but the action is contextually adjacent and occurs within the same product and scene. | V76: R1 | W76: 1 | Z76: no | AA76: 第1帧 t=19.9s 炸篮中已有食物，第3-5帧 t=21.7s-23.5s 仅在翻动食物，未见放入炸篮的动作。 | AB76: AI等级为2，但画面展示的是翻动已放入炸篮的食物，并未展示如何将食物放入炸篮，不能部分回答加载问题。 | AC76: completed | AD76: 2026-07-28T01:18:39+08:00 | AE76: =IF(AC76<>"completed","",IF(W76=O76,"no","yes")) | AF76: =IF(AC76<>"completed","",IF(AND(X76=P76,Y76=Q76),"no","yes")) | AG76: =IF(AC76<>"completed","待复核",IF(OR(W76="",Z76="",AA76="",AD76=""),"缺少必填项",IF(AND(OR(AE76="yes",AF76="yes"),AB76=""),"修正原因缺失",IF(OR(W76=0,W76=1),IF(AND(X76="",Y76=""),"通过","0/1级时间应留空"),IF(AND(OR(W76=2,W76=3),X76<>"",Y76<>"",X76>=I76,Y76<=J76,Y76>X76),"通过","2/3级时间无效")))))
A77: VQ-002 | B77: How should food be loaded into an air-fryer basket? | C77: en | D77: Air Fryer | E77: operation | F77: development | G77: airfryer-032-scene-0082 | H77: airfryer-032 | I77: 397.1 | J77: 401.7 | K77: items/airfryer-032-scene-0082/clip.mp4 | L77: items/airfryer-032-scene-0082/thumbnail.jpg | M77: ASR: if not all of it should be gone by now and depending on the airfryer model you have this This is a great time to check all the screws that connect the handle to the basket and the pan to the cover. VLM: Visual summary: A close-up view of a screwdriver unscrewing a screw from a black plastic component of an appliance. 视觉摘要: 一个螺丝刀正在从电器的黑色塑料部件上拧下螺丝的特写镜头。 Visible product: Air Fryer Visible components: screwdriver; screw; black plastic component; metallic ring Visible actions: unscrewing Visible states: screw partially removed Visual uncertainty: The full appliance and its context are not visible. | N77: 35 | O77: 0 | R77: The evidence shows unscrewing a screw from an air fryer component, not loading food into the basket. | S77: VLM|ASR | T77: low | U77: No evidence of food loading or basket handling. | V77: R1 | W77: 0 | Z77: no | AA77: Every frame shows a screwdriver unscrewing screws from a plastic air-fryer component, not food being loaded. | AC77: completed | AD77: 2026-07-28T01:18:39+08:00 | AE77: =IF(AC77<>"completed","",IF(W77=O77,"no","yes")) | AF77: =IF(AC77<>"completed","",IF(AND(X77=P77,Y77=Q77),"no","yes")) | AG77: =IF(AC77<>"completed","待复核",IF(OR(W77="",Z77="",AA77="",AD77=""),"缺少必填项",IF(AND(OR(AE77="yes",AF77="yes"),AB77=""),"修正原因缺失",IF(OR(W77=0,W77=1),IF(AND(X77="",Y77=""),"通过","0/1级时间应留空"),IF(AND(OR(W77=2,W77=3),X77<>"",Y77<>"",X77>=I77,Y77<=J77,Y77>X77),"通过","2/3级时间无效")))))
A78: VQ-002 | B78: How should food be loaded into an air-fryer basket? | C78: en | D78: Air Fryer | E78: operation | F78: development | G78: airfryer-030-scene-0001 | H78: airfryer-030 | I78: 0.0 | J78: 1092.15 | K78: items/airfryer-030-scene-0001/clip.mp4 | L78: items/airfryer-030-scene-0001/thumbnail.jpg | M78: ASR: Welcome to Hardin County Extension today. My name is Chandra Doraemus, and I work with Cooperative Extension for Kentucky State University, and today we're going to be talking about using the air fryer to create some nutritious meals, and I'm also going to show you how to make some strawberry skewers with pineapples, and we're going to be featuring our bird's eye meal with the swastikas and broccoli fries, and we'll get started today. So I'm going to be using the air fryer today and this is a 4.2 quart liter size so this is primarily for family meals and if you have a big group of people that you're serving food for and today we're going to be using the bird's eye broccoli fries and we're going to use a little bit of this Pam cooking spray and we're going to heat the oven up here our little air fryer and just to let you know this is supposed to use less cooking oil and it's supposed to be a lot healthier for you so if you haven't considered buying the new air fryer this size is a little bit bigger than the average size usually the quart size is a little bit smaller so you only have one to two servings that you'll get and I can show you here the actual plate of it is actually pretty big and once I put the food in the directions instructed me specifically not to feel to the top so you want to think about that as you're loading your food in the other thing on some of the features they have an actual push button this one does not have a push button some also has electronic controls this one does not it has the controls on the top and so when you turn it on it kind of makes like a loud noise and you have pretty much you put it on a timer we're going to put ours on about 15 minutes about 350 and those were the instructions they have you a little instruction booklet and it gives you gives you a time and um temperature to put whatever you're cooking on so that way you don't overheat or overcook something so in just a few minutes is here, I'm going to go ahead and spray us down with the Pam. And this is my first time using the unit. And just as a side note, they said that there would be a little bit of smoking. So just don't get concerned if it smokes just a little bit. The other thing is it says just do not immerse the whole machine in water because that would be an electronic kind of electrical shock warning there so make sure you don't immerse this whole machine in water to clean it all you would have to do is remove this bottom half like I did so pull it out and wash the inside unit after we actually use utilize it with the broccoli fries so you want to be mindful of that so I'm gonna go ahead and insert the broccoli fries here and this is nutritious cooking so I noticed I didn't use any actual oil so I'm just going to dump the fries in here and we're just going to let those go ahead and start cooking for a few minutes. And so one thing to note about our nutritious snack we have here with the bird's eye broccoli fries, I have a nutrition label here. I printed it out and it has 21 grams of carbs, has 290 milligrams of sodium. Now if you have someone who has high high blood pressure, diabetes, it's going to be really important. Also, it has 0.16 milligrams of iron, 160 milligrams of potassium, so it's going to provide a pretty good amount of energy for you. The carbs is kind of high for somebody who's diabetic. If you're diabetic, you do have to watch your carb limits throughout the day, so this may be a little bit too much on your carb I would recommend if you are going to eat them and you have diabetes to only eat about three or four so that throughout the day you can use some of your carbs for a much bigger meal than just broccoli fries. Like I said, I recommend this for kids because they love eating fries. It's something quick that you can do in the summertime, something handy, something they can pick up with their own hands. and so like I said we're waiting on it to get finished and while that's cooking I have already started preparing our strawberry and pineapple kebabs and those are some really good treats for kids you can put them on little sticks and you can put them on little toothpicks and it's a very colorful fruit and the best thing about it is kids can actually help you make them it's super easy. All you have to do is cut off the ends of the strawberries and pretty much just stick the little strawberries through the little skewer or the little stick and you have a nice little treat. So we're going to talk about that a little bit later after we get finished with the broccoli fries and we're just gonna take a little break. Alright well back with our pineapples and strawberries and so we're going to be doing some strawberry and pineapple skewers today and this usually takes about 10 to 15 minutes and it's a very light fruit that you can enjoy with your family you can use your kids you guys can make this kind of a summer treat something that they can fix it on their own or you can do it together so I have what I actually used in our little recipe here and it typically just uses your strawberries and pineapples and so So I purchased some pineapple chunks from Kroger, and one little can of this, if you're gonna get the Kroger brand, typically runs about $1.50 with tax. Now they do have the other brands like the Dole, which usually run about $2, and the nutrition facts are about the same for it. For this one, pretty much you're gonna get high amounts of vitamin C at 20%, and you're gonna get 2% of iron, and it has 10 milligrams of sodium total carbs is 17 grams and you have about amount per serving it's about a half a cup so I only use half a cup for this presentation on the strawberries I use one carton or one small half of a carton of strawberries and I actually took the strawberries and I'll cut the little green half off and this is a personal um personal decision here you can either cut the strawberry in half or you can leave it whole i i mostly for the most part just for presentation reasons i kept the strawberry whole but if you have a lot of kids that you're feeding for the price of the strawberries um you might want to cut them in half i would highly recommend that just because of the cost. For original cost on one little half carton or a little bunch of your strawberries is $5. Fortunately yesterday I was able to get these for $2.50. I didn't realize that until I got to the register. It was a very, very good moment for me. So as far as your pineapple chunks, when you're using a whole pineapple that is actually a pineapple, pineapple, you can get the benefit of having that fresh fruit. You will have to just probably use one half of the pineapple, which you'll start by cutting it in half. Then you will have to take off the jacket edges of the pineapple and use it in that way. Now what I would recommend also is that you go ahead and purchase your wooden skewers, which I have here with the strawberries and pineapples already on them also i would recommend purchasing toothpicks but i recommend purchasing some colorful toothpicks because it's going to be a little bit more colorful and it's going to get your kids more interested in eating fruits because kids tend to be some of them especially if they're a taller age or between the ages of five to ten they may not want to eat fruits or vegetables right off the top so you want to encourage them to eat more fruits and vegetables so the way you're going to do that is you use it as the fruits as finger foods and it will let allow them to pick up the fruit themselves but with the use of the toothpick and what you will do with your toothpick is you will put it in the center of the pineapple chunk and you will allow them to actually use eat it themselves and they'll feel like they're more in control and then that way you kind of introduce the fruit or introduce them into eating fruits and it's going to be something that's very nutritious for them and it also has that sweet taste that they are used to with with drinking fruit juices and a lot of the capri suns and things of that nature but it's a different kind of fruit it's more of a natural fruit so their body will be it will be a lot easier for them to digest and it won't be as high calories as some of your ice creams and some of your shakes and things of that nature. Also some of your chocolate bars, things that kids are more likely or amped to ask for. So this is just going to be something that you could give them as an option so that they won't gain too much weight over the summer by eating things that aren't as nutritious and healthy for them like i mentioned before the sugars in these are going to be a lot healthier now in terms of if you're on the go if you're on the go mom on the go dad and you're always with your kids you got soccer practice you got football practice you might want to use i would recommend using these as takeaways or as your little carriers for your fruit and what you would do is you literally would just put the fruit in one of these little containers and use the top twist it on and it doesn't pour out you don't have to worry about it spilling on your car seat you don't have to worry about that you can actually put it in a lunch bag that zips up then you really won't have to worry about it'll be pretty much leak proof and spill proof and also if your kid happens to deal with it themselves it's just something that's very small they could probably get the top off themselves without your help. So that's something that I would recommend for you to use as far as storing your fruit. Now, I have already prepared the strawberry and pineapple skewers prior to this presentation. As you can see here, I used more of a half of the fruit kebabs or created little kebabs and like I said they're a nice little easy little dish that you can create nice little fruit and here I use the whole strawberry on the one on the top just it seems to be a little bit extremely big and top-heavy but like I said this is gonna be very sweet but at the same time the strawberries gonna have a little bit of that tartness so So it's going to be still nutritious for your kids and very easy to handle. So over here I have the little toothpicks with the little pineapple chunks on them and look how tiny it is. I mean look how small and cute. I mean the kids are just going to love this because it's so cute and it's so nutritious. I think they're going to love it. So with that being said, I think I've shown you all the things that we've done with our strawberry and pineapple skewers today now we're going to see how our broccoli fries turned out hi we're back with the hardin county extension today and we're going through some um food options that we're cooking in the air daddy today and we cooked some broccoli fries and now they are done so i'm going to go through and go ahead and open up our little bin here and oh my gosh look how how wonderful these turned out. So if you can, as you can see there, they turned out pretty crispy, no grease. And we're gonna put it on a little paper towel here. And we're gonna go ahead and get these out. And I think that this is gonna be a nutritious little treat for us here. Oh, they're really crispy. And as you can see, the reason why I'm putting it on these paper towels is I want you to see that there is no grease. hey like that right so um and this is broccoli oh my gosh can you believe it um the birds eye also has a cauliflower variety version and man i tell you it is very very nutritious it's good has about the same amount of potassium as the broccoli and i keep talking about potassium potassium because potassium gives you a lot of energy. So it helps you throughout the day. You don't have to drink all those energy drinks and it's healthy. So why not eat it? So this is going to be something that I recommend instead of eating french fries at McDonald's, Wendy's, wherever. Not trying to talk down on the fast food restaurants. However, the calorie amount of eating say 10 of these versus eating 10 fries from McDonald's you got to think that's more saturated fats it's more not healthy for you so this way you get to eat good and you're healthy so sorry about that so hopefully you have learned some nutritious tips for me today and you have will actually utilize some of these tips on this summer and you and your family can have some nutritious treats I would just recommend in terms of cleaning the air daddy like I said before just take your unit out and just wash that part out you don't have to use watch this at all now if you get something down on the inside of the plate or something just use a rag with warm water and dishwash dishwashing liquid and clean it and I recommend also putting on these little mittens like I have because for safety reasons the handle is really not that hot it's lonely warm however with kids I don't want you to burn your hand or for it to be too warm for you so that's why I recommend using the mittens and make sure your unit is turned off typically it will turn off by itself however if you were to open it and take out something early you will have to manually shut the unit down and how you would do that is turn your dial counterclockwise to the zero on your time side you don't have to change your dial on the temperature. You only can keep the temperature where it is currently located and that's how you would shut the unit off. I would recommend allowing the unit to cool at least 30 to 45 minutes. I also would not recommend putting it inside of your car close to any plastic because the unit is still fairly warm. It's not hot. However, if you do have to travel with it, like I said, give it at least 10 to 15 minutes if you're on the go and you have somewhere to be but if you can wait that 30 to 45 minutes to let it completely cool down and then move the unit to your car maybe inside of a box or something more mobile to the point where you won't drop anything and that's all I would recommend in terms of cleaning and moving the unit after you have just used it and as far as your snacks go I have I decided to do broccoli fries however this unit can cook chicken pork chops steak muffins fish anything so if you have some other things that you want to try in it go ahead and it's gonna come out just as good as our broccoli fries did and it's gonna be tasty so that's all I have for you today and I hope you enjoyed this this session with me. Thanks for joining us for Hardin County Extension today. Today we went over a couple of nutritious snacks and things of that nature and I hope you will join us for other calendar events later on in the month and I hope to see you then. OCR: Hardin County Extension Today Music Sponsoredby COOPERATIVE EXTENSION UK KENTUCKY UNIVERSITY OI STATE College of Agriculture INVERSITV FARM BUREAU FMusicJNT Youth Project Completion Show Featuring Nutritious Snacks Using an Air Fryer Chandra DeRamus Family & Consumer Science Extension Agent Hardin County Extension Today or University. ELELE 5 o me meais Hardin County Estension Today LOLE some strawberry skewers ineapp Hardin County Extonsion Today with t h e Swanson broccolitries Hardin Caunty Extonsion Today hn ths 1s primarily tor tami that you're serving tood a nd toda y n d nna use i tt a m e C spray Kardin County Extension Today gonna heat t he oven u p t hi supposed u 5 e e55 cooking considered sa oretty a n d put t o od So you want to think about that so me a I s o controis o + a y o u p u t t o n timer 3 5 0 Ittle Hardin @ounty Extension Today w a y don't overheat overcook something spr o W n † sa1d t h a t there WouId 5moking The other thing is it says n mmer wa remove this bottom h ait like I d i d We h want t o mi ndt u l t hat nse Hardlin County Extension Today na have nutrtion I a b e 1oes Notrition Facts And i t has 21 grams ot carbs Bird's Eye Broccoli HEW! Friles Nutritious Snack BROC(OL Fextares lering Se 4 8 pleces (86) Great snaick for kids in the summert Lunch oe in bebeen Nutrition AIRDADOY Calories 160 h a s 2 9 0 milligrams ot sodium. WEW Fries EROLLOL Teatrs 8 gleces (Mg) Great saca t h e the h1 Hardin County Extoasion Today NEW! BROCCOU Features: Serving Sure:4 8 pleces (86g) Great snack for kids in the sumumert Lunch or in between dinner. AlSO it has 0.16 igrams iron Bird's Eye Broccolil EW1 Nutntieus Snack Serang Se eces (8) tassium o n n a aras wh vou diabetic watch o ur b imits throughout the day. so this m a muc diabetes abo ut three h e ur carbs Like I said I recommend this tor kids. uck ha summertime whe that's cooking already start preparing our strawberry and pineapple kebabs, those a r rea good r k is avery colortul truit h ave much just stick trawberries nrough little skewer stick t a I k a b o u t u st reak And so. we're gonna be d o i n g Fardin County Extension Today ardin County Extension Today n County Cxtension Today or you could do it together. her nd chunks trom Kroger ne Iittl can o† Hardin Caunty Extension Taday ypically runs 5 0 t a x Hardin County Extensien Today reapples Churte which usua lly run about 5 2.0 0 Hardin Ceunty Extension Today eapple.Chur nst mo un Eardin County Extension Today has it's about a halt a cup. Hardie County Cxtension Today strawberries carton And I actually took t his persona ecision here Hardin County Extension Tadsy you can either cut the h a -t most part. just Hardin County Extansion Today W n I would highly recommend that. just because ot the cost Ittle bunch ot your rawberries. i5 S5 Fortunately yeste w a wa s very. ver ood momen Hardh County Extension Today As tar as your pineapple chunks, that is actually a pineapple which you'll start by cutting it in halt the pineapple, and a h e a d Sr wooden h a ve here, with the awberries pineapples Hardin Ceunty Extonsion Today between a ges t e n i g h t o tt t o p The way youire gonna do that. truits to pick up the truit themseives with the use ot the toothpick Hardin County Extension Todiay is you will put it in the ot the pineapplechunk And you will allow them eat it thems ve s And then way you ntroduce Hardin County Extension -Today or introduce them eating Hardin County Extension Toduy it's more ot a natural truit t he m digest a nd it y o ur creams Hardin County Extension Joday k ids are more a 5 k 1 0 n t he y weiqht Wardin County Extension -Today aren't a s heait hy o r he Hardin County Extension-Today or rs your lytle ruit And what you do And also it your kid happens deai with it thas just sonething They couId probably om o mmend Now, I have already prepared prior to this presentation. kebabs Hardin Countg Extension Joday and like I said, they're I i t t l e . e a s y I i t t l e d i s h Hardir County Extension Today extremely b 1 g a nd top hea vy Iaughs Hardin County Extonsino Taday at same time. the wberry qonna Kardin County Extonsion Today be stii your kid s very e a s y to handle. Hardin County Extenston Today Over here I have the itt-e toothpicks Hardir Gounty Extension Today mean lo0k h ow smal l and cute a n din County Extension Today trawberr N ow HardinCouaty Extension Toda ac t h H a r - n5 ay n o w done u m urned out you can see there, they out pretty crispy Oh. they're really crispy. Harditn County Extension Today 0 n these paper towels. w ant to Hey.like that.right? hi s c a n The Birdseye also has variety version m a n a use potassium gives ener instead ot eating trench tries his you get to eat heaithy So,(coughs) sorry about that et u l ly you Iearned o5 some ot these tips on this summer recommend i n q Air Daddy ju s t wash part d o w n inside ot the Just use a rag with warm water and dishwashing iiquid a iso. putting itt mittens have. because reasons warm why take out something early turn ;al counter ckw 5 7 change temperature where it is currently Iocated would u n it a t Ieast 3 0 4 5 minutes. Hardin County Extension comp |etey cool down maybeinside ot box 5ome wo uId terms cleaning movinq a5 tar snacksgo however, this unit cook chicken steak 5h anything that you want t rv qo a head hav tod ay o d a y o day went over o1n Would you like to have a quilt on your barn'and be listed on the"Clothesline of Quilts Trail"'? Contact the Hardin Co. Extension Musicervice Office @ 270-765-4121 “Embroidery Club' welcomes new members the 4th Tuesday of each month, from 10-2:00 p.m. Bring any project you are working on or one you need help with Registration not required! Embroidery Club members the 4th month from 10-2:00 project you are on or one you need help with Registration not “Applique' Sew Fun" meets from 9-2:00 pm on the 3rd Weds. of each' month \Music come join us! “Cross Stitchers will meet occasionally Saturdays beginning Oct. 1,'from 9 9-5:00 pm. Work current projects & learn new techniques each other. For beg eginners experienced stitchers. Brngg or supplies get started, someone help you.' No RSVP necessary; just show up! For more information on the above events orany other classes call Hardin Co. Cooperative of the University of (270) 765-4121. Videographer/Editor Reed Sampley For more information on HCEC-TV programming call 270-769-8855 www.hardin.k12.ky.us/HCEC-TV Mu s i cla ryan@hardin.kyschools.us VLM: Visual summary: A woman in a green apron is demonstrating a black kitchen appliance in a kitchen setting, gesturing and speaking while holding a small object. 视觉摘要: 一位穿着绿色围裙的女士在厨房里演示一台黑色厨房电器，边做手势边说话，手中拿着一个小物件。 Visible product: Air Fryer Visible components: black appliance; white countertop; wooden cabinets; white sink; paper towel holder; green apron; white gloves; plate with food Visible actions: woman gesturing with hand; woman speaking; woman holding object Visual uncertainty: The exact product name is not visible, only the category 'Air Fryer' is provided. The specific features or actions being demonstrated are inferred from subtitles, not directly visible. | N78: 36 | O78: 2 | P78: 600.0 | Q78: 630.0 | R78: ASR states: '...directions instructed me specifically not to fill to the top so you want to think about that as you're loading your food in...' which directly addresses the question about how food should be loaded into the air-fryer basket. | S78: ASR | T78: low | U78: The ASR evidence is clear and directly addresses the question with explicit instruction about not overfilling the basket. | V78: R1 | W78: 1 | Z78: no | AA78: 第2帧（t=218.4s）仅显示演讲者站在空气炸锅旁，第5帧（t=873.7s）显示用夹子从炸篮中取物，均未清晰呈现将食物放入炸篮的加载动作。 | AB78: Contact sheet samples the whole video sparsely; relevant visual evidence is at 218.4-873.7 s, not 600-630 s. | 第三轮双复核一致修正：R1=2→indep=1：稀疏采样帧中未见食物被放入炸篮的直接画面，仅有炸篮操作相邻片段；时间区间不再适用。 | AC78: completed | AD78: 2026-07-28T20:35:21+08:00 | AE78: =IF(AC78<>"completed","",IF(W78=O78,"no","yes")) | AF78: =IF(AC78<>"completed","",IF(AND(X78=P78,Y78=Q78),"no","yes")) | AG78: =IF(AC78<>"completed","待复核",IF(OR(W78="",Z78="",AA78="",AD78=""),"缺少必填项",IF(AND(OR(AE78="yes",AF78="yes"),AB78=""),"修正原因缺失",IF(OR(W78=0,W78=1),IF(AND(X78="",Y78=""),"通过","0/1级时间应留空"),IF(AND(OR(W78=2,W78=3),X78<>"",Y78<>"",X78>=I78,Y78<=J78,Y78>X78),"通过","2/3级时间无效")))))
A79: VQ-002 | B79: How should food be loaded into an air-fryer basket? | C79: en | D79: Air Fryer | E79: operation | F79: development | G79: airfryer-017-scene-0019 | H79: airfryer-017 | I79: 149.049 | J79: 156.757 | K79: items/airfryer-017-scene-0019/clip.mp4 | L79: items/airfryer-017-scene-0019/thumbnail.jpg | M79: ASR: The fix it video I watched previously said to check the door of the air fryer to make sure it wasn't loose and preventing the air fryer from working. But as I found out later, the metal bumps on top of the fryer door are just attached OCR: 2 S VLM: Visual summary: A person is interacting with a stainless steel air fryer on a dark wooden table in a room with furniture and decorations in the background. 视觉摘要: 一个人正在与放在深色木桌上的不锈钢空气炸锅互动，背景是家具和装饰品。 Visible product: Air Fryer Visible components: stainless steel appliance; black front panel; handle; dark wooden table; window with blinds; chairs; stuffed animals; decorative wall pieces; toy house Visible actions: hand holding the handle; hand pressing or pulling the handle Visible states: appliance on table; appliance in use or being operated Visual uncertainty: The exact function of the action being performed is not visible. | N79: 37 | O79: 0 | R79: The visual evidence shows a person interacting with the air fryer handle but does not show food being loaded into the basket or any related action. | S79: VLM | T79: low | U79: The action is not clearly identifiable as loading food into the basket, and no food or basket loading is visible. | V79: R1 | W79: 0 | Z79: no | AA79: The frames show the air fryer drawer being handled, not food being loaded into the basket. | AC79: completed | AD79: 2026-07-28T01:18:39+08:00 | AE79: =IF(AC79<>"completed","",IF(W79=O79,"no","yes")) | AF79: =IF(AC79<>"completed","",IF(AND(X79=P79,Y79=Q79),"no","yes")) | AG79: =IF(AC79<>"completed","待复核",IF(OR(W79="",Z79="",AA79="",AD79=""),"缺少必填项",IF(AND(OR(AE79="yes",AF79="yes"),AB79=""),"修正原因缺失",IF(OR(W79=0,W79=1),IF(AND(X79="",Y79=""),"通过","0/1级时间应留空"),IF(AND(OR(W79=2,W79=3),X79<>"",Y79<>"",X79>=I79,Y79<=J79,Y79>X79),"通过","2/3级时间无效")))))
A80: VQ-002 | B80: How should food be loaded into an air-fryer basket? | C80: en | D80: Air Fryer | E80: operation | F80: development | G80: airfryer-033-scene-0159 | H80: airfryer-033 | I80: 1415.382 | J80: 1424.925 | K80: items/airfryer-033-scene-0159/clip.mp4 | L80: items/airfryer-033-scene-0159/thumbnail.jpg | M80: ASR: Mentira Ui, quente Quente Ai meu Deus, quente Vou pegar um pratinho aqui, aguenta aí VLM: Visual summary: A hand is placing potato wedges into the basket of an air fryer. 视觉摘要: 一只手将土豆块放入空气炸锅的篮子中。 Visible product: Air Fryer Visible components: air fryer basket; air fryer interior; potato wedges; hand Visible actions: placing potato wedges into air fryer basket | N80: 38 | O80: 3 | P80: 1415.382 | Q80: 1424.925 | R80: A hand is visually placing potato wedges into the air fryer basket, directly demonstrating how food should be loaded. | S80: VLM | T80: low | U80: The action is clearly visible and matches the question's intent without ambiguity. | V80: R1 | W80: 3 | X80: 1417.3 | Y80: 1419.2 | Z80: no | AA80: Frames t=1417.3-1419.2 s clearly show a hand placing potato wedges into the air fryer basket. | AB80: Direct loading occurs at 1417.3-1419.2 s, narrower than AI's full-window time. | AC80: completed | AD80: 2026-07-28T01:18:39+08:00 | AE80: =IF(AC80<>"completed","",IF(W80=O80,"no","yes")) | AF80: =IF(AC80<>"completed","",IF(AND(X80=P80,Y80=Q80),"no","yes")) | AG80: =IF(AC80<>"completed","待复核",IF(OR(W80="",Z80="",AA80="",AD80=""),"缺少必填项",IF(AND(OR(AE80="yes",AF80="yes"),AB80=""),"修正原因缺失",IF(OR(W80=0,W80=1),IF(AND(X80="",Y80=""),"通过","0/1级时间应留空"),IF(AND(OR(W80=2,W80=3),X80<>"",Y80<>"",X80>=I80,Y80<=J80,Y80>X80),"通过","2/3级时间无效")))))
A81: VQ-002 | B81: How should food be loaded into an air-fryer basket? | C81: en | D81: Air Fryer | E81: operation | F81: development | G81: airfryer-005-scene-0039 | H81: airfryer-005 | I81: 338.741 | J81: 352.002 | K81: items/airfryer-005-scene-0039/clip.mp4 | L81: items/airfryer-005-scene-0039/thumbnail.jpg | M81: ASR: Now I want to cut into the yoke here just to show you kind of what the yoke looks like. I'm just going to cut kind of straight through and there should be a little bit of a run to that yoke. OK, awesome. VLM: Visual summary: A person is cutting into a piece of toast with an egg and bacon on it, while another similar piece sits untouched on a white plate. 视觉摘要: 一个人正在切一片放有鸡蛋和培根的吐司，旁边另一片类似的吐司放在白色盘子上未动。 Visible product: unknown Visible components: white plate; toasted bread; egg; bacon; knife; fork; hand Visible actions: cutting food with a knife and fork; eating food Visible states: egg yolk broken; food partially eaten | N81: 39 | O81: 0 | R81: The scene shows cutting toast with egg and bacon, not loading food into an air-fryer basket. No air-fryer or related loading action is visible or mentioned. | S81: VLM|ASR | T81: low | U81: No evidence of air-fryer or food loading action is present. | V81: R1 | W81: 0 | Z81: no | AA81: All frames show toast with egg and bacon being cut on a plate; no air fryer or loading action is visible. | AC81: completed | AD81: 2026-07-28T01:18:39+08:00 | AE81: =IF(AC81<>"completed","",IF(W81=O81,"no","yes")) | AF81: =IF(AC81<>"completed","",IF(AND(X81=P81,Y81=Q81),"no","yes")) | AG81: =IF(AC81<>"completed","待复核",IF(OR(W81="",Z81="",AA81="",AD81=""),"缺少必填项",IF(AND(OR(AE81="yes",AF81="yes"),AB81=""),"修正原因缺失",IF(OR(W81=0,W81=1),IF(AND(X81="",Y81=""),"通过","0/1级时间应留空"),IF(AND(OR(W81=2,W81=3),X81<>"",Y81<>"",X81>=I81,Y81<=J81,Y81>X81),"通过","2/3级时间无效")))))
A82: VQ-002 | B82: How should food be loaded into an air-fryer basket? | C82: en | D82: Air Fryer | E82: operation | F82: development | G82: airfryer-024-scene-0003 | H82: airfryer-024 | I82: 7.574 | J82: 11.478 | K82: items/airfryer-024-scene-0003/clip.mp4 | L82: items/airfryer-024-scene-0003/thumbnail.jpg | M82: ASR: We love great tasting fried food, but who wants to deal with the mess and all the added fat and calories? Now you can have all the deep fried food you love without the oil. OCR: Now have all the fried food you love VLM: Visual summary: A deep fryer with a basket is shown on a countertop next to two large plastic jugs containing liquid. A close-up shows chicken pieces frying in the fryer basket. 视觉摘要: 一个深油炸锅配有篮子，放在台面上，旁边有两个装有液体的大塑料壶。特写镜头显示鸡块在油炸锅篮子中油炸。 Visible product: Air Fryer Visible components: deep fryer; frying basket; plastic jugs; countertop Visible states: chicken frying in oil; oil bubbling | N82: 40 | O82: 0 | R82: The evidence shows a deep fryer with chicken frying in oil, not an air fryer, and does not show or describe how food is loaded into an air fryer basket. | S82: VLM|ASR|OCR | T82: low | U82: The visible product is a deep fryer, not an air fryer, and no loading action or instruction is shown. | V82: R1 | W82: 0 | Z82: no | AA82: Frames at 9.9s and 10.7s show chicken pieces frying in bubbling oil in a deep fryer basket, with no air fryer visible across the 7.6-11.5s window. | AC82: completed | AD82: 2026-07-28T01:18:39+08:00 | AE82: =IF(AC82<>"completed","",IF(W82=O82,"no","yes")) | AF82: =IF(AC82<>"completed","",IF(AND(X82=P82,Y82=Q82),"no","yes")) | AG82: =IF(AC82<>"completed","待复核",IF(OR(W82="",Z82="",AA82="",AD82=""),"缺少必填项",IF(AND(OR(AE82="yes",AF82="yes"),AB82=""),"修正原因缺失",IF(OR(W82=0,W82=1),IF(AND(X82="",Y82=""),"通过","0/1级时间应留空"),IF(AND(OR(W82=2,W82=3),X82<>"",Y82<>"",X82>=I82,Y82<=J82,Y82>X82),"通过","2/3级时间无效")))))
A83: VQ-002 | B83: How should food be loaded into an air-fryer basket? | C83: en | D83: Air Fryer | E83: operation | F83: development | G83: pressure-006-scene-0007 | H83: pressure-006 | I83: 19.875 | J83: 22.417 | K83: items/pressure-006-scene-0007/clip.mp4 | L83: items/pressure-006-scene-0007/thumbnail.jpg | M83: ASR: • Touch screen control, LCD display, visual window, cooking process at a glance • 360-degree hot air baking, wrapping heating, original flavor, 1500W high power, rapid heating VLM: Visual summary: A cooked whole chicken surrounded by chopped potatoes inside a black air fryer basket, which is placed in a yellow appliance. 视觉摘要: 一只烤好的整鸡，周围围着切块的土豆，放在一个黑色空气炸锅篮子里，篮子置于一个黄色的电器中。 Visible product: Air Fryer Visible components: black air fryer basket; yellow appliance body; cooked whole chicken; chopped potatoes Visible states: food cooked; food resting in basket | N83: 41 | O83: 1 | R83: The scene shows cooked food (chicken and potatoes) already in the basket, but does not show or describe how food is loaded into the basket. | S83: VLM | T83: low | U83: No evidence of loading action or instruction is present. | V83: R1 | W83: 1 | Z83: no | AA83: Frames at 20.9s-21.9s show a fully cooked whole chicken already resting in the air fryer basket, with no loading action captured across the window. | AC83: completed | AD83: 2026-07-28T01:18:39+08:00 | AE83: =IF(AC83<>"completed","",IF(W83=O83,"no","yes")) | AF83: =IF(AC83<>"completed","",IF(AND(X83=P83,Y83=Q83),"no","yes")) | AG83: =IF(AC83<>"completed","待复核",IF(OR(W83="",Z83="",AA83="",AD83=""),"缺少必填项",IF(AND(OR(AE83="yes",AF83="yes"),AB83=""),"修正原因缺失",IF(OR(W83=0,W83=1),IF(AND(X83="",Y83=""),"通过","0/1级时间应留空"),IF(AND(OR(W83=2,W83=3),X83<>"",Y83<>"",X83>=I83,Y83<=J83,Y83>X83),"通过","2/3级时间无效")))))
A84: VQ-002 | B84: How should food be loaded into an air-fryer basket? | C84: en | D84: Air Fryer | E84: operation | F84: development | G84: airfryer-032-scene-0038 | H84: airfryer-032 | I84: 173.667 | J84: 176.367 | K84: items/airfryer-032-scene-0038/clip.mp4 | L84: items/airfryer-032-scene-0038/thumbnail.jpg | M84: ASR: about a tablespoon or two of lemon juice, place it in the air fryer basket, and run it for five OCR: COSORI X 5. °F ITAT 400" + Realen VLM: Visual summary: A hand holds a glass bowl containing a light-colored liquid over the basket of an air fryer. 视觉摘要: 一只手拿着一个装有浅色液体的玻璃碗，悬在空气炸锅的篮子上方。 Visible product: Air Fryer Visible components: glass bowl; air fryer basket; hand Visible actions: holding a bowl; positioning bowl over air fryer basket Visible states: liquid in bowl; air fryer basket empty | N84: 42 | O84: 1 | R84: The scene shows a bowl being held over the air fryer basket, and ASR mentions placing lemon juice in the basket, but no actual loading action is shown or described. | S84: VLM|ASR | T84: low | U84: No evidence of food being loaded into the basket, only liquid and positioning. | V84: R1 | W84: 1 | Z84: no | AA84: Frames at 173.7s-176.4s show a hand holding a glass bowl of liquid over the air fryer basket; food (not liquid) loading is not depicted. | AC84: completed | AD84: 2026-07-28T01:18:39+08:00 | AE84: =IF(AC84<>"completed","",IF(W84=O84,"no","yes")) | AF84: =IF(AC84<>"completed","",IF(AND(X84=P84,Y84=Q84),"no","yes")) | AG84: =IF(AC84<>"completed","待复核",IF(OR(W84="",Z84="",AA84="",AD84=""),"缺少必填项",IF(AND(OR(AE84="yes",AF84="yes"),AB84=""),"修正原因缺失",IF(OR(W84=0,W84=1),IF(AND(X84="",Y84=""),"通过","0/1级时间应留空"),IF(AND(OR(W84=2,W84=3),X84<>"",Y84<>"",X84>=I84,Y84<=J84,Y84>X84),"通过","2/3级时间无效")))))
A85: VQ-002 | B85: How should food be loaded into an air-fryer basket? | C85: en | D85: Air Fryer | E85: operation | F85: development | G85: airfryer-032-scene-0058 | H85: airfryer-032 | I85: 267.2 | J85: 269.833 | K85: items/airfryer-032-scene-0058/clip.mp4 | L85: items/airfryer-032-scene-0058/thumbnail.jpg | M85: ASR: a little bit faster. And then after cleaning, make sure your air fryer is nice and dry before you plug it back in and use it. I tend to let mine sit overnight and dry completely just for a little VLM: Visual summary: A person is holding a black air fryer basket while standing next to a black air fryer on a kitchen countertop. 视觉摘要: 一个人正拿着一个黑色空气炸锅篮子，站在厨房台面上的黑色空气炸锅旁。 Visible product: Air Fryer Visible components: black air fryer basket; black air fryer; kitchen countertop; person's hand; person's red sleeve Visible actions: person holding air fryer basket | N85: 43 | O85: 1 | R85: The visual shows a person holding the air fryer basket, but no action of loading food is depicted or described. | S85: VLM | T85: low | U85: No evidence of food being loaded into the basket. | V85: R1 | W85: 1 | Z85: no | AA85: Frames at 267.2s and 269.8s show an empty square air fryer basket being held; no food or placement action is captured. | AC85: completed | AD85: 2026-07-28T01:18:39+08:00 | AE85: =IF(AC85<>"completed","",IF(W85=O85,"no","yes")) | AF85: =IF(AC85<>"completed","",IF(AND(X85=P85,Y85=Q85),"no","yes")) | AG85: =IF(AC85<>"completed","待复核",IF(OR(W85="",Z85="",AA85="",AD85=""),"缺少必填项",IF(AND(OR(AE85="yes",AF85="yes"),AB85=""),"修正原因缺失",IF(OR(W85=0,W85=1),IF(AND(X85="",Y85=""),"通过","0/1级时间应留空"),IF(AND(OR(W85=2,W85=3),X85<>"",Y85<>"",X85>=I85,Y85<=J85,Y85>X85),"通过","2/3级时间无效")))))
A86: VQ-003 | B86: 怎样插回炸篮并启动空气炸锅？ | C86: zh-CN | D86: Air Fryer | E86: operation | F86: development | G86: airfryer-033-scene-0037 | H86: airfryer-033 | I86: 266.9 | J86: 271.004 | K86: items/airfryer-033-scene-0037/clip.mp4 | L86: items/airfryer-033-scene-0037/thumbnail.jpg | M86: ASR: Que não tem necessidade de ficar aqui Ou seja, tá suja ainda Porque ela tava em uso A gente, quando a gente tava no outro apartamento VLM: Visual summary: An air fryer is shown unboxed on a white cloth, with its basket and lid visible, and packaging materials nearby. 视觉摘要: 一台空气炸锅被拆箱放置在白色布上，其炸篮和盖子可见，旁边有包装材料。 Visible product: Air Fryer Visible components: air fryer basket; air fryer lid; power cord; plastic packaging Visible actions: unboxing; placing on cloth Visible states: unboxed; assembled Visual uncertainty: The brand name is partially visible but not fully legible. | N86: 1 | O86: 0 | R86: The scene shows an unboxed air fryer with its basket and lid visible, but no action of inserting the basket or starting the appliance is shown. | S86: VLM | T86: low | U86: No evidence of basket insertion or appliance startup is present in the visual or audio content. | V86: R1 | W86: 1 | Z86: no | AA86: Frames at 268.5s-270.2s show the air fryer with the basket already inside the cavity; no insertion motion or startup action is captured. | AB86: AI marked 0; the same air fryer is visible, only the insertion action is absent, so grade 1. | AC86: completed | AD86: 2026-07-28T01:18:39+08:00 | AE86: =IF(AC86<>"completed","",IF(W86=O86,"no","yes")) | AF86: =IF(AC86<>"completed","",IF(AND(X86=P86,Y86=Q86),"no","yes")) | AG86: =IF(AC86<>"completed","待复核",IF(OR(W86="",Z86="",AA86="",AD86=""),"缺少必填项",IF(AND(OR(AE86="yes",AF86="yes"),AB86=""),"修正原因缺失",IF(OR(W86=0,W86=1),IF(AND(X86="",Y86=""),"通过","0/1级时间应留空"),IF(AND(OR(W86=2,W86=3),X86<>"",Y86<>"",X86>=I86,Y86<=J86,Y86>X86),"通过","2/3级时间无效")))))
A87: VQ-003 | B87: 怎样插回炸篮并启动空气炸锅？ | C87: zh-CN | D87: Air Fryer | E87: operation | F87: development | G87: airfryer-024-scene-0006 | H87: airfryer-024 | I87: 19.953 | J87: 22.689 | K87: items/airfryer-024-scene-0006/clip.mp4 | L87: items/airfryer-024-scene-0006/thumbnail.jpg | M87: ASR: Now make crispy air fried French fries in just 8 minutes, crunchy onion rings in 10 minutes, OCR: AIR-FRIED French Fries only 8 Minutes VLM: Visual summary: A person is pouring cooked French fries from an air fryer basket into a red and white checkered paper-lined basket. 视觉摘要: 一个人正将从空气炸锅篮子里倒出的炸薯条倒入一个红白格子纸衬的篮子中。 Visible product: Air Fryer Visible components: air fryer basket; red and white checkered paper liner; paper bag; white cup; text overlay: AIR-FRIED French Fries Visible actions: pouring French fries; holding air fryer basket Visible states: French fries being transferred; fries in basket; fries in air fryer basket | N87: 2 | O87: 1 | R87: The scene shows fries being poured out of the air fryer basket, indicating removal, not insertion or startup. | S87: VLM | T87: low | U87: No evidence of inserting the basket or starting the air fryer. | V87: R1 | W87: 1 | Z87: no | AA87: Frames t=20.0s-22.7s show the basket being removed and fries poured out, not reinserted or started. | AC87: completed | AD87: 2026-07-28T01:18:39+08:00 | AE87: =IF(AC87<>"completed","",IF(W87=O87,"no","yes")) | AF87: =IF(AC87<>"completed","",IF(AND(X87=P87,Y87=Q87),"no","yes")) | AG87: =IF(AC87<>"completed","待复核",IF(OR(W87="",Z87="",AA87="",AD87=""),"缺少必填项",IF(AND(OR(AE87="yes",AF87="yes"),AB87=""),"修正原因缺失",IF(OR(W87=0,W87=1),IF(AND(X87="",Y87=""),"通过","0/1级时间应留空"),IF(AND(OR(W87=2,W87=3),X87<>"",Y87<>"",X87>=I87,Y87<=J87,Y87>X87),"通过","2/3级时间无效")))))
A88: VQ-003 | B88: 怎样插回炸篮并启动空气炸锅？ | C88: zh-CN | D88: Air Fryer | E88: operation | F88: development | G88: airfryer-005-scene-0024 | H88: airfryer-005 | I88: 232.694 | J88: 239.199 | K88: items/airfryer-005-scene-0024/clip.mp4 | L88: items/airfryer-005-scene-0024/thumbnail.jpg | M88: ASR: at that nice golden brown toast with a basket of bacon and egg in the middle. VLM: Visual summary: A man in a kitchen is standing behind a black air fryer with its basket partially removed, smiling at the camera. 视觉摘要: 一名男子站在厨房里，面前是一个黑色空气炸锅，其炸篮部分被取出，他正对着镜头微笑。 Visible product: Air Fryer Visible components: black air fryer; air fryer basket; stainless steel refrigerator; white kitchen cabinets; glass jars; knife block; paper towel holder; WHEY protein container Visible actions: man smiling; man holding air fryer basket | N88: 3 | O88: 2 | P88: 232.694 | Q88: 239.199 | R88: The man is holding the air fryer basket, visually indicating the step of handling the basket, which is relevant to inserting it back into the air fryer, though no explicit action of inserting or starting the device is shown. | S88: VLM | T88: low | U88: No explicit action of inserting the basket back or starting the air fryer is visible; only the basket being held is shown. | V88: R1 | W88: 2 | X88: 232.7 | Y88: 239.199 | Z88: no | AA88: Frames at 232.7s-239.2s show the man with the black air fryer basket partially out of the unit, providing partial context for basket re-insertion handling. | AB88: 时间按实际证据片段重定位 | AC88: completed | AD88: 2026-07-28T01:18:39+08:00 | AE88: =IF(AC88<>"completed","",IF(W88=O88,"no","yes")) | AF88: =IF(AC88<>"completed","",IF(AND(X88=P88,Y88=Q88),"no","yes")) | AG88: =IF(AC88<>"completed","待复核",IF(OR(W88="",Z88="",AA88="",AD88=""),"缺少必填项",IF(AND(OR(AE88="yes",AF88="yes"),AB88=""),"修正原因缺失",IF(OR(W88=0,W88=1),IF(AND(X88="",Y88=""),"通过","0/1级时间应留空"),IF(AND(OR(W88=2,W88=3),X88<>"",Y88<>"",X88>=I88,Y88<=J88,Y88>X88),"通过","2/3级时间无效")))))
A89: VQ-003 | B89: 怎样插回炸篮并启动空气炸锅？ | C89: zh-CN | D89: Air Fryer | E89: operation | F89: development | G89: airfryer-011-scene-0001 | H89: airfryer-011 | I89: 0.0 | J89: 107.95 | K89: items/airfryer-011-scene-0001/clip.mp4 | L89: items/airfryer-011-scene-0001/thumbnail.jpg | M89: ASR: Hi, welcome back to Montana, and today we're going to be making another one of my favorite air fryer recipes, grilled cheese. The ingredients are white bread, salted butter, sharp cheddar cheese, and Italian blend cheese. Your first step is to add some of your cheddar into the middle of your bread, and then sprinkle some Italian blend on top. Then butter the exterior of your bread. Put your grilled cheese inside of your air fryer, and then cook for four minutes. Now flip it over and then cook for another three minutes. Now that the three minutes is up, take it out of the air fryer, cut it, and give it a try. OCR: That's Good! WITH MONTANA MONTEREY play! RECREATION NG 5<S HONTEREY BINGA ISUR VF 2000 CA QUAS IONTEREY DECREATION BINCNAE 1SUS VIV ). 2021 ONTREY DECRATION DA REC ONTEREY ECREATION /V 20MON REC MONNEY A RECR TION 202 252 MO DA RE 1S8V 2120 BREC 2n2 MON MONTREYY DA Air Fryer Grilled Cheese 2 slices white bread Sharp Cheddar & Italian Blend Cheeses Salted butter X #showushowyouplayMonterey VLM: Visual summary: A young man in a kitchen prepares to make a grilled cheese sandwich using an air fryer. 视觉摘要: 一名年轻男子在厨房里准备使用空气炸锅制作烤奶酪三明治。 Visible product: Air Fryer Visible components: air fryer; refrigerator; wooden cabinets; countertop; knife block; coffee maker; glass jars; mug; red cutting board; bread; apron Visible actions: man standing; man handling bread | N89: 4 | O89: 1 | R89: The video shows an air fryer being used to cook a grilled cheese sandwich, but does not show the basket being inserted or the appliance being started; the ASR mentions putting the sandwich 'inside of your air fryer' but does not describe inserting the basket or powering on the device. | S89: VLM|ASR|OCR | T89: low | U89: No visual or spoken evidence of inserting the fry basket or starting the air fryer is present. | V89: R1 | W89: 1 | Z89: no | AA89: 画面展示将三明治/炸篮放入机身，但未出现按下启动键、设置程序等启动操作，无法回答'启动'部分。 | AC89: completed | AD89: 2026-07-27T22:01:34+08:00 | AE89: =IF(AC89<>"completed","",IF(W89=O89,"no","yes")) | AF89: =IF(AC89<>"completed","",IF(AND(X89=P89,Y89=Q89),"no","yes")) | AG89: =IF(AC89<>"completed","待复核",IF(OR(W89="",Z89="",AA89="",AD89=""),"缺少必填项",IF(AND(OR(AE89="yes",AF89="yes"),AB89=""),"修正原因缺失",IF(OR(W89=0,W89=1),IF(AND(X89="",Y89=""),"通过","0/1级时间应留空"),IF(AND(OR(W89=2,W89=3),X89<>"",Y89<>"",X89>=I89,Y89<=J89,Y89>X89),"通过","2/3级时间无效")))))
A90: VQ-003 | B90: 怎样插回炸篮并启动空气炸锅？ | C90: zh-CN | D90: Air Fryer | E90: operation | F90: development | G90: airfryer-033-scene-0034 | H90: airfryer-033 | I90: 251.818 | J90: 257.024 | K90: items/airfryer-033-scene-0034/clip.mp4 | L90: items/airfryer-033-scene-0034/thumbnail.jpg | M90: ASR: Ela dispara um relêzinho E é bom desligar Tem hora que ela liga, tem hora que ela não liga Vou ter que desmontar ela todinha VLM: Visual summary: A black air fryer with its top cover removed, revealing internal components, is shown on a white surface. The digital display shows a temperature of 200 degrees. 视觉摘要: 一台黑色空气炸锅，其上盖被移开，露出内部组件，放置在白色表面上。数字显示屏显示温度为200度。 Visible product: Air Fryer Visible components: digital display; temperature reading; control buttons; brand name 'PHILIPS WALITA'; internal heating element; power cord; handle Visible states: top cover removed; digital display active | N90: 5 | O90: 1 | R90: The air fryer is shown with its top cover removed, indicating disassembly, but no action of reinserting the basket or starting the appliance is visible or described. | S90: VLM | T90: low | U90: No evidence of basket reinsertion or appliance startup is present. | V90: R1 | W90: 1 | Z90: no | AA90: 画面为拆机状态，未展示插回炸篮或启动操作。 | AC90: completed | AD90: 2026-07-27T22:23:08+08:00 | AE90: =IF(AC90<>"completed","",IF(W90=O90,"no","yes")) | AF90: =IF(AC90<>"completed","",IF(AND(X90=P90,Y90=Q90),"no","yes")) | AG90: =IF(AC90<>"completed","待复核",IF(OR(W90="",Z90="",AA90="",AD90=""),"缺少必填项",IF(AND(OR(AE90="yes",AF90="yes"),AB90=""),"修正原因缺失",IF(OR(W90=0,W90=1),IF(AND(X90="",Y90=""),"通过","0/1级时间应留空"),IF(AND(OR(W90=2,W90=3),X90<>"",Y90<>"",X90>=I90,Y90<=J90,Y90>X90),"通过","2/3级时间无效")))))
